Workbook

Sheet Cover
B2: SURAKKHA Action - DG ECHO 2026/00158/RQ/01/03
B3: FIVDB - Detailed MEAL Plan & Indicator Performance Tracking Table (IPTT)
B4: Local implementing partner under the technical support of Plan International Bangladesh (PIB)
B6: Action title | C6: Strengthening Integrated EiE, Child Protection, Health & GBV Services for Rohingya Refugees and Host Communities in Cox's Bazar, and Scaling up Multi-Hazard Anticipatory Action (SURAKKHA)
B7: Request number | C7: 2026/00158/RQ/01/03
B8: Action period | C8: 1 June 2026 – 31 May 2028 (24 months / 8 quarters)
B9: Consortium lead | C9: Save the Children International (SC)
B10: Technical supervision of FIVDB | C10: Plan International Bangladesh (PIB)
B11: FIVDB scope | C11: Result 1 – Education in Emergencies (Activities 1-7); Result 2 – Child Protection (Activities 1, 3, 4, 5)
B12: Target camps | C12: Camp 1W, Camp 6, Camp 21, Camp 24 (Cox's Bazar)
B13: FIVDB budget | C13: EUR 592,371.41
B15: Contents
B16: • 1. MEAL Framework, RACI, DCP & Reporting (combined: Framework, RACI Matrix, Data Collection Plan, Reporting Schedule)
B17: • 4. M&E Calendar
B18: • 6. CFM Log Template
B19: • 6b. Collective Feedback
B20: • 6c. Target Breakdown (facility & beneficiary targets by sex/disability)
B21: • 7. IPTT (Indicator Performance Tracking Table)
B22: • 8. Activity Tracker (implementation progress by activity)
B23: • 10. Activity Data Log (per-event data entry, Host/FDMN, sex & age, target/discrepancy)
B24: • 11. Distribution Log (per-item distribution data entry, Host/FDMN, sex & age, ODM/PDM, target/discrepancy)
B25: • 12. Dropout Tracker (learners, staff & volunteers by designation, month-wise trend)
B26: • 12b. Attendance Tracker (learner attendance rate by camp, month-wise under quarter)
... B58: A: Activity Tracker (Sheet 8): RAG compares cumulative ACTUAL (auto, from Sheets 10-11) against cumulative PLANNED (FIVDB's own manual quarterly targets) - On Track >=90%, Slightly Behind 70-89%, Behind <70%. It has nothing to do with the IPTT's indicator-level status.

Sheet 1. MEAL-RACI-DCP-Reporting
B2: 1. MEAL Framework, RACI Matrix, Data Collection Plan & Reporting Schedule
B3: FIVDB delivers Result 1 (Education) and Result 2 Activities 1, 3, 4, 5 (Child Protection) under PIB's technical supervision, within SC's consortium-wide MEAL system. This sheet combines four previously separate sections (Framework, RACI, Data Collection Plan, Reporting Schedule) for a single, continuous read.
B5: 1.1 MEAL Objectives
B6: Objective | C6: Reference
B7: Track FIVDB's contribution to Result 1 and Result 2 indicators against agreed targets, disaggregated by sex, age and disability. | C7: Logframe (Annex I), Result 1 & 2 indicators
B8: Ensure quality, safety and protection-sensitivity of education and case-management/PSS services delivered by FIVDB. | C8: CP Minimum Standards in Humanitarian Settings; Plan Safeguarding Framework
B9: Provide accurate, timely, verifiable data to PIB for consolidation into SC's ECHO interim/final reporting. | C9: Narrative Proposal, reporting obligations section
B10: Maintain a functioning, safe, child-friendly complaints and feedback mechanism (CFM) across all FIVDB camps. | C10: Plan/FIVDB CFM SOP
B11: Generate learning that informs adaptive management of FIVDB's activities across the 24-month action. | C11: MEAL Plan, Section 10 (Learning & Adaptive Management)
B13: 1.2 Guiding Principles
B14: Principle | C14: Reference
B15: Do no harm / child safeguarding is non-negotiable in all data collection involving children. | C15: Plan Safeguarding Framework (Updated Risk Assessment Process, 2024)
B16: Participation: communities (adolescents, parents, CESGs, CBCPCs) are consulted on monitoring design, not only as data sources. | C16: CHS Commitment 4 (participation and feedback)
B17: Triangulation: indicators are, where possible, verified through more than one data source. | C17: IPTT & MEAL Workbook, Sheet 7, Verification/QA Step column
B18: Proportionality: MEAL effort is proportionate to FIVDB's budget share and risk profile within the consortium. | C18: FIVDB Detailed Budget (EUR 592,371.41 total)
B19: Data protection: beneficiary data (esp. CP case data) is stored/shared under SC/PIB's data protection protocol. | C19: SC/PIB Data Protection Protocol
B21: 1.3 MEAL Governance Structure
B22: Level | C22: Responsibility | D22: Reference
B23: FIVDB | C23: Field-level data collection, first-line quality checks, case management, CFM Tier 1, monthly indicator tracker updates. | D23: IPTT & MEAL Workbook, Sheets 7-8
B24: PIB (technical supervision) | C24: Technical quality assurance, monthly data-quality spot checks, consolidation of FIVDB data into EiE_PIB / CP_PIB_V2 tabs, CFM Tier 2 (sensitive/safeguarding) escalation point. | D24: Narrative Proposal, technical supervision arrangements
B25: SC (consortium lead) | C25: Consortium-wide MEAL standards, indicator consolidation across all partners, ECHO interim/final reporting, leads mid-term/final evaluation. | D25: Logframe (Annex I), consortium reporting structure
B27: 1.4 RACI Matrix - FIVDB / PIB / SC
B28: R = Responsible A = Accountable C = Consulted I = Informed
B30: Function | C30: FIVDB | D30: PIB | E30: SC (Lead) | F30: Frequency | G30: Reference
B31: Field data collection (attendance, case files, distributions) | C31: R | D31: C | E31: I | F31: Ongoing/daily | G31: IPTT & MEAL Workbook, Sheets 10-11
B32: Data entry & indicator tracker update | C32: R | D32: A | E32: I | F32: Weekly | G32: IPTT & MEAL Workbook, Sheet 7
B33: Data quality spot-checks / verification visits | C33: C | D33: R | E33: A | F33: Monthly | G33: Field Reporting Templates, Template 7
B34: Indicator consolidation (FIVDB/PIB share) | C34: Input | D34: R | E34: A | F34: Monthly | G34: IPTT & MEAL Workbook, Sheet 7
B35: Consortium indicator consolidation (all partners) | C35: I | D35: Input | E35: R | F35: Quarterly | G35: Logframe (Annex I)
B36: Complaints & feedback handling - Tier 1 (non-sensitive) | C36: R | D36: C | E36: I | F36: Ongoing | G36: MEAL Plan, Section 9 (AAP/CFM)
B37: Complaints & feedback handling - Tier 2 (safeguarding/sensitive) | C37: Escalate | D37: R | E37: A | F37: Within 24-48h | G37: Field Reporting Templates, Template 16
B38: Post-distribution monitoring (PDM) | C38: R | D38: C (QC) | E38: I | F38: Per distribution | G38: IPTT & MEAL Workbook, Sheet 11 (ODM/PDM columns)
B39: Case-management supervision | C39: R (case workers) | D39: R (technical) | E39: A (standards) | F39: Weekly/bi-weekly | G39: CP Minimum Standards, 7-step process
B40: Training delivery & pre/post assessment | C40: R | D40: C | E40: I | F40: Per training | G40: Field Reporting Templates, Template 2
B41: Baseline / KAP survey | C41: Input | D41: R | E41: A | F41: Month 1-2 | G41: MEAL Plan, Section 8 (M&E Calendar)
... B45: Safeguarding incident management | C45: R (first response) | D45: A (escalation) | E45: I | F45: Within 24-48h | G45: Field Reporting Templates, Template 16
B47: 1.5 Data Collection Plan - Tools & Methods
B49: Tool | C49: Purpose | D49: Linked indicator(s) | E49: Responsible | F49: Frequency | G49: Reference
B50: Enrolment/attendance registers (CBLF) | C50: Track learner enrolment, attendance, drop-out | D50: R1-I1, R1-I2, R1-I4, SO-I2 | E50: Facilitators | F50: Daily/weekly | G50: IPTT & MEAL Workbook, Sheet 7
B51: Case management database (CPIMS+ or equivalent) | C51: Track CP case ID, planning, services, closure | D51: R2-I1, R2-I2 | E51: Case workers | F51: Per case, continuous | G51: CP Minimum Standards, 7-step process
B52: Training registers + pre/post-tests | C52: Measure knowledge/skills gained | D52: R1-I5, R1-I7, R2-I3 | E52: MEAL Officer / trainers | F52: Per training | G52: FIVDB Detailed Budget, R1A4/R2A5
B53: Distribution/dispatch records & waybills | C53: Verify materials/kits reached beneficiaries | D53: R1-I3, R1-I4 | E53: Logistics / MEAL Officer | F53: Per distribution | G53: IPTT & MEAL Workbook, Sheet 11
B54: Referral tracker (EiE <-> CP <-> Health) | C54: Track cross-sector referrals & follow-up | D54: R1-I8, R2-I1 | E54: Case workers / facilitators | F54: Ongoing, reviewed weekly | G54: Field Reporting Templates, Template 8
B55: Post-distribution monitoring (PDM) survey | C55: Verify quality, appropriateness, safety of distributions | D55: SO-I1 | E55: MEAL Officer | F55: Within 2-4 weeks of distribution | G55: IPTT & MEAL Workbook, Sheet 11 (PDM columns)
B56: PSS pre/post assessment (IASC domains) | C56: Measure wellbeing/coping change | D56: R2-I4 | E56: Case workers / PSS facilitators | F56: At PSS group entry & exit | G56: IASC Common M&E Framework
B57: Community perception / KAP survey | C57: Measure safety, accountability, satisfaction | D57: SO-I1 | E57: MEAL Officer / PIB | F57: Baseline, midline, endline | G57: MEAL Plan, Section 8 (M&E Calendar)
B58: Facility monitoring checklist | C58: Verify safe-learning standards, environmental activities | D58: R1-I2, R1-I9 | E58: Education Officer | F58: Quarterly | G58: Field Reporting Templates, Template 5
B59: Complaints & Feedback Mechanism (CFM) log | C59: Record, triage, resolve complaints | D59: SO-I1 | E59: MEAL Officer / Safeguarding FP | F59: Ongoing | G59: MEAL Plan, Section 9 (AAP/CFM)
B61: 1.6 Reporting Schedule
B63: Report | C63: Due | D63: Prepared by | E63: Submitted to | F63: Reference
B64: Weekly activity/attendance summary | C64: Weekly | D64: FIVDB field teams | E64: FIVDB Project Manager / PIB | F64: Field Reporting Templates, Template 1
B65: Monthly progress & indicator update | C65: Monthly | D65: FIVDB MEAL Officer | E65: PIB | F65: IPTT & MEAL Workbook, Sheet 7
B66: Quarterly narrative + indicator report | C66: Quarterly | D66: FIVDB Project Manager | E66: PIB -> SC | F66: IPTT & MEAL Workbook, Sheets 7-8
B67: Interim narrative & financial report inputs | C67: Month 12 | D67: FIVDB | E67: PIB -> SC -> DG ECHO | F67: Logframe cover page (action timeline)
B68: Final narrative & financial report inputs | C68: Month 24 | D68: FIVDB | E68: PIB -> SC -> DG ECHO | F68: Logframe cover page (action timeline)
B69: Incident / safeguarding report | C69: Within 24-48h of incident | D69: FIVDB Safeguarding Focal Point | E69: PIB Safeguarding Focal Point | F69: Field Reporting Templates, Template 16

Sheet 4. M&E Calendar
B2: 4. Monitoring & Evaluation Calendar (by month, grouped under quarter)
B3: X = planned activity in that month. Q1 = Jun-Aug 2026 ... Q8 = Mar-May 2028; months are grouped under their quarter. 'Tool Used' cites the actual template/sheet; 'Tool Status' flags where no ready-made instrument exists yet and needs developing. 'Full Process' gives the step-by-step method, Step 1 to last.
B5: Activity | C5: Tool Used | D5: Tool Status | E5: Indicator Reference | F5: Activity Reference | G5: Full Process (Step 1 to last) | H5: Q1 | K5: Q2 | N5: Q3 | Q5: Q4 | T5: Q5 | W5: Q6 | Z5: Q7 | AC5: Q8 | AF5: Notes
H6: 06/2026 | I6: 07/2026 | J6: 08/2026 | K6: 09/2026 | L6: 10/2026 | M6: 11/2026 | N6: 12/2026 | O6: 01/2027 | P6: 02/2027 | Q6: 03/2027 | R6: 04/2027 | S6: 05/2027 | T6: 06/2027 | U6: 07/2027 | V6: 08/2027 | W6: 09/2027 | X6: 10/2027 | Y6: 11/2027 | Z6: 12/2027 | AA6: 01/2028 | AB6: 02/2028 | AC6: 03/2028 | AD6: 04/2028 | AE6: 05/2028
B7: Baseline / KAP survey | C7: Baseline/KAP Survey Questionnaire | D7: Needs development - no ready-made instrument yet in the Field Reporting Templates pack | E7: SO-I1 | F7: INC-6 | G7: Step 1: Design/adapt questionnaire with PIB MEAL. Step 2: Train enumerators. Step 3: Sample households per camp (stratified by sex/age/disability). Step 4: Administer face-to-face (paper or KoBo/ODK). Step 5: Clean and analyse data. Step 6: Share baseline report with PIB. | H7: X | I7: X | J7: X | K7: X | L7: X | M7: X | AF7: Month 1-2 start-up
B8: Monthly indicator tracking | C8: IPTT Data Reporting Form | D8: Needs development - removed from the Field Reporting Templates pack pending redesign (see pack's closing note) | E8: All Sheet 7 indicators | F8: N/A (cross-cutting) | G8: Step 1: Field staff record activity data in source registers. Step 2: MEAL Officer extracts monthly cumulative figures. Step 3: Enter into IPTT Sheet 7 ACTUAL columns. Step 4: Cross-check against Activity Tracker Sheet 8. Step 5: Flag off-track indicators to Project Manager. | H8: X | I8: X | J8: X | K8: X | L8: X | M8: X | N8: X | O8: X | P8: X | Q8: X | R8: X | S8: X | T8: X | U8: X | V8: X | W8: X | X8: X | Y8: X | Z8: X | AA8: X | AB8: X | AC8: X | AD8: X | AE8: X | AF8: Continuous
B9: Quarterly data review (FIVDB-PIB-SC) | C9: IPTT (Sheet 7) + Activity Tracker (Sheet 8) | D9: Exists - this workbook | E9: All indicators | F9: All activities | G9: Step 1: MEAL Officer prepares quarterly extract. Step 2: Joint meeting scheduled with PIB/SC. Step 3: Walk through IPTT % Achieved and Activity Tracker RAG status together. Step 4: Agree corrective actions for off-track items. Step 5: Minute and circulate action points. | H9: X | I9: X | J9: X | K9: X | L9: X | M9: X | N9: X | O9: X | P9: X | Q9: X | R9: X | S9: X | T9: X | U9: X | V9: X | W9: X | X9: X | Y9: X | Z9: X | AA9: X | AB9: X | AC9: X | AD9: X | AE9: X | AF9: Every quarter
B10: Data quality spot-check (PIB) | C10: Data Quality Check / Spot-Check Report | D10: Exists - Field Reporting Templates, Template 7 | E10: All indicators | F10: N/A (cross-cutting) | G10: Step 1: PIB MEAL randomly samples >=10% of source records. Step 2: Verify reported value against source document. Step 3: Record match/discrepancy and root cause. Step 4: Calculate % accuracy. Step 5: Agree corrective action with FIVDB; set follow-up date. | H10: X | I10: X | J10: X | K10: X | L10: X | M10: X | N10: X | O10: X | P10: X | Q10: X | R10: X | S10: X | T10: X | U10: X | V10: X | W10: X | X10: X | Y10: X | Z10: X | AA10: X | AB10: X | AC10: X | AD10: X | AE10: X | AF10: Monthly, reviewed quarterly
B11: Post-distribution monitoring (PDM) | C11: PDM Questionnaire | D11: Needs development - ODM/PDM tracking columns exist (Sheet 11) but no standalone PDM survey instrument yet | E11: SO-I1 | F11: R1A2, R1A3, R2A3 | G11: Step 1: Select random sample of recipients (2-4 weeks post-distribution). Step 2: Contact by phone or in-person. Step 3: Administer PDM questionnaire (quality, appropriateness, safety, satisfaction). Step 4: Record findings in Distribution Log Sheet 11 (PDM Findings). Step 5: Flag issues for follow-up. | H11: X | I11: X | J11: X | K11: X | L11: X | M11: X | N11: X | O11: X | P11: X | Q11: X | R11: X | S11: X | T11: X | U11: X | V11: X | W11: X | X11: X | Y11: X | Z11: X | AA11: X | AB11: X | AC11: X | AD11: X | AE11: X | AF11: Per distribution cycle
B12: Case management supervision & review | C12: CPMS Supervision Checklist | D12: Needs development - referenced against CP Minimum Standards but not yet built as a standalone checklist | E12: R2-I1, R2-I5 | F12: R2A1 | G12: Step 1: PIB technical supervisor reviews case files. Step 2: Individual/group supervision session with case workers. Step 3: Score against CPMS supervision checklist. Step 4: Identify coaching needs. Step 5: Record in supervision log; follow up at next session. | H12: X | I12: X | J12: X | K12: X | L12: X | M12: X | N12: X | O12: X | P12: X | Q12: X | R12: X | S12: X | T12: X | U12: X | V12: X | W12: X | X12: X | Y12: X | Z12: X | AA12: X | AB12: X | AC12: X | AD12: X | AE12: X | AF12: Weekly/bi-weekly
B13: Facility monitoring checklist | C13: Monitoring Visit Checklist | D13: Exists - Field Reporting Templates, Template 5 | E13: R1-I2, R1-I9, R2-I4 | F13: R1A2, R2A3 | G13: Step 1: Joint FIVDB-PIB site visit scheduled. Step 2: Complete the relevant Template 5 section (by visit type). Step 3: Record observations and photographic evidence. Step 4: Complete Monitoring Visit Report (Template 4). Step 5: Share findings and agree action points. | K13: X | L13: X | M13: X | Q13: X | R13: X | S13: X | W13: X | X13: X | Y13: X | AC13: X | AD13: X | AE13: X | AF13: Quarterly
B14: Mid-term review contribution | C14: IPTT extract + case examples | D14: Exists - this workbook + Field Reporting Templates, Template 10 | E14: All indicators | F14: All activities | G14: Step 1: Compile camp-level data from IPTT/Activity Tracker. Step 2: Self-assess progress against targets. Step 3: Compile illustrative case examples (Template 10). Step 4: Submit to PIB/SC ahead of the review. Step 5: Participate in KIIs/FGDs. | Q14: X | R14: X | S14: X | AF14: Month 12
B15: Interim ECHO report data package | C15: IPTT extract | D15: Exists - this workbook | E15: All indicators | F15: All activities | G15: Step 1: MEAL Officer compiles IPTT extract. Step 2: Draft narrative highlights. Step 3: Compile supporting evidence. Step 4: PIB validates. Step 5: Submit to SC. | Q15: X | R15: X | S15: X | AF15: Month 12
B16: Community perception / KAP midline | C16: Community Perception Survey | D16: Needs development - no standalone instrument yet, to mirror the baseline tool once built | E16: SO-I1 | F16: INC-6 | G16: Step 1: Repeat baseline sampling approach. Step 2: Administer same/comparable questionnaire. Step 3: Analyse and compare to baseline. Step 4: Share midline report with PIB. | Q16: X | R16: X | S16: X | AF16: Month 12
B17: Final evaluation contribution | C17: IPTT extract + KII/FGD participation | D17: Exists - this workbook | E17: All indicators | F17: All activities | G17: Step 1: Support SC/PIB-led evaluators with data access. Step 2: Participate in KIIs/FGDs. Step 3: Verify final indicator values. Step 4: Review draft evaluation findings. | AC17: X | AD17: X | AE17: X | AF17: Month 22-24
B18: Endline KAP survey | C18: Baseline/KAP Survey Questionnaire (repeat) | D18: Needs development - same instrument as baseline, once built | E18: SO-I1 | F18: INC-6 | G18: Step 1: Repeat baseline/midline methodology. Step 2: Administer at project close. Step 3: Compare results against baseline and midline. Step 4: Share endline report. | AC18: X | AD18: X | AE18: X | AF18: Month 22-23
B19: Final ECHO report data package | C19: IPTT extract | D19: Exists - this workbook | E19: All indicators | F19: All activities | G19: Step 1: Compile final IPTT extract for the full 24-month period. Step 2: Draft narrative. Step 3: Compile evidence. Step 4: PIB validates. Step 5: Submit to SC. | AC19: X | AD19: X | AE19: X | AF19: Month 24
B20: Sustainability / handover review | C20: Workshop discussion (no fixed instrument) | D20: Not applicable - facilitated discussion, no data-collection tool needed | E20: SO-I1 | F20: CLOSE | G20: Step 1: Joint FIVDB-PIB-SC workshop scheduled. Step 2: Document lessons learned. Step 3: Agree handover/sustainability arrangements for CESGs, CBCPCs, MPCACs, adolescent clubs. Step 4: Circulate handover plan. | AC20: X | AD20: X | AE20: X | AF20: Month 22-24

Sheet 5b. Dashboard
B2: Dashboard - Program, MEAL, Management & Finance Summary
B3: Live summary pulled automatically from the IPTT (Sheet 7), Activity Tracker (Sheet 8), Budget Tracker (Sheet 13), Activity Data Log (Sheet 10) and Distribution Log (Sheet 11). Nothing on this sheet is entered manually - update the current reporting quarter on the IPTT sheet and everything below recalculates.
B5: Current Reporting Quarter | D5: Overall Budget Utilised | F5: Avg. Physical Progress (all activities) | H5: Total Data Log Entries (Sheets 10+11)
B6: ='7. IPTT'!$C$3 -> 1 | D6: =IFERROR('13. Budget Tracker'!AD21/'13. Budget Tracker'!D21,"") -> 0 | F6: =IFERROR(AVERAGE('8. Activity Tracker'!AD7:AD93),"") | H6: =COUNTA('10. Activity Data Log'!$C$7:$C$46)+COUNTA('11. Distribution Log'!$C$7:$C$46) -> 0
B8: ACTION NEEDED - What requires attention right now
B9: Consolidated from every section below, so decision-makers see what needs attention without reading the whole sheet.
B11: Area | E11: Alert | I11: Count
B12: Activities | E12: Sub-activities marked 'Behind' (Sheet 8) | I12: =COUNTIF('8. Activity Tracker'!AE7:AE93,"Behind") -> 0
B13: Indicators | E13: Indicators 'At Risk' (<70% of expected pace, Sheet 7) | I13: =COUNTIFS('7. IPTT'!$W$15:$W$37,"<0.7",'7. IPTT'!$W$15:$W$37,"<>") -> 8
B14: Budget | E14: Lines at Overspend Risk (>110% utilised, Sheet 13c) | I14: =COUNTIF('13c. Budget - Yearly & Total'!$H$6:$H$19,">1.1") -> 0
B15: CFM | E15: Category 5/6 safeguarding/PSEA/fraud/security concerns logged | I15: =SUMPRODUCT(ISNUMBER(SEARCH("5.",'6. CFM Log Template'!$U$7:$U$46))*1)+SUMPRODUCT(ISNUMBER(SEARCH("6.",'6. CFM Log Template'!$U$7:$U$46))*1) -> 0
B16: Data Quality | E16: Activity Data Log rows missing Event Date (breaks the auto-link) | I16: =SUMPRODUCT(('10. Activity Data Log'!$F$7:$F$46="")*('10. Activity Data Log'!$U$7:$U$46>0)) -> 0
B18: For Management - Implementation Status
B19: RAG status distribution across all 75 sub-activities (Activity Tracker, Sheet 8), based on cumulative % Physical Progress vs plan.
B21: On Track | D21: Slightly Behind | F21: Behind | H21: No data yet
B22: =COUNTIF('8. Activity Tracker'!AE7:AE93,"On Track") -> 0 | D22: =COUNTIF('8. Activity Tracker'!AE7:AE93,"Slightly Behind") -> 0 | F22: =COUNTIF('8. Activity Tracker'!AE7:AE93,"Behind") -> 0 | H22: =COUNTIF('8. Activity Tracker'!AE7:AE93,"No data yet") -> 75
B24: 'Behind' activities need management attention - filter the Activity Tracker's RAG Status column (Sheet 8) directly to see which ones.
B26: For MEAL - Indicator Achievement
B27: % of LOP Target Achieved, averaged by Result (IPTT, Sheet 7). Indicator count classified: On Track (>=90% of expected pace), Watch (70-89%), At Risk (<70%).
B29: Result | D29: Avg % of LOP Target Achieved | F29: Indicators On Track | H29: Indicators Watch | J29: Indicators At Risk
B30: Result 1 (Education) | D30: =IFERROR(AVERAGEIF('7. IPTT'!$B$15:$B$37,"Result 1*",'7. IPTT'!$W$15:$W$37),"") -> 0 | F30: =COUNTIFS('7. IPTT'!$B$15:$B$37,"Result 1*",'7. IPTT'!$W$15:$W$37,">=0.9") -> 0 | H30: =COUNTIFS('7. IPTT'!$B$15:$B$37,"Result 1*",'7. IPTT'!$W$15:$W$37,">=0.7",'7. IPTT'!$W$15:$W$37,"<0.9") -> 0 | J30: =COUNTIFS('7. IPTT'!$B$15:$B$37,"Result 1*",'7. IPTT'!$W$15:$W$37,"<0.7") -> 8
B31: Result 2 (Protection) | D31: =IFERROR(AVERAGEIF('7. IPTT'!$B$15:$B$37,"Result 2*",'7. IPTT'!$W$15:$W$37),"") | F31: =COUNTIFS('7. IPTT'!$B$15:$B$37,"Result 2*",'7. IPTT'!$W$15:$W$37,">=0.9") -> 0 | H31: =COUNTIFS('7. IPTT'!$B$15:$B$37,"Result 2*",'7. IPTT'!$W$15:$W$37,">=0.7",'7. IPTT'!$W$15:$W$37,"<0.9") -> 0 | J31: =COUNTIFS('7. IPTT'!$B$15:$B$37,"Result 2*",'7. IPTT'!$W$15:$W$37,"<0.7") -> 0
B32: Specific Objective | D32: =IFERROR(AVERAGEIF('7. IPTT'!$B$15:$B$37,"Specific Objective Indicator*",'7. IPTT'!$W$15:$W$37),"") | F32: =COUNTIFS('7. IPTT'!$B$15:$B$37,"Specific Objective Indicator*",'7. IPTT'!$W$15:$W$37,">=0.9") -> 0 | H32: =COUNTIFS('7. IPTT'!$B$15:$B$37,"Specific Objective Indicator*",'7. IPTT'!$W$15:$W$37,">=0.7",'7. IPTT'!$W$15:$W$37,"<0.9") -> 0 | J32: =COUNTIFS('7. IPTT'!$B$15:$B$37,"Specific Objective Indicator*",'7. IPTT'!$W$15:$W$37,"<0.7") -> 0
B34: Data collection volume (Sheets 10-11) and retention (Sheet 12) are tracked on their own sheets - see Activity Data Log, Distribution Log, and Dropout Tracker directly for full detail.
B36: For Program Staff - This Quarter's Delivery
B37: Focused on what's due this quarter and what needs catching up - planned vs actually logged, current reporting quarter only.
B39: Metric | G39: Value
B40: Sub-activities with a target planned this quarter | G40: =SUMPRODUCT((COLUMN('8. Activity Tracker'!N7:U93)-COLUMN('8. Activity Tracker'!N7)+1=('7. IPTT'!$C$3))*(N('8. Activity Tracker'!N7:U93)>0)) -> 0
B41: Sub-activities marked 'Behind' (need catch-up) | G41: =COUNTIF('8. Activity Tracker'!AE7:AE93,"Behind") -> 0
B42: Events/sessions logged this quarter (Sheet 10) | G42: =COUNTIF('10. Activity Data Log'!$AD$7:$AD$46,"Q"&'7. IPTT'!$C$3) -> 0
B43: Distributions logged this quarter (Sheet 11) | G43: =COUNTIF('11. Distribution Log'!$AI$7:$AI$46,"Q"&'7. IPTT'!$C$3) -> 0
B44: Participants reached this quarter (Sheet 10, Total Participants) | G44: =SUMIF('10. Activity Data Log'!$AD$7:$AD$46,"Q"&'7. IPTT'!$C$3,'10. Activity Data Log'!$U$7:$U$46) -> 0
B45: Recipients reached this quarter (Sheet 11, Total Recipients) | G45: =SUMIF('11. Distribution Log'!$AI$7:$AI$46,"Q"&'7. IPTT'!$C$3,'11. Distribution Log'!$W$7:$W$46) -> 0
B47: For Finance - Budget Utilisation
B48: From the Budget Tracker (Sheet 13). Utilisation = cumulative spend to date / approved budget, per line.
B50: Metric | E50: Value
B51: Total Approved Budget (EUR) | E51: ='13. Budget Tracker'!E21 -> 592371.41
B52: Total Spent to Date (EUR) | E52: =IFERROR('13. Budget Tracker'!AD21/143,"") -> 0
B53: Overall Utilisation % | E53: =IFERROR('13. Budget Tracker'!AD21/'13. Budget Tracker'!D21,"") -> 0
B54: Budget Lines - Underspend Risk | E54: =COUNTIF('13c. Budget - Yearly & Total'!$H$6:$H$19,"<0.7") -> 13
B55: Budget Lines - On Track | E55: =COUNTIFS('13c. Budget - Yearly & Total'!$H$6:$H$19,">=0.7",'13c. Budget - Yearly & Total'!$H$6:$H$19,"<=1.1") -> 0
B56: Budget Lines - Overspend Risk | E56: =COUNTIF('13c. Budget - Yearly & Total'!$H$6:$H$19,">1.1") -> 0
B57: Activity & Distribution - Male / Female Breakdown
B58: Sums Host + FDMN across all logged rows (Activity Data Log, Sheet 10; Distribution Log, Sheet 11). Male = Boys <18 + Male 18+; Female = Girls <18 + Female 18+, per each sheet's own sex/age columns.
B60: Source | E60: Male | G60: Female | I60: Total
B61: Activity Data Log (Sheet 10) | E61: =SUM('10. Activity Data Log'!M7:M46,'10. Activity Data Log'!N7:N46,'10. Activity Data Log'!Q7:Q46,'10. Activity Data Log'!R7:R46) -> 0 | G61: =SUM('10. Activity Data Log'!O7:O46,'10. Activity Data Log'!P7:P46,'10. Activity Data Log'!S7:S46,'10. Activity Data Log'!T7:T46) -> 0 | I61: =E61+G61 -> 0
B62: Distribution Log (Sheet 11) | E62: =SUM('11. Distribution Log'!O7:O46,'11. Distribution Log'!P7:P46,'11. Distribution Log'!S7:S46,'11. Distribution Log'!T7:T46) -> 0 | G62: =SUM('11. Distribution Log'!Q7:Q46,'11. Distribution Log'!R7:R46,'11. Distribution Log'!U7:U46,'11. Distribution Log'!V7:V46) -> 0 | I62: =E62+G62 -> 0
B63: TOTAL (Activity + Distribution) | E63: =SUM(E61:F62) -> 0 | G63: =SUM(G61:H62) -> 0 | I63: =E63+G63 -> 0
B65: Indicator-by-Indicator Detail (all 17 indicators)
B66: Every indicator individually, not just Result-level averages - pulled live from IPTT (Sheet 7). Status: On Track >=90% of expected pace, Watch 70-89%, At Risk <70%, No data yet if blank.
B68: Code | D68: Indicator | H68: Unit | I68: Cumulative Actual | J68: LOP Target | K68: % Achieved / Status
B69: ='7. IPTT'!$C$16 -> R1-I1 | D69: ='7. IPTT'!$F$16 -> Number of targeted girls and boys enrolled in non-formal education services | H69: ='7. IPTT'!$N$16 -> Number | I69: =IFERROR(LOOKUP(2,1/('7. IPTT'!$O$16:$V$16<>""),'7. IPTT'!$O$16:$V$16),"") -> 0 | J69: =IF('7. IPTT'!$M$16="N/A","N/A",'7. IPTT'!$M$16) -> 1224 | K69: =IF('7. IPTT'!$W$16="","No data yet",IF('7. IPTT'!$W$16>=0.9,TEXT('7. IPTT'!$W$16,"0%")&" - On Track",IF('7. IPTT'!$W$16>=0.7,TEXT('7. IPTT'!$W$16,"0%")&" - Watch",TEXT('7. IPTT'!$W$16,"0%")&" - At Risk"))) -> 0% - At Risk
B70: ='7. IPTT'!$C$17 -> R1-I2 | D70: ='7. IPTT'!$F$17 -> Number of learning spaces established or restored to minimum standards for safe learning | H70: ='7. IPTT'!$N$17 -> Number | I70: =IFERROR(LOOKUP(2,1/('7. IPTT'!$O$17:$V$17<>""),'7. IPTT'!$O$17:$V$17),"") -> 0 | J70: =IF('7. IPTT'!$M$17="N/A","N/A",'7. IPTT'!$M$17) -> 51 | K70: =IF('7. IPTT'!$W$17="","No data yet",IF('7. IPTT'!$W$17>=0.9,TEXT('7. IPTT'!$W$17,"0%")&" - On Track",IF('7. IPTT'!$W$17>=0.7,TEXT('7. IPTT'!$W$17,"0%")&" - Watch",TEXT('7. IPTT'!$W$17,"0%")&" - At Risk"))) -> 0% - At Risk
B71: ='7. IPTT'!$C$18 -> R1-I3 | D71: ='7. IPTT'!$F$18 -> Number of teachers provided with teaching aids/materials | H71: ='7. IPTT'!$N$18 -> Number | I71: =IFERROR(LOOKUP(2,1/('7. IPTT'!$O$18:$V$18<>""),'7. IPTT'!$O$18:$V$18),"") -> 0 | J71: =IF('7. IPTT'!$M$18="N/A","N/A",'7. IPTT'!$M$18) -> 68 | K71: =IF('7. IPTT'!$W$18="","No data yet",IF('7. IPTT'!$W$18>=0.9,TEXT('7. IPTT'!$W$18,"0%")&" - On Track",IF('7. IPTT'!$W$18>=0.7,TEXT('7. IPTT'!$W$18,"0%")&" - Watch",TEXT('7. IPTT'!$W$18,"0%")&" - At Risk"))) -> 0% - At Risk
B72: ='7. IPTT'!$C$19 -> R1-I4 | D72: ='7. IPTT'!$F$19 -> Number of girls and boys provided with learning materials | H72: ='7. IPTT'!$N$19 -> Number | I72: =IFERROR(LOOKUP(2,1/('7. IPTT'!$O$19:$V$19<>""),'7. IPTT'!$O$19:$V$19),"") -> 0 | J72: =IF('7. IPTT'!$M$19="N/A","N/A",'7. IPTT'!$M$19) -> 1224 | K72: =IF('7. IPTT'!$W$19="","No data yet",IF('7. IPTT'!$W$19>=0.9,TEXT('7. IPTT'!$W$19,"0%")&" - On Track",IF('7. IPTT'!$W$19>=0.7,TEXT('7. IPTT'!$W$19,"0%")&" - Watch",TEXT('7. IPTT'!$W$19,"0%")&" - At Risk"))) -> 0% - At Risk
B73: ='7. IPTT'!$C$20 -> R1-I5 | D73: ='7. IPTT'!$F$20 -> Number of teachers/education personnel showing increased knowledge and teaching skills to address children's learning needs | H73: ='7. IPTT'!$N$20 -> Number | I73: =IFERROR(LOOKUP(2,1/('7. IPTT'!$O$20:$V$20<>""),'7. IPTT'!$O$20:$V$20),"") -> 0 | J73: =IF('7. IPTT'!$M$20="N/A","N/A",'7. IPTT'!$M$20) -> 68 | K73: =IF('7. IPTT'!$W$20="","No data yet",IF('7. IPTT'!$W$20>=0.9,TEXT('7. IPTT'!$W$20,"0%")&" - On Track",IF('7. IPTT'!$W$20>=0.7,TEXT('7. IPTT'!$W$20,"0%")&" - Watch",TEXT('7. IPTT'!$W$20,"0%")&" - At Risk"))) -> 0% - At Risk
B74: ='7. IPTT'!$C$21 -> R1-I6 | D74: ='7. IPTT'!$F$21 -> Number of students, teachers and other education personnel provided with psycho-social support services | H74: ='7. IPTT'!$N$21 -> Number | I74: =IFERROR(LOOKUP(2,1/('7. IPTT'!$O$21:$V$21<>""),'7. IPTT'!$O$21:$V$21),"") -> 0 | J74: =IF('7. IPTT'!$M$21="N/A","N/A",'7. IPTT'!$M$21) -> 2516 | K74: =IF('7. IPTT'!$W$21="","No data yet",IF('7. IPTT'!$W$21>=0.9,TEXT('7. IPTT'!$W$21,"0%")&" - On Track",IF('7. IPTT'!$W$21>=0.7,TEXT('7. IPTT'!$W$21,"0%")&" - Watch",TEXT('7. IPTT'!$W$21,"0%")&" - At Risk"))) -> 0% - At Risk
B75: ='7. IPTT'!$C$22 -> R1-I7 | D75: ='7. IPTT'!$F$22 -> Number of teachers and other education personnel showing increased knowledge and skills to address the protection needs of girls and boys | H75: ='7. IPTT'!$N$22 -> Number | I75: =IFERROR(LOOKUP(2,1/('7. IPTT'!$O$22:$V$22<>""),'7. IPTT'!$O$22:$V$22),"") -> 0 | J75: =IF('7. IPTT'!$M$22="N/A","N/A",'7. IPTT'!$M$22) -> 68 | K75: =IF('7. IPTT'!$W$22="","No data yet",IF('7. IPTT'!$W$22>=0.9,TEXT('7. IPTT'!$W$22,"0%")&" - On Track",IF('7. IPTT'!$W$22>=0.7,TEXT('7. IPTT'!$W$22,"0%")&" - Watch",TEXT('7. IPTT'!$W$22,"0%")&" - At Risk"))) -> 0% - At Risk
B76: ='7. IPTT'!$C$23 -> R1-I8 | D76: ='7. IPTT'!$F$23 -> Number of girls and boys referred to specialised services (e.g. child protection, health, MHPSS) | H76: ='7. IPTT'!$N$23 -> Number | I76: =IFERROR(LOOKUP(2,1/('7. IPTT'!$O$23:$V$23<>""),'7. IPTT'!$O$23:$V$23),"") -> 0 | J76: =IF('7. IPTT'!$M$23="N/A","N/A",'7. IPTT'!$M$23) -> 122 | K76: =IF('7. IPTT'!$W$23="","No data yet",IF('7. IPTT'!$W$23>=0.9,TEXT('7. IPTT'!$W$23,"0%")&" - On Track",IF('7. IPTT'!$W$23>=0.7,TEXT('7. IPTT'!$W$23,"0%")&" - Watch",TEXT('7. IPTT'!$W$23,"0%")&" - At Risk"))) -> 0% - At Risk
B77: ='7. IPTT'!$C$24 -> R1-I9 | D77: ='7. IPTT'!$F$24 -> % educational facilities that are carrying out environmental and climate friendly activities day-to-day | H77: ='7. IPTT'!$N$24 -> % | I77: =IFERROR(LOOKUP(2,1/('7. IPTT'!$O$24:$V$24<>""),'7. IPTT'!$O$24:$V$24),"") | J77: =IF('7. IPTT'!$M$24="N/A","N/A",'7. IPTT'!$M$24) -> 0.65 | K77: =IF('7. IPTT'!$W$24="","No data yet",IF('7. IPTT'!$W$24>=0.9,TEXT('7. IPTT'!$W$24,"0%")&" - On Track",IF('7. IPTT'!$W$24>=0.7,TEXT('7. IPTT'!$W$24,"0%")&" - Watch",TEXT('7. IPTT'!$W$24,"0%")&" - At Risk"))) -> No data yet
B78: ='7. IPTT'!$C$26 -> R2-I1 | D78: ='7. IPTT'!$F$26 -> (MANDATORY) % of children and caregivers whose urgent child protection needs/risks have been addressed through the case management process | H78: ='7. IPTT'!$N$26 -> % | I78: =IFERROR(LOOKUP(2,1/('7. IPTT'!$O$26:$V$26<>""),'7. IPTT'!$O$26:$V$26),"") | J78: =IF('7. IPTT'!$M$26="N/A","N/A",'7. IPTT'!$M$26) -> 0.95 | K78: =IF('7. IPTT'!$W$26="","No data yet",IF('7. IPTT'!$W$26>=0.9,TEXT('7. IPTT'!$W$26,"0%")&" - On Track",IF('7. IPTT'!$W$26>=0.7,TEXT('7. IPTT'!$W$26,"0%")&" - Watch",TEXT('7. IPTT'!$W$26,"0%")&" - At Risk"))) -> No data yet
B79: ='7. IPTT'!$C$27 -> R2-I2 | D79: ='7. IPTT'!$F$27 -> % of children separated from or allegedly associated with armed groups and armed forces who benefit from appropriate care and services | H79: ='7. IPTT'!$N$27 -> % | I79: =IFERROR(LOOKUP(2,1/('7. IPTT'!$O$27:$V$27<>""),'7. IPTT'!$O$27:$V$27),"") | J79: =IF('7. IPTT'!$M$27="N/A","N/A",'7. IPTT'!$M$27) -> 0.8 | K79: =IF('7. IPTT'!$W$27="","No data yet",IF('7. IPTT'!$W$27>=0.9,TEXT('7. IPTT'!$W$27,"0%")&" - On Track",IF('7. IPTT'!$W$27>=0.7,TEXT('7. IPTT'!$W$27,"0%")&" - Watch",TEXT('7. IPTT'!$W$27,"0%")&" - At Risk"))) -> No data yet
B80: ='7. IPTT'!$C$28 -> R2-I3 | D80: ='7. IPTT'!$F$28 -> Average % knowledge increase amongst participants on the protection subject in focus | H80: ='7. IPTT'!$N$28 -> % | I80: =IFERROR(LOOKUP(2,1/('7. IPTT'!$O$28:$V$28<>""),'7. IPTT'!$O$28:$V$28),"") | J80: =IF('7. IPTT'!$M$28="N/A","N/A",'7. IPTT'!$M$28) -> 0.8 | K80: =IF('7. IPTT'!$W$28="","No data yet",IF('7. IPTT'!$W$28>=0.9,TEXT('7. IPTT'!$W$28,"0%")&" - On Track",IF('7. IPTT'!$W$28>=0.7,TEXT('7. IPTT'!$W$28,"0%")&" - Watch",TEXT('7. IPTT'!$W$28,"0%")&" - At Risk"))) -> No data yet
B81: ='7. IPTT'!$C$29 -> R2-I4 | D81: ='7. IPTT'!$F$29 -> (MANDATORY) % of persons who receive appropriate PSS reporting improved mental health and psychosocial well-being OR capacities to cope | H81: ='7. IPTT'!$N$29 -> % | I81: =IFERROR(LOOKUP(2,1/('7. IPTT'!$O$29:$V$29<>""),'7. IPTT'!$O$29:$V$29),"") | J81: =IF('7. IPTT'!$M$29="N/A","N/A",'7. IPTT'!$M$29) -> 0.8 | K81: =IF('7. IPTT'!$W$29="","No data yet",IF('7. IPTT'!$W$29>=0.9,TEXT('7. IPTT'!$W$29,"0%")&" - On Track",IF('7. IPTT'!$W$29>=0.7,TEXT('7. IPTT'!$W$29,"0%")&" - Watch",TEXT('7. IPTT'!$W$29,"0%")&" - At Risk"))) -> No data yet
B82: ='7. IPTT'!$C$30 -> R2-I5 | D82: ='7. IPTT'!$F$30 -> % of caseworkers whose knowledge assessment score is at least 70% | H82: ='7. IPTT'!$N$30 -> % | I82: =IFERROR(LOOKUP(2,1/('7. IPTT'!$O$30:$V$30<>""),'7. IPTT'!$O$30:$V$30),"") | J82: =IF('7. IPTT'!$M$30="N/A","N/A",'7. IPTT'!$M$30) -> 0.75 | K82: =IF('7. IPTT'!$W$30="","No data yet",IF('7. IPTT'!$W$30>=0.9,TEXT('7. IPTT'!$W$30,"0%")&" - On Track",IF('7. IPTT'!$W$30>=0.7,TEXT('7. IPTT'!$W$30,"0%")&" - Watch",TEXT('7. IPTT'!$W$30,"0%")&" - At Risk"))) -> No data yet
B83: ='7. IPTT'!$C$32 -> R2-Ref1 | D83: ='7. IPTT'!$F$32 -> (MANDATORY) Number of minimum standards for care for survivors achieved | H83: ='7. IPTT'!$N$32 -> Number | I83: =IFERROR(LOOKUP(2,1/('7. IPTT'!$O$32:$V$32<>""),'7. IPTT'!$O$32:$V$32),"") -> 0 | J83: =IF('7. IPTT'!$M$32="N/A","N/A",'7. IPTT'!$M$32) -> N/A | K83: =IF('7. IPTT'!$W$32="","No data yet",IF('7. IPTT'!$W$32>=0.9,TEXT('7. IPTT'!$W$32,"0%")&" - On Track",IF('7. IPTT'!$W$32>=0.7,TEXT('7. IPTT'!$W$32,"0%")&" - Watch",TEXT('7. IPTT'!$W$32,"0%")&" - At Risk"))) -> N/A - On Track
B84: ='7. IPTT'!$C$33 -> R2-Ref2 | D84: ='7. IPTT'!$F$33 -> Number of individuals benefiting from GBV response services (SC-led, R2-A2) | H84: ='7. IPTT'!$N$33 -> % | I84: =IFERROR(LOOKUP(2,1/('7. IPTT'!$O$33:$V$33<>""),'7. IPTT'!$O$33:$V$33),"") -> N/A | J84: =IF('7. IPTT'!$M$33="N/A","N/A",'7. IPTT'!$M$33) -> N/A | K84: =IF('7. IPTT'!$W$33="","No data yet",IF('7. IPTT'!$W$33>=0.9,TEXT('7. IPTT'!$W$33,"0%")&" - On Track",IF('7. IPTT'!$W$33>=0.7,TEXT('7. IPTT'!$W$33,"0%")&" - Watch",TEXT('7. IPTT'!$W$33,"0%")&" - At Risk"))) -> N/A - On Track
B85: ='7. IPTT'!$C$34 -> R2-Ref3 | D85: ='7. IPTT'!$F$34 -> % of GBV high-risk cases supervised (SC-led, R2-A2) | H85: ='7. IPTT'!$N$34 -> % | I85: =IFERROR(LOOKUP(2,1/('7. IPTT'!$O$34:$V$34<>""),'7. IPTT'!$O$34:$V$34),"") -> N/A | J85: =IF('7. IPTT'!$M$34="N/A","N/A",'7. IPTT'!$M$34) -> N/A | K85: =IF('7. IPTT'!$W$34="","No data yet",IF('7. IPTT'!$W$34>=0.9,TEXT('7. IPTT'!$W$34,"0%")&" - On Track",IF('7. IPTT'!$W$34>=0.7,TEXT('7. IPTT'!$W$34,"0%")&" - Watch",TEXT('7. IPTT'!$W$34,"0%")&" - At Risk"))) -> N/A - On Track
B86: ='7. IPTT'!$C$36 -> SO-I1 | D86: ='7. IPTT'!$F$36 -> % of beneficiaries reporting that humanitarian assistance is delivered in a safe, accessible, accountable and participatory manner | H86: ='7. IPTT'!$N$36 -> % | I86: =IFERROR(LOOKUP(2,1/('7. IPTT'!$O$36:$V$36<>""),'7. IPTT'!$O$36:$V$36),"") | J86: =IF('7. IPTT'!$M$36="N/A","N/A",'7. IPTT'!$M$36) -> 0.85 | K86: =IF('7. IPTT'!$W$36="","No data yet",IF('7. IPTT'!$W$36>=0.9,TEXT('7. IPTT'!$W$36,"0%")&" - On Track",IF('7. IPTT'!$W$36>=0.7,TEXT('7. IPTT'!$W$36,"0%")&" - Watch",TEXT('7. IPTT'!$W$36,"0%")&" - At Risk"))) -> No data yet
B87: ='7. IPTT'!$C$37 -> SO-I2 | D87: ='7. IPTT'!$F$37 -> % targeted girls and boys who are retained in education at the end of the action | H87: ='7. IPTT'!$N$37 -> % | I87: =IFERROR(LOOKUP(2,1/('7. IPTT'!$O$37:$V$37<>""),'7. IPTT'!$O$37:$V$37),"") | J87: =IF('7. IPTT'!$M$37="N/A","N/A",'7. IPTT'!$M$37) -> 0.9 | K87: =IF('7. IPTT'!$W$37="","No data yet",IF('7. IPTT'!$W$37>=0.9,TEXT('7. IPTT'!$W$37,"0%")&" - On Track",IF('7. IPTT'!$W$37>=0.7,TEXT('7. IPTT'!$W$37,"0%")&" - Watch",TEXT('7. IPTT'!$W$37,"0%")&" - At Risk"))) -> No data yet
B89: Budget Line-by-Line Detail (all 14 lines)
B90: Every budget line individually, pulled live from the Budget Tracker (Sheet 13c, Yearly & Total). Status: On Track 70-110% utilisation for time elapsed, Underspend Risk <70%, Overspend Risk >110%.
B92: Budget Line | E92: Approved (EUR) | G92: Spent to Date (EUR) | I92: % Utilised | J92: Status
B93: ='13c. Budget - Yearly & Total'!$C$6 -> Identification, assessment and appropriate placement of out-of-school and dropout children, incl. disability screening (min. 3% target) | E93: ='13c. Budget - Yearly & Total'!$E$6+'13c. Budget - Yearly & Total'!$F$6 -> 0 | G93: ='13c. Budget - Yearly & Total'!$G$6 -> 0 | I93: ='13c. Budget - Yearly & Total'!$H$6 -> 0 | J93: =IF('13c. Budget - Yearly & Total'!$H$6>1.1,"Overspend Risk",IF('13c. Budget - Yearly & Total'!$H$6<0.7,"Underspend Risk","On Track")) -> Underspend Risk
B94: ='13c. Budget - Yearly & Total'!$C$7 -> Education Service Delivery Support: learning materials, teaching-volunteer incentives, CBLF minimum package, solar/fire safety, maintenance, assistive devices | E94: ='13c. Budget - Yearly & Total'!$E$7+'13c. Budget - Yearly & Total'!$F$7 -> 0 | G94: ='13c. Budget - Yearly & Total'!$G$7 -> 0 | I94: ='13c. Budget - Yearly & Total'!$H$7 -> 0 | J94: =IF('13c. Budget - Yearly & Total'!$H$7>1.1,"Overspend Risk",IF('13c. Budget - Yearly & Total'!$H$7<0.7,"Underspend Risk","On Track")) -> Underspend Risk
B95: ='13c. Budget - Yearly & Total'!$C$8 -> Gender-Appropriate Dignity Kits and MHM Support for adolescent girls | E95: ='13c. Budget - Yearly & Total'!$E$8+'13c. Budget - Yearly & Total'!$F$8 -> 0 | G95: ='13c. Budget - Yearly & Total'!$G$8 -> 0 | I95: ='13c. Budget - Yearly & Total'!$H$8 -> 0 | J95: =IF('13c. Budget - Yearly & Total'!$H$8>1.1,"Overspend Risk",IF('13c. Budget - Yearly & Total'!$H$8<0.7,"Underspend Risk","On Track")) -> Underspend Risk
B96: ='13c. Budget - Yearly & Total'!$C$9 -> Strengthening Technical/Operational Capacities of Staff, Teaching Volunteers and Consortium Partners | E96: ='13c. Budget - Yearly & Total'!$E$9+'13c. Budget - Yearly & Total'!$F$9 -> 0 | G96: ='13c. Budget - Yearly & Total'!$G$9 -> 0 | I96: ='13c. Budget - Yearly & Total'!$H$9 -> 0 | J96: =IF('13c. Budget - Yearly & Total'!$H$9>1.1,"Overspend Risk",IF('13c. Budget - Yearly & Total'!$H$9<0.7,"Underspend Risk","On Track")) -> Underspend Risk
B97: ='13c. Budget - Yearly & Total'!$C$10 -> Community Engagement (CESG), Caregiver Support and SEL Storybooks | E97: ='13c. Budget - Yearly & Total'!$E$10+'13c. Budget - Yearly & Total'!$F$10 -> 0 | G97: ='13c. Budget - Yearly & Total'!$G$10 -> 0 | I97: ='13c. Budget - Yearly & Total'!$H$10 -> 0 | J97: =IF('13c. Budget - Yearly & Total'!$H$10>1.1,"Overspend Risk",IF('13c. Budget - Yearly & Total'!$H$10<0.7,"Underspend Risk","On Track")) -> Underspend Risk
B98: ='13c. Budget - Yearly & Total'!$C$11 -> Child protection case management services (identification, assessment, planning, referral, closure) | E98: ='13c. Budget - Yearly & Total'!$E$11+'13c. Budget - Yearly & Total'!$F$11 -> 0 | G98: ='13c. Budget - Yearly & Total'!$G$11 -> 0 | I98: ='13c. Budget - Yearly & Total'!$H$11 -> 0 | J98: =IF('13c. Budget - Yearly & Total'!$H$11>1.1,"Overspend Risk",IF('13c. Budget - Yearly & Total'!$H$11<0.7,"Underspend Risk","On Track")) -> Underspend Risk
B99: ='13c. Budget - Yearly & Total'!$C$12 -> Establish and/or refurbish Multipurpose Centres + deliver MHPSS (shown as 0 in source - costs captured under R2A3 below) | E99: ='13c. Budget - Yearly & Total'!$E$12+'13c. Budget - Yearly & Total'!$F$12 -> 0 | G99: ='13c. Budget - Yearly & Total'!$G$12 -> 0 | I99: ='13c. Budget - Yearly & Total'!$H$12 | J99: =IF('13c. Budget - Yearly & Total'!$H$12>1.1,"Overspend Risk",IF('13c. Budget - Yearly & Total'!$H$12<0.7,"Underspend Risk","On Track")) -> Overspend Risk
B100: ='13c. Budget - Yearly & Total'!$C$13 -> PSS and protection-focused group interventions via MPCACs (incl. establishment, ISMF, Men & Boys Engagement, dignity/MHM kits) | E100: ='13c. Budget - Yearly & Total'!$E$13+'13c. Budget - Yearly & Total'!$F$13 -> 0 | G100: ='13c. Budget - Yearly & Total'!$G$13 -> 0 | I100: ='13c. Budget - Yearly & Total'!$H$13 -> 0 | J100: =IF('13c. Budget - Yearly & Total'!$H$13>1.1,"Overspend Risk",IF('13c. Budget - Yearly & Total'!$H$13<0.7,"Underspend Risk","On Track")) -> Underspend Risk
B101: ='13c. Budget - Yearly & Total'!$C$14 -> Strengthening community-based protection mechanisms (CBCPC, PALS, risk mapping, IPT/puppet, DRR training) | E101: ='13c. Budget - Yearly & Total'!$E$14+'13c. Budget - Yearly & Total'!$F$14 -> 0 | G101: ='13c. Budget - Yearly & Total'!$G$14 -> 0 | I101: ='13c. Budget - Yearly & Total'!$H$14 -> 0 | J101: =IF('13c. Budget - Yearly & Total'!$H$14>1.1,"Overspend Risk",IF('13c. Budget - Yearly & Total'!$H$14<0.7,"Underspend Risk","On Track")) -> Underspend Risk
B102: ='13c. Budget - Yearly & Total'!$C$15 -> Capacity-building for frontline staff/volunteers on CP-GBV integration | E102: ='13c. Budget - Yearly & Total'!$E$15+'13c. Budget - Yearly & Total'!$F$15 -> 0 | G102: ='13c. Budget - Yearly & Total'!$G$15 -> 0 | I102: ='13c. Budget - Yearly & Total'!$H$15 -> 0 | J102: =IF('13c. Budget - Yearly & Total'!$H$15>1.1,"Overspend Risk",IF('13c. Budget - Yearly & Total'!$H$15<0.7,"Underspend Risk","On Track")) -> Underspend Risk
B103: ='13c. Budget - Yearly & Total'!$C$16 -> Human Resources (all local staff salaries - Project Coordinator, Technical Coordinator, officers, M&E, admin, etc.) | E103: ='13c. Budget - Yearly & Total'!$E$16+'13c. Budget - Yearly & Total'!$F$16 -> 0 | G103: ='13c. Budget - Yearly & Total'!$G$16 -> 0 | I103: ='13c. Budget - Yearly & Total'!$H$16 -> 0 | J103: =IF('13c. Budget - Yearly & Total'!$H$16>1.1,"Overspend Risk",IF('13c. Budget - Yearly & Total'!$H$16<0.7,"Underspend Risk","On Track")) -> Underspend Risk
B104: ='13c. Budget - Yearly & Total'!$C$17 -> Running Costs (staff/support travel, office rent & utilities, communications) | E104: ='13c. Budget - Yearly & Total'!$E$17+'13c. Budget - Yearly & Total'!$F$17 -> 0 | G104: ='13c. Budget - Yearly & Total'!$G$17 -> 0 | I104: ='13c. Budget - Yearly & Total'!$H$17 -> 0 | J104: =IF('13c. Budget - Yearly & Total'!$H$17>1.1,"Overspend Risk",IF('13c. Budget - Yearly & Total'!$H$17<0.7,"Underspend Risk","On Track")) -> Underspend Risk
B105: ='13c. Budget - Yearly & Total'!$C$18 -> Equipment (laptops, furniture and fixtures) | E105: ='13c. Budget - Yearly & Total'!$E$18+'13c. Budget - Yearly & Total'!$F$18 -> 0 | G105: ='13c. Budget - Yearly & Total'!$G$18 -> 0 | I105: ='13c. Budget - Yearly & Total'!$H$18 -> 0 | J105: =IF('13c. Budget - Yearly & Total'!$H$18>1.1,"Overspend Risk",IF('13c. Budget - Yearly & Total'!$H$18<0.7,"Underspend Risk","On Track")) -> Underspend Risk
B106: ='13c. Budget - Yearly & Total'!$C$19 -> Indirect Costs (Local Partner ICR, max 2% of direct costs) | E106: ='13c. Budget - Yearly & Total'!$E$19+'13c. Budget - Yearly & Total'!$F$19 -> 0 | G106: ='13c. Budget - Yearly & Total'!$G$19 -> 0 | I106: ='13c. Budget - Yearly & Total'!$H$19 -> 0 | J106: =IF('13c. Budget - Yearly & Total'!$H$19>1.1,"Overspend Risk",IF('13c. Budget - Yearly & Total'!$H$19<0.7,"Underspend Risk","On Track")) -> Underspend Risk
B108: Camp-wise Summary
B109: Total participants/recipients reached to date, by camp - summed live from the Activity Data Log (Sheet 10) and Distribution Log (Sheet 11) Camp columns.
B111: Camp | E111: Activity Data Log Participants | H111: Distribution Log Recipients | K111: Total
B112: Camp 1W | E112: =SUMIF('10. Activity Data Log'!$E$7:$E$46,"Camp 1W",'10. Activity Data Log'!$U$7:$U$46) -> 0 | H112: =SUMIF('11. Distribution Log'!$E$7:$E$46,"Camp 1W",'11. Distribution Log'!$W$7:$W$46) -> 0 | K112: =E112+H112 -> 0
B113: Camp 6 | E113: =SUMIF('10. Activity Data Log'!$E$7:$E$46,"Camp 6",'10. Activity Data Log'!$U$7:$U$46) -> 0 | H113: =SUMIF('11. Distribution Log'!$E$7:$E$46,"Camp 6",'11. Distribution Log'!$W$7:$W$46) -> 0 | K113: =E113+H113 -> 0
B114: Camp 21 | E114: =SUMIF('10. Activity Data Log'!$E$7:$E$46,"Camp 21",'10. Activity Data Log'!$U$7:$U$46) -> 0 | H114: =SUMIF('11. Distribution Log'!$E$7:$E$46,"Camp 21",'11. Distribution Log'!$W$7:$W$46) -> 0 | K114: =E114+H114 -> 0
B115: Camp 24 | E115: =SUMIF('10. Activity Data Log'!$E$7:$E$46,"Camp 24",'10. Activity Data Log'!$U$7:$U$46) -> 0 | H115: =SUMIF('11. Distribution Log'!$E$7:$E$46,"Camp 24",'11. Distribution Log'!$W$7:$W$46) -> 0 | K115: =E115+H115 -> 0
B117: Complaints & Feedback (CFM) Summary
B118: Pulled live from the CFM Log (Sheet 6). Category 5/6 = safeguarding/PSEA/fraud/security concerns - these need immediate management attention regardless of overall volume.
B120: Metric | G120: Value
B121: Total feedback/complaints logged | G121: =COUNTIF('6. CFM Log Template'!$AB$7:$AB$46,"<>") -> 0
B122: Unresolved (open) | G122: =COUNTIF('6. CFM Log Template'!$AB$7:$AB$46,"Unresolved")+COUNTIF('6. CFM Log Template'!$AB$7:$AB$46,"In progress") -> 0
B123: Category 5/6 (safeguarding/PSEA/fraud/security) - needs immediate attention | G123: =SUMPRODUCT(ISNUMBER(SEARCH("5.",'6. CFM Log Template'!$U$7:$U$46))*1)+SUMPRODUCT(ISNUMBER(SEARCH("6.",'6. CFM Log Template'!$U$7:$U$46))*1) -> 0
...

Sheet 6. CFM Log Template
B2: 6. Complaints & Feedback Mechanism (CFM) - Individual Feedback Database
B3: Adapted from Save the Children's MPCA Feedback Database Template for FIVDB/SURAKKHA. Records individual pieces of feedback and concerns (hotline, feedback box, one-to-one conversations, face-to-face). For group/collective feedback (community meetings, FGDs, informal debriefs), use Sheet 6b (Collective Feedback) instead. Do NOT record names or descriptive detail for Category 5/6 sensitive concerns (safeguarding, PSEA, fraud, security) - record only the reference number of the formal report filed with the PIB/FIVDB Safeguarding Focal Point. Category 5/6 concerns must be escalated within 24-48 hours per the Safeguarding Framework.
B5: Information about when and by whom the feedback/concern was received or documented | H5: Information about the person who shared feedback/concern and the feedback/concern itself (OPTIONAL - the person may decline to give this information) | Z5: Information about referring, actioning and closing the feedback loop
B6: Unique Number | C6: Date Received (dd/mm/yy) | D6: Name of Staff Who Received/Documented | E6: Position of Staff Member | F6: Contact Details of Staff Member | G6: Channel | H6: Name of Person Sharing Feedback (if known) | I6: Type of Person | J6: Age (if known) | K6: Age Group (auto) | L6: Gender | M6: Vulnerability | N6: Phone Number (if provided) | O6: Camp | P6: Block (if known) | Q6: Address (if applicable) | R6: Theme/Sector | S6: Activity/Project (Activity Code if known) | T6: Description of Feedback (NOT for Category 5/6 - cite report ref# instead) | U6: Category | V6: Sub-Category (Category 5/6 only) | W6: Date of Referral (dd/mm/yy) | X6: Name of Staff Referred To | Y6: Position of Staff Referred To | Z6: Contact of Staff Referred To | AA6: Actions Undertaken to Resolve (NOT for Category 5/6) | AB6: Status | AC6: Date Resolved (dd/mm/yy) | AD6: Days Taken to Resolve (auto) | AE6: Feedback Loop Closed? (communicated back to person) | AF6: Additional Comments
B7: 1 | K7: =IFERROR(IF(J7="","",IF(J7<18,"Child",IF(J7>=18,"Adult","Unknown"))),"") | AD7: =IFERROR(IF(OR(C7="",AC7=""),"",AC7-C7),"")
B8: 2 | K8: =IFERROR(IF(J8="","",IF(J8<18,"Child",IF(J8>=18,"Adult","Unknown"))),"") | AD8: =IFERROR(IF(OR(C8="",AC8=""),"",AC8-C8),"")
B9: 3 | K9: =IFERROR(IF(J9="","",IF(J9<18,"Child",IF(J9>=18,"Adult","Unknown"))),"") | AD9: =IFERROR(IF(OR(C9="",AC9=""),"",AC9-C9),"")
B10: 4 | K10: =IFERROR(IF(J10="","",IF(J10<18,"Child",IF(J10>=18,"Adult","Unknown"))),"") | AD10: =IFERROR(IF(OR(C10="",AC10=""),"",AC10-C10),"")
B11: 5 | K11: =IFERROR(IF(J11="","",IF(J11<18,"Child",IF(J11>=18,"Adult","Unknown"))),"") | AD11: =IFERROR(IF(OR(C11="",AC11=""),"",AC11-C11),"")
B12: 6 | K12: =IFERROR(IF(J12="","",IF(J12<18,"Child",IF(J12>=18,"Adult","Unknown"))),"") | AD12: =IFERROR(IF(OR(C12="",AC12=""),"",AC12-C12),"")
B13: 7 | K13: =IFERROR(IF(J13="","",IF(J13<18,"Child",IF(J13>=18,"Adult","Unknown"))),"") | AD13: =IFERROR(IF(OR(C13="",AC13=""),"",AC13-C13),"")
B14: 8 | K14: =IFERROR(IF(J14="","",IF(J14<18,"Child",IF(J14>=18,"Adult","Unknown"))),"") | AD14: =IFERROR(IF(OR(C14="",AC14=""),"",AC14-C14),"")
B15: 9 | K15: =IFERROR(IF(J15="","",IF(J15<18,"Child",IF(J15>=18,"Adult","Unknown"))),"") | AD15: =IFERROR(IF(OR(C15="",AC15=""),"",AC15-C15),"")
B16: 10 | K16: =IFERROR(IF(J16="","",IF(J16<18,"Child",IF(J16>=18,"Adult","Unknown"))),"") | AD16: =IFERROR(IF(OR(C16="",AC16=""),"",AC16-C16),"")
B17: 11 | K17: =IFERROR(IF(J17="","",IF(J17<18,"Child",IF(J17>=18,"Adult","Unknown"))),"") | AD17: =IFERROR(IF(OR(C17="",AC17=""),"",AC17-C17),"")
B18: 12 | K18: =IFERROR(IF(J18="","",IF(J18<18,"Child",IF(J18>=18,"Adult","Unknown"))),"") | AD18: =IFERROR(IF(OR(C18="",AC18=""),"",AC18-C18),"")
... B46: 40 | K46: =IFERROR(IF(J46="","",IF(J46<18,"Child",IF(J46>=18,"Adult","Unknown"))),"") | AD46: =IFERROR(IF(OR(C46="",AC46=""),"",AC46-C46),"")

Sheet 6b. Collective Feedback
B2: 6b. Complaints & Feedback Mechanism (CFM) - Collective Feedback
B3: Records feedback gathered from a GROUP of adults or children (e.g. community meetings, FGDs) or informal feedback shared by front-line staff (e.g. during a de-brief session) - as distinct from Sheet 6's individual feedback log. This allows FIVDB/PIB to analyse both formal/individual and informal/collective feedback together.
B5: Unique Number | C5: Date (dd/mm/yy) | D5: Name of Staff Who Documented | E5: Position | F5: Method (community meeting/FGD/debrief) | G5: Camp | H5: Group Composition (e.g. CESG, CBCPC, parents) | I5: No. of Participants (M/F/Total) | J5: Theme/Sector | K5: Summary of Feedback/Concerns Raised | L5: Category | M5: Actions Undertaken | N5: Status | O5: Date Resolved (dd/mm/yy) | P5: Feedback Loop Closed? (communicated back to group) | Q5: Additional Comments
B6: 1
B7: 2
B8: 3
B9: 4
B10: 5
B11: 6
B12: 7
B13: 8
B14: 9
B15: 10
B16: 11
B17: 12
... B45: 40

Sheet 6c. Target Breakdown
B2: 6c. Target Breakdown - FIVDB Facility & Beneficiary Targets
B3: Figures cross-validated against the Narrative Proposal (18-Mar-26), the FIVDB Detailed Budget, and Annex 3 (Locations & Integration Mapping). Updated from earlier Annex-2-derived estimates where the Narrative/Budget give more precise, confirmed numbers - see the Comments column and the note at the end of each section. Education and Protection beneficiary totals are counted as unique within each sector separately; the same person may appear in both sectors, so the combined FIVDB total at the bottom is not a de-duplicated headcount across sectors.
B5: A. Education (Result 1) Targets
B6: A.1 Facility / structure targets
B7: Structure | C7: Camp 1W | D7: Camp 6 | E7: Camp 21 | F7: Camp 24 | G7: Total | H7: Reference
B8: Community-Based Learning Facilities (CBLFs) - girls' | C8: 10 | D8: 10 | E8: 7 | F8: 7 | G8: 34 | H8: Narrative Proposal; camp split computed proportionally (2:1 girls:boys ratio applied to Annex 3 camp totals)
B9: Community-Based Learning Facilities (CBLFs) - boys' | C9: 6 | D9: 5 | E9: 3 | F9: 3 | G9: 17 | H9: Narrative Proposal; camp split computed proportionally (2:1 girls:boys ratio applied to Annex 3 camp totals)
B10: CBLFs total (by camp, per Annex 3) | C10: 16 | D10: 15 | E10: 10 | F10: 10 | G10: 51 | H10: Annex 3, PLAN sheet, rows 3-6
B11: Community Education Support Groups (CESGs, ~1 per 2 CBLFs) | C11: 8 | D11: 8 | E11: 5 | F11: 5 | G11: ~26 groups | H11: FIVDB Detailed Budget, R1A5; camp split = CBLFs per camp / 2, rounded
B12: CORRECTED: FIVDB's 51 facilities are all CBLFs (34 girls' + 17 boys'), per the Narrative Proposal. GoLFs (Girls-Only Learning Facilities, secondary level) belong to SC, not FIVDB - the earlier 'GoLF included within the 51' assumption was incorrect and has been removed. Camp-wise girls'/boys' split is NOT independently specified in the Narrative Proposal or Annex 3 - it is computed by applying the confirmed overall 2:1 girls:boys ratio (34:17) to each camp's known total facility count (16/15/10/10), rounded to whole facilities; validate the actual per-camp split with PIB once site allocation is finalised.
B14: A.2 Beneficiary targets - camp-wise (life of project)
B15: Category | C15: Target (Total) | D15: Total Days/Sessions (indicative) | E15: Of whom with disability | F15: Reference / Basis
B16: Learners (11-18 years) - Camp 1W | C16: 384 | D16: 160 | E16: 37 (3% target) | F16: 384 CBLFs 16 x 24 learners/facility; 66.7% female per facility-ratio
B17: Learners (11-18 years) - Camp 6 | C17: 360 | D17: 150 | E17: 34 (3% target) | F17: 15 CBLFs x 24 learners/facility
B18: Learners (11-18 years) - Camp 21 | C18: 240 | D18: 100 | E18: 23 (3% target) | F18: 10 CBLFs x 24 learners/facility
B19: Learners (11-18 years) - Camp 24 | C19: 240 | D19: 100 | E19: 23 (3% target) | F19: 10 CBLFs x 24 learners/facility
B20: Learners (11-18 years) - TOTAL | C20: 1,224 | D20: - | E20: 37 (3% target) | F20: 51 CBLFs x 24 learners/facility, 2 shifts; matches Narrative Proposal & FIVDB Detailed Budget row 65
B21: CESG members (7-8 per group, ~26 groups) | C21: 204 | D21: - | E21: - | F21: FIVDB Detailed Budget, R1A5; camp split not independently specified
B22: Parents / caregivers (1 per enrolled child) | C22: 1,224 | D22: - | E22: - | F22: FIVDB Detailed Budget, R1A5; follows learner enrolment 1:1, so mirrors the camp split above
B23: Teachers / facilitators (refugee + host) | C23: 68 | D23: - | E23: - | F23: Annex 2, EiE_PIB tab; 51 refugee + 17 host, camp split not independently specified
B24: Learners are broken down camp-wise using the direct, defensible relationship confirmed in the Narrative Proposal: each CBLF serves exactly 24 learners (2 shifts) - so Learners per camp = CBLFs per camp (Section A.1) x 24. This gives clean, source-derived numbers (384/360/240/240), not an estimate. The 'Total Days/Sessions' column for camp-level learner rows shows an indicative female sub-count (applying the same 66.7%/33.3% facility-based sex ratio used in A.1) - not an independently confirmed sex split by camp; validate with PIB. CESG members, Parents/caregivers and Teachers do NOT have an independently confirmed camp-wise split in either the Narrative Proposal or FIVDB Detailed Budget - showing the Total only for these rows is more honest than fabricating a camp breakdown; a camp-wise split can be computed once FIVDB confirms actual CESG/teacher deployment per camp.
B26: B. Child Protection (Result 2) Targets
B27: B.1 Facility / structure targets
B28: Structure | C28: Camp 1W | D28: Camp 6 | E28: Camp 21 | F28: Camp 24 | G28: Total | H28: Reference
B29: MPCAC - newly established | C29: 1 | D29: 1 | E29: 1 | F29: 1 | G29: 4 | H29: Narrative Proposal; Detailed Budget R2A3
B30: MPCAC - refurbished | C30: 1 | D30: 0 | E30: 0 | F30: 1 | G30: 2 | H30: Narrative Proposal; Detailed Budget R2A3
B31: MPCAC total facility actions | C31: 2 | D31: 1 | E31: 1 | F31: 2 | G31: 6 | H31: Narrative Proposal; Detailed Budget R2A3
B32: Case Management Offices | C32: 1 | D32: 1 | E32: 1 | F32: 1 | G32: 4 | H32: FIVDB Detailed Budget, R2A1
B33: Community-Based Child Protection Committees (CBCPCs, 2 per camp x 4 camps) | C33: - | D33: - | E33: - | F33: - | G33: 8 | H33: FIVDB Detailed Budget, R2A4
B34: CONFIRMED: MPCAC (4 new + 2 refurbished = 6) matches exactly between the Narrative Proposal and the Detailed Budget. CBCPCs updated to 8 committees (2 per camp x 4 camps, 17 members each = 136 total members) per the Detailed Budget - more precise than the earlier 'indicative 4' estimate.
B36: B.2 Beneficiary targets (life of project)
B37: Category | C37: Female | D37: Male | E37: Total | F37: Of whom with disability | G37: Reference
B38: Children in case management (R2A1) | C38: 160 | D38: 160 | E38: 320 | F38: TBD | G38: FIVDB Detailed Budget, R2A1
B39: Adolescents in PALS sessions (R2A4) | C39: 2,160 | D39: 2,160 | E39: 4,320 | F39: TBD | G39: FIVDB Detailed Budget, R2A4
B40: Parents/Caregivers in PALS sessions (R2A4) | C40: TBD | D40: TBD | E40: 4,320 | F40: - | G40: FIVDB Detailed Budget, R2A4
B41: CBCPC members (2 x 4 camps x 17) | C41: TBD | D41: TBD | E41: 136 | F41: - | G41: FIVDB Detailed Budget, R2A4
B42: Persons receiving Dignity/MHM kits (CP side, R2A3) | C42: 1,814 | D42: - | E42: 1,814 | F42: - | G42: FIVDB Detailed Budget, R2A3
B43: Community Leaders & Volunteers - DRR/Climate training (R2A4) | C43: TBD | D43: TBD | E43: 240 | F43: - | G43: FIVDB Detailed Budget, R2A4
B44: Case management volunteers (2 per camp x 4 camps) | C44: TBD | D44: TBD | E44: 8 | F44: - | G44: FIVDB Detailed Budget, R2A1
B45: CP total (FIVDB, indicative, categories overlap) | C45: - | D45: - | E45: See rows above | F45: -
B46: UPDATED from the FIVDB Detailed Budget: case management children 314->320; PALS adolescents/caregivers 4,234->4,320; CBCPC members 132->136. Dignity/MHM kits (CP side, 1,814 persons) and the DRR/Climate training cohort (240) are new rows not previously captured. Sex splits marked 'TBD' are not specified in the Budget/Narrative at this level of detail - the CP unique-total row from the previous version has been removed because these categories overlap (e.g. a PALS adolescent may also be a case-management child or CBCPC-linked); summing them would double-count. Validate all figures and true unique headcounts with PIB.
B48: C. Notes on Combined FIVDB Reach
B49: A single combined FIVDB headcount (Education + Protection) is not shown here because several Protection categories (PALS adolescents, CBCPC members, case-management children) overlap with each other and potentially with Education learners, and the Budget/Narrative do not provide a de-duplicated total. For consortium-level unique-beneficiary reporting, defer to PIB's consolidated Beneficiary Table rather than summing the rows above.

Sheet 6d. Key Milestones
B2: 6d. Key Milestones - FIVDB (SURAKKHA)
B3: Every FIVDB sub-activity with its expected completion window, derived live from the same planned-quarter data used in the Activity Tracker (Sheet 8) - Q1 = Jun-Aug 2026 through Q8 = Mar-May 2028.
B5: Activity Code | C5: Milestone | D5: Expected Month/Year of Completion | E5: Responsible Person
B6: Result 1: Adolescent girls and boys have sustained access to inclusive, quality learning opportunities in safe, protective, community-based learning facilities.
B7: R1A1.1 | C7: Conduct household survey through community volunteers to identify out-of-school and dropout children. | D7: Jun 2026 - May 2027 | E7: Education Officer
B8: R1A1.2 | C8: Conduct technical/disability assessment and screening of identified children (minimum 3% disability target), referring complex cases to Humanity & Inclusion (HI) under FIVDB's MoU. | D8: Jun 2026 - May 2027 | E8: Education Officer
B9: R1A1.3 | C9: Print placement/assessment and disability-screening tools. | D9: Jun 2026 - May 2027 | E9: Education Officer
B10: R1A2.1 | C10: Provide monthly incentives to host-community teacher volunteers. | D10: Jun 2026 - May 2028 | E10: Education Officer
B11: R1A2.2 | C11: Provide monthly incentives to refugee-community teacher volunteers. | D11: Jun 2026 - May 2028 | E11: Education Officer
B12: R1A2.3 | C12: Distribute scholastic material kits (exercise books, ALP books, drawing books, pens, pencils, water bottle, erasers, sharpeners) to enrolled children, 2 shifts per CBLF. | D12: Jun 2026 - May 2027 | E12: Education Officer
B13: R1A2.4 | C13: Distribute one school bag per enrolled child (one-time distribution). | D13: Jun 2026 - Aug 2026 | E13: Education Officer
B14: R1A2.5 | C14: Provide assistive devices and reasonable accommodation for children with disabilities (device cost only; assessment carried out by HI). | D14: Jun 2026 - May 2027 | E14: Education Officer
B15: R1A2.6 | C15: Provide the CBLF minimum package (floor mats, whiteboards, boxes, stationery, cleaning materials). | D15: Jun 2026 - May 2027 | E15: Education Officer
B16: R1A2.7 | C16: Install solar panels, lighting and fire extinguishers at all CBLFs. | D16: Jun 2026 - May 2027 | E16: Education Officer
B17: R1A2.8 | C17: Cover ongoing CBLF maintenance costs. | D17: Jun 2026 - May 2028 | E17: Education Officer
B18: R1A2.9 | C18: Produce and display IEC materials (safeguarding, child protection, PSHEA posters) at all CBLFs. | D18: Jun 2026 - May 2027 | E18: Education Officer
... B38: R1A5.3 | C38: Hold bi-monthly parent/caregiver engagement meetings (1 parent per enrolled child). | D38: Jun 2026 - May 2028 | E38: Education Officer
B39: Result 2: Strengthened, inclusive child protection services prevent and respond to protection risks of girls, boys, women and men affected by the Rohingya crisis.
B40: R2A1.1 | C40: Identify and enhance the capacity of alternative-care family members (foster and kinship) for unaccompanied/separated children (UASC). | D40: Jun 2026 - May 2027 | E40: Technical Coordinator–Protection
B41: R2A1.2 | C41: Provide case-management need-based and emergency support (NFIs) to children/families in active cases. | D41: Jun 2026 - May 2028 | E41: Technical Coordinator–Protection
B42: R2A1.3 | C42: Maintain functioning Case Management Offices (1 per camp). | D42: Jun 2026 - May 2028 | E42: Technical Coordinator–Protection
B43: R2A1.4 | C43: Deliver case management services per the CPMS 7-step process (non-budgetary - covered by CM Officer/volunteer time). | D43: Jun 2026 - May 2028 | E43: Case Management Officer
B44: R2A1.5 | C44: Train para-social workers, volunteers and facilitators on referral pathways. | D44: Jun 2026 - May 2027 | E44: Technical Coordinator–Protection
B45: R2A1.6 | C45: Provide monthly incentives to case-management volunteers (2 per camp, all refugees) for identification and referral. | D45: Jun 2026 - May 2027 | E45: Technical Coordinator–Protection
B46: R2A1.7 | C46: Provide support-material kits (case-worker kits) for case-management service providers. | D46: Jun 2026 - May 2027 | E46: Technical Coordinator–Protection
B47: R2A3.1 | C47: Construct new MPCACs and refurbish existing MPCACs, including running costs. | D47: Jun 2026 - May 2027 | E47: Technical Coordinator–Protection
B48: R2A3.2 | C48: Roll out 'I Support My Friend' (ISMF) at community level, including inception meeting and adolescent training. | D48: Jun 2026 - May 2027 | E48: Technical Coordinator–Protection
B49: R2A3.3 | C49: Deploy MPCAC facilitators (refugee volunteers, host-community volunteers, security guards) to run PSS/awareness sessions. | D49: Jun 2026 - May 2028 | E49: Technical Coordinator–Protection
B50: R2A3.4 | C50: Orient and engage proactive Men and Boys in GBV prevention and response (bi-weekly sessions). | D50: Jun 2026 - May 2028 | E50: Technical Coordinator–Protection
B51: R2A3.5 | C51: Deliver community-led activities on CP and GBV issues (day/event observation). | D51: Jun 2026 - May 2028 | E51: Technical Coordinator–Protection
... B63: R2A5.5 | C63: Hold a project inception workshop with relevant stakeholders at camp level. | D63: Jun 2026 - Aug 2026 | E63: Project Manager

Sheet 6e. Logframe
B2: 6e. Logframe - FIVDB (SURAKKHA)
B3: Matches the structure of Annex 1 (Logframe) submitted separately to PIB - Level / Ref / Performance Indicator / Target / Agency / Agency Target / Indicator Definition / Comments. Ref codes here (e.g. R1.1) are a THIRD numbering system, distinct from the IPTT's indicator codes (R1-I1) and the Activity Tracker's budget codes (R1A1) - see the Cover sheet FAQ for how the three relate.
B5: Level | C5: Ref | D5: Performance Indicator | E5: Target | F5: Agency | G5: Agency Target | H5: Indicator Definition | I5: Comments / Clarifications
B6: Outcome statement | C6: SO | D6: Girls and boys, including the most vulnerable and children with disabilities, have safe and equitable access to quality, inclusive non-formal education and child protection services.
B7: Outcome indicator | C7: SO.1 | D7: % of beneficiaries reporting that humanitarian assistance is delivered in a safe, accessible, accountable and participatory manner | E7: 85% | F7: FIVDB | G7: 85% | H7: Officially approved Logframe (Annex I) target.
B8: Outcome indicator | C8: SO.2 | D8: % targeted girls and boys who are retained in education at the end of the action | E8: 90% | F8: FIVDB | G8: 90% | H8: Denominator = FIVDB's 1,224 enrolled learners.
B9: Output statement | C9: R1 | D9: Adolescent girls and boys have sustained access to inclusive, quality learning opportunities in safe, protective, community-based learning facilities.
B10: Output indicator | C10: R1.1 | D10: Number of targeted girls and boys enrolled in non-formal education services | E10: 1224 | F10: FIVDB | G10: 1224 | I10: 816 girls + 408 boys across 51 CBLFs.
B11: Output indicator | C11: R1.2 | D11: Number of learning spaces established or restored to minimum standards for safe learning | E11: 51 | F11: FIVDB | G11: 51 | I11: 34 girls' + 17 boys' CBLFs across Camps 1W, 6, 21, 24.
B12: Output indicator | C12: R1.3 | D12: Number of teachers provided with teaching aids/materials | E12: 68 | F12: FIVDB | G12: 68 | I12: 51 refugee + 17 host.
B13: Output indicator | C13: R1.4 | D13: Number of girls and boys provided with learning materials | E13: 1224 | F13: FIVDB | G13: 1224 | I13: Same 1,224 learners as R1.1.
B14: Output indicator | C14: R1.5 | D14: Number of teachers/education personnel showing increased knowledge and teaching skills | E14: 68 | F14: FIVDB | G14: 68 | I14: 100% of FIVDB's own teachers targeted.
B15: Output indicator | C15: R1.6 | D15: Number of students, teachers and other education personnel provided with psycho-social support services | E15: 2516 | F15: FIVDB | G15: 2516 | I15: 68 teachers + 1,224 learners + 1,224 parents/caregivers.
B16: Output indicator | C16: R1.7 | D16: Number of teachers and other education personnel showing increased knowledge and skills to address protection needs | E16: 68 | F16: FIVDB | G16: 68 | I16: FIVDB's own teaching cohort.
B17: Output indicator | C17: R1.8 | D17: Number of girls and boys referred to specialised services | E17: 122 | F17: FIVDB | G17: 122 | I17: ~10% of 1,224 enrolled learners (projection).
B18: Output indicator | C18: R1.9 | D18: % educational facilities carrying out environmental and climate friendly activities day-to-day | E18: 65% | F18: FIVDB | G18: 65% | I18: ~33 of FIVDB's 51 CBLFs.
B19: Output statement | C19: R2 | D19: Strengthened, inclusive child protection services prevent and respond to protection risks of girls, boys, women and men affected by the Rohingya crisis (FIVDB: Activities 1, 3, 4, 5).
B20: Output indicator | C20: R2.1 | D20: (MANDATORY) % of children and caregivers whose urgent child protection needs/risks have been addressed | E20: 95% | F20: FIVDB | G20: 95% | I20: 320 children in case management, 4 Case Management Offices.
B21: Output indicator | C21: R2.2 | D21: % of CAAFAG who benefit from appropriate care and services | E21: 80% | F21: FIVDB | G21: 80% | I21: Within FIVDB's caseload.
B22: Output indicator | C22: R2.3 | D22: Average % knowledge increase amongst participants on the protection subject in focus | E22: 80% | F22: FIVDB | G22: 80% | I22: Pre-/post-test knowledge gain.
B23: Output indicator | C23: R2.4 | D23: (MANDATORY) % of persons who receive appropriate PSS reporting improved wellbeing | E23: 80% | F23: FIVDB | G23: 80% | I23: 6 MPCACs (4 new + 2 refurbished), PALS reaching 4,320 + 4,320.
B24: Output indicator | C24: R2.5 | D24: % of caseworkers whose knowledge assessment score is at least 70% | E24: 75% | F24: FIVDB | G24: 75% | I24: Annual Case Worker Capacity Assessment.
B25: Output indicator (reference) | C25: R2.Ref | D25: (MANDATORY) Number of minimum standards for care for survivors achieved | E25: 12 | F25: FIVDB/PLAN | G25: 12 | H25: SC-led overall (Activity 2); FIVDB's role is referral-only. PLAN's own sub-target is 12 (of 31 reviewed); SC's separate target is 16.

Sheet 7. IPTT
B2: 7. Indicator Performance Tracking Table (IPTT) - FIVDB
B3: >>> SET CURRENT REPORTING QUARTER HERE (1-8): | C3: 1 | D3: (everything in this workbook depends on this cell)
B5: Consortium baselines/targets from the Logframe (Annex I). FIVDB's LOP Target = indicative FIVDB contribution derived from Annex 2 (EiE_PIB / CP_PIB_V2). 'Linked Activity/ies' shows the primary (first-listed) Activity Tracker SUB-ACTIVITY code (Sheet 8) whose own Linked Indicator(s) field matches this indicator - auto-computed, single source of truth. Where more than one sub-activity feeds the same indicator, the rest are listed in 'Additional Linked Sub-Activities' immediately to its right, rather than crammed into one cell. TARGET columns are auto-calculated from LOP Target using the phasing assumptions below (blue cells = editable inputs). ACTUAL columns: for 'Number'-unit indicators, ACTUAL is now AUTOMATIC - cumulative sum, by quarter, of every Activity Tracker (Sheet 8) sub-activity ACTUAL total whose Linked Indicator(s) matches this indicator's code (light-blue cells; no manual entry, recalculates as Sheets 10-11 are populated). For '%'-unit indicators, FIVDB enters cumulative-to-date achievement directly into the quarter cell (yellow cells; survey/assessment-based - a percentage cannot be derived from headcount sums). Validate all figures with PIB at inception.
B7: HOW TO READ THIS SHEET - answers to the most common PIB review questions: (1) LOP Target (column O) is always FIVDB's OWN contribution only - never the wider consortium (SC+FIVDB/PLAN) total; the consortium total and the full breakdown behind every composite figure (e.g. 'X teachers + Y learners + Z parents') are always spelled out in the Comments column so every number is traceable, not just asserted. (2) Several '%'-unit LOP Targets across Result 2 look similar (75-95%) because they are the officially approved figures from the same Logframe (Annex I) table, reflecting comparable prior-phase (ECHO HIP 2023) performance baselines across CP/PSS/GBV service lines - not copied from one row to another; each has its own distinct source paragraph in Comments. (3) Result 2 has 5 Activities; FIVDB delivers Activities 1, 3, 4, 5. Activity 2 (adult 18+ GBV case management) is SC-led and explicitly defined in the Narrative Proposal ('Result 2 - Activity 2'), with FIVDB's role limited to referral - this is why it has no FIVDB budget code (R2A2) anywhere in the Activity Tracker. (4) 'Reference' indicator rows (R2-Ref1-3) are led by another consortium agency, shown here for traceability only - FIVDB is not directly accountable for the full consortium figure on those rows. (5) Any Annex number cited in a Comments cell (e.g. Annex 27) refers to an annex of the consortium's DG ECHO Single Form proposal, held by PIB/SC, not a standalone FIVDB document.
B9: ONGOING-delivery phasing (training, referrals, PSS, case management - accrues continuously) - used only for Status calculation below, not shown per-indicator: | O9: 0.05 | P9: 0.15 | Q9: 0.3 | R9: 0.45 | S9: 0.62 | T9: 0.78 | U9: 0.92 | V9: 1
B10: ENROLMENT/ESTABLISHMENT phasing (learners enrolled, facilities/teachers set up - front-loaded, then RETAINED not re-enrolled): | O10: 0.45 | P10: 0.85 | Q10: 0.97 | R10: 1 | S10: 1 | T10: 1 | U10: 1 | V10: 1
B11: RATIONALE for TWO phasing curves, not one: enrolment/establishment-type indicators (learners enrolled, facilities/teachers/kits set up) do NOT grow every quarter - once a learner is enrolled or a CBLF is established, they don't get 're-enrolled' or 're-established' again next quarter; almost all of the growth happens once, early (CBLF opening, initial enrolment drive), then the LOP target is essentially reached and held (minus/plus small dropout replacement, tracked separately in the Dropout Tracker, Sheet 12). Ongoing-delivery indicators (training sessions, referrals, PSS, case management, knowledge assessments) behave differently - they genuinely accrue new instances every quarter as activities continue - so they follow the original S-curve instead. R1-I1, R1-I2, R1-I3 and R1-I4 (enrolment, facilities, teacher/learner materials) use the ENROLMENT/ESTABLISHMENT curve; every other Number-unit indicator uses the ONGOING-delivery curve - edit either blue/orange row directly if FIVDB's actual pattern differs; the Status column recalculates automatically from whichever row it's assigned to.
B13: Result | C13: Indicator Code | D13: Linked Activity/ies (primary sub-activity) | E13: Additional Linked Sub-Activities | F13: Indicator | G13: Reference Source (indicator origin) | H13: Indicator Definition | I13: Measurement Methodology | J13: Disaggregation Required | K13: Baseline | L13: Target Population / Denominator (indicative) | M13: LOP Target (FIVDB) | N13: Unit | O13: ACTUAL (cumulative, by quarter - auto-linked for Number indicators; FIVDB to complete for % indicators) | W13: % of LOP Target Achieved | X13: Status | Y13: Means of Verification | Z13: Source and Method of Data Collection | AA13: Verification / QA Step | AB13: Frequency | AC13: Responsible | AD13: Support Type (how they support) | AE13: Risks / Assumptions | AF13: How to Articulate in Narrative Report | AG13: Comments | AH13: CUMULATIVE SEX/AGE DISAGGREGATION (auto, from Sheets 10-11)
O14: Q1 | P14: Q2 | Q14: Q3 | R14: Q4 | S14: Q5 | T14: Q6 | U14: Q7 | V14: Q8 | AH14: Girls <18 | AI14: Boys <18 | AJ14: Women 18+ | AK14: Men 18+
B15: RESULT 1 - EDUCATION IN EMERGENCIES (FIVDB Activities 1-7)
B16: Result 1 | C16: R1-I1 | D16: R1A1.1 | E16: R1A1.2, R1A1.3 | F16: Number of targeted girls and boys enrolled in non-formal education services | G16: Logframe (Annex I), Result 1 indicators - code R1-I1 | H16: Enrolled = registered to participate in non-formal education. NFE is usually not accredited by the national education system (e.g. catch-up programmes, homework support, basic literacy/numeracy, language support, remedial education). For learners enrolled in both formal and complementary NFE services, a clear breakdown of multi-service enrolment must be provided. Disaggregate by sex, NFE type/level of education (primary, lower secondary, upper secondary) and disability. | I16: Enrolment registers maintained at CBLF level plus daily attendance sheets completed by teaching volunteers, recorded at facility level and compiled regularly by CBLF facilitators. | J16: Sex, level of education, disability | K16: 0 | L16: - | M16: 1224 | N16: Number | O16: =IF(1>'7. IPTT'!$C$3,"",IFERROR((SUMPRODUCT(ISNUMBER(SEARCH($C16,'8. Activity Tracker'!$J$7:$J$93))*N('8. Activity Tracker'!V$7:V$93))),0)) -> 0 | P16: =IF(2>'7. IPTT'!$C$3,"",IFERROR((SUMPRODUCT(ISNUMBER(SEARCH($C16,'8. Activity Tracker'!$J$7:$J$93))*N('8. Activity Tracker'!V$7:V$93))+SUMPRODUCT(ISNUMBER(SEARCH($C16,'8. Activity Tracker'!$J$7:$J$93))*N('8. Activity Tracker'!W$7:W$93))),0)) | Q16: =IF(3>'7. IPTT'!$C$3,"",IFERROR((SUMPRODUCT(ISNUMBER(SEARCH($C16,'8. Activity Tracker'!$J$7:$J$93))*N('8. Activity Tracker'!V$7:V$93))+SUMPRODUCT(ISNUMBER(SEARCH($C16,'8. Activity Tracker'!$J$7:$J$93))*N('8. Activity Tracker'!W$7:W$93))+SUMPRODUCT(ISNUMBER(SEARCH($C16,'8. Activity Tracker'!$J$7:$J$93))*N('8. Activity Tracker'!X$7:X$93))),0)) | R16: =IF(4>'7. IPTT'!$C$3,"",IFERROR((SUMPRODUCT(ISNUMBER(SEARCH($C16,'8. Activity Tracker'!$J$7:$J$93))*N('8. Activity Tracker'!V$7:V$93))+SUMPRODUCT(ISNUMBER(SEARCH($C16,'8. Activity Tracker'!$J$7:$J$93))*N('8. Activity Tracker'!W$7:W$93))+SUMPRODUCT(ISNUMBER(SEARCH($C16,'8. Activity Tracker'!$J$7:$J$93))*N('8. Activity Tracker'!X$7:X$93))+SUMPRODUCT(ISNUMBER(SEARCH($C16,'8. Activity Tracker'!$J$7:$J$93))*N('8. Activity Tracker'!Y$7:Y$93))),0)) | S16: =IF(5>'7. IPTT'!$C$3,"",IFERROR((SUMPRODUCT(ISNUMBER(SEARCH($C16,'8. Activity Tracker'!$J$7:$J$93))*N('8. Activity Tracker'!V$7:V$93))+SUMPRODUCT(ISNUMBER(SEARCH($C16,'8. Activity Tracker'!$J$7:$J$93))*N('8. Activity Tracker'!W$7:W$93))+SUMPRODUCT(ISNUMBER(SEARCH($C16,'8. Activity Tracker'!$J$7:$J$93))*N('8. Activity Tracker'!X$7:X$93))+SUMPRODUCT(ISNUMBER(SEARCH($C16,'8. Activity Tracker'!$J$7:$J$93))*N('8. Activity Tracker'!Y$7:Y$93))+SUMPRODUCT(ISNUMBER(SEARCH($C16,'8. Activity Tracker'!$J$7:$J$93))*N('8. Activity Tracker'!Z$7:Z$93))),0)) | T16: =IF(6>'7. IPTT'!$C$3,"",IFERROR((SUMPRODUCT(ISNUMBER(SEARCH($C16,'8. Activity Tracker'!$J$7:$J$93))*N('8. Activity Tracker'!V$7:V$93))+SUMPRODUCT(ISNUMBER(SEARCH($C16,'8. Activity Tracker'!$J$7:$J$93))*N('8. Activity Tracker'!W$7:W$93))+SUMPRODUCT(ISNUMBER(SEARCH($C16,'8. Activity Tracker'!$J$7:$J$93))*N('8. Activity Tracker'!X$7:X$93))+SUMPRODUCT(ISNUMBER(SEARCH($C16,'8. Activity Tracker'!$J$7:$J$93))*N('8. Activity Tracker'!Y$7:Y$93))+SUMPRODUCT(ISNUMBER(SEARCH($C16,'8. Activity Tracker'!$J$7:$J$93))*N('8. Activity Tracker'!Z$7:Z$93))+SUMPRODUCT(ISNUMBER(SEARCH($C16,'8. Activity Tracker'!$J$7:$J$93))*N('8. Activity Tracker'!AA$7:AA$93))),0)) | U16: =IF(7>'7. IPTT'!$C$3,"",IFERROR((SUMPRODUCT(ISNUMBER(SEARCH($C16,'8. Activity Tracker'!$J$7:$J$93))*N('8. Activity Tracker'!V$7:V$93))+SUMPRODUCT(ISNUMBER(SEARCH($C16,'8. Activity Tracker'!$J$7:$J$93))*N('8. Activity Tracker'!W$7:W$93))+SUMPRODUCT(ISNUMBER(SEARCH($C16,'8. Activity Tracker'!$J$7:$J$93))*N('8. Activity Tracker'!X$7:X$93))+SUMPRODUCT(ISNUMBER(SEARCH($C16,'8. Activity Tracker'!$J$7:$J$93))*N('8. Activity Tracker'!Y$7:Y$93))+SUMPRODUCT(ISNUMBER(SEARCH($C16,'8. Activity Tracker'!$J$7:$J$93))*N('8. Activity Tracker'!Z$7:Z$93))+SUMPRODUCT(ISNUMBER(SEARCH($C16,'8. Activity Tracker'!$J$7:$J$93))*N('8. Activity Tracker'!AA$7:AA$93))+SUMPRODUCT(ISNUMBER(SEARCH($C16,'8. Activity Tracker'!$J$7:$J$93))*N('8. Activity Tracker'!AB$7:AB$93))),0)) | V16: =IF(8>'7. IPTT'!$C$3,"",IFERROR((SUMPRODUCT(ISNUMBER(SEARCH($C16,'8. Activity Tracker'!$J$7:$J$93))*N('8. Activity Tracker'!V$7:V$93))+SUMPRODUCT(ISNUMBER(SEARCH($C16,'8. Activity Tracker'!$J$7:$J$93))*N('8. Activity Tracker'!W$7:W$93))+SUMPRODUCT(ISNUMBER(SEARCH($C16,'8. Activity Tracker'!$J$7:$J$93))*N('8. Activity Tracker'!X$7:X$93))+SUMPRODUCT(ISNUMBER(SEARCH($C16,'8. Activity Tracker'!$J$7:$J$93))*N('8. Activity Tracker'!Y$7:Y$93))+SUMPRODUCT(ISNUMBER(SEARCH($C16,'8. Activity Tracker'!$J$7:$J$93))*N('8. Activity Tracker'!Z$7:Z$93))+SUMPRODUCT(ISNUMBER(SEARCH($C16,'8. Activity Tracker'!$J$7:$J$93))*N('8. Activity Tracker'!AA$7:AA$93))+SUMPRODUCT(ISNUMBER(SEARCH($C16,'8. Activity Tracker'!$J$7:$J$93))*N('8. Activity Tracker'!AB$7:AB$93))+SUMPRODUCT(ISNUMBER(SEARCH($C16,'8. Activity Tracker'!$J$7:$J$93))*N('8. Activity Tracker'!AC$7:AC$93))),0)) | W16: =IFERROR(LOOKUP(2,1/(O16:V16<>""),O16:V16)/$M16,"") -> 0 | X16: =IFERROR(IF(COUNT(O16:V16)=0,"No data yet",IF(LOOKUP(2,1/(O16:V16<>""),O16:V16)>=INDEX(O10:V10,$C$3)*$M16,"On Track",IF(LOOKUP(2,1/(O16:V16<>""),O16:V16)>=INDEX(O10:V10,$C$3)*$M16*0.85,"Slightly Behind","Behind"))),"") -> Behind | Y16: CBLF enrolment registers, daily attendance sheets (compiled quarterly by MEAL focal points) | Z16: Source: enrolment registers maintained at CBLF level, daily attendance sheets completed by teaching volunteers. Method: recorded at facility level, compiled regularly by CBLF facilitators. Frequency: attendance recorded daily; enrolment and quality-monitoring data compiled, validated and reported quarterly by MEAL focal points. | AA16: Monthly PIB spot-check (min. 10% sample) of enrolment registers against attendance records; quarterly FIVDB-PIB reconciliation. | AB16: Attendance recorded daily; enrolment and quality-monitoring data compiled, validated and reported quarterly by MEAL focal points | AC16: MEAL Officer | AD16: Data consolidation, quality assurance & reporting | AE16: New arrivals/relocation may disrupt enrolment tracking; mitigate via regular registry updates and coordination with camp CiC. | AF16: =IFERROR("During the reporting period (cumulative through Q"&'7. IPTT'!$C$3&"), FIVDB reported "&TEXT(LOOKUP(2,1/(O16:V16<>""),O16:V16),"#,##0")&" against the indicator '"&$F16&"' - "&TEXT($W16,"0%")&" of the "&TEXT($M16,"#,##0")&" life-of-project target. "&"Disaggregated: "&TEXT($AH16,"#,##0")&" girls (<18), "&TEXT($AI16,"#,##0")&" boys (<18), "&TEXT($AJ16,"#,##0")&" women (18+), "&TEXT($AK16,"#,##0")&" men (18+).","During the reporting period, FIVDB reported progress against this indicator - see Cumulative Actual to Date and % of LOP Target Achieved.") -> During the reporting period (cumulative through Q1), FIVDB reported 0 against the indicator 'Number of targeted girls and boys enrolled in non-formal education services' - 0% of the 1,224 life-of-project target. Disaggregated: 0 girls (<18), 0 boys (<18), 0 women (18+), 0 men (18+). | AG16: Narrative Proposal, Result 1 Indicator 1: consortium Baseline 1,340 (SC's continuing learners from ECHO HIP 2023) / consortium Target 4,067 (SC 2,843: 2,293 girls, 550 boys; PLAN/FIVDB 1,224: 816 girls, 408 boys, >=3% disability). FIVDB's own baseline is 0 (out-of-school children, all new enrolment). FIVDB target 1,224 confirmed twice: Narrative Proposal AND FIVDB Detailed Budget (kits line item). CLARIFICATION: 1,224 = 816 girls + 408 boys, across 51 CBLFs (34 girls' + 17 boys') x 24 learners/facility x 2 shifts. Age range 11-18 (Narrative Proposal: 'children and adolescents aged 11-18... 51 CBLFs run by PLAN'). Minimum 3% (~37) with disability. Consortium total 4,067 = SC's 2,843 + FIVDB's 1,224 - FIVDB is not accountable for SC's share. | AH16: =IFERROR(SUMPRODUCT(ISNUMBER(SEARCH($C16,'10. Activity Data Log'!$AC$7:$AC$46))*(IFERROR(VALUE(MID('10. Activity Data Log'!$AD$7:$AD$46,2,1)),99)<='7. IPTT'!$C$3)*N('10. Activity Data Log'!$O$7:$O$46))+SUMPRODUCT(ISNUMBER(SEARCH($C16,'11. Distribution Log'!$AH$7:$AH$46))*(IFERROR(VALUE(MID('11. Distribution Log'!$AI$7:$AI$46,2,1)),99)<='7. IPTT'!$C$3)*N('11. Distribution Log'!$Q$7:$Q$46))+SUMPRODUCT(ISNUMBER(SEARCH($C16,'10. Activity Data Log'!$AC$7:$AC$46))*(IFERROR(VALUE(MID('10. Activity Data Log'!$AD$7:$AD$46,2,1)),99)<='7. IPTT'!$C$3)*N('10. Activity Data Log'!$S$7:$S$46))+SUMPRODUCT(ISNUMBER(SEARCH($C16,'11. Distribution Log'!$AH$7:$AH$46))*(IFERROR(VALUE(MID('11. Distribution Log'!$AI$7:$AI$46,2,1)),99)<='7. IPTT'!$C$3)*N('11. Distribution Log'!$U$7:$U$46)),0) -> 0 | AI16: =IFERROR(SUMPRODUCT(ISNUMBER(SEARCH($C16,'10. Activity Data Log'!$AC$7:$AC$46))*(IFERROR(VALUE(MID('10. Activity Data Log'!$AD$7:$AD$46,2,1)),99)<='7. IPTT'!$C$3)*N('10. Activity Data Log'!$M$7:$M$46))+SUMPRODUCT(ISNUMBER(SEARCH($C16,'11. Distribution Log'!$AH$7:$AH$46))*(IFERROR(VALUE(MID('11. Distribution Log'!$AI$7:$AI$46,2,1)),99)<='7. IPTT'!$C$3)*N('11. Distribution Log'!$O$7:$O$46))+SUMPRODUCT(ISNUMBER(SEARCH($C16,'10. Activity Data Log'!$AC$7:$AC$46))*(IFERROR(VALUE(MID('10. Activity Data Log'!$AD$7:$AD$46,2,1)),99)<='7. IPTT'!$C$3)*N('10. Activity Data Log'!$Q$7:$Q$46))+SUMPRODUCT(ISNUMBER(SEARCH($C16,'11. Distribution Log'!$AH$7:$AH$46))*(IFERROR(VALUE(MID('11. Distribution Log'!$AI$7:$AI$46,2,1)),99)<='7. IPTT'!$C$3)*N('11. Distribution Log'!$S$7:$S$46)),0) -> 0 | AJ16: =IFERROR(SUMPRODUCT(ISNUMBER(SEARCH($C16,'10. Activity Data Log'!$AC$7:$AC$46))*(IFERROR(VALUE(MID('10. Activity Data Log'!$AD$7:$AD$46,2,1)),99)<='7. IPTT'!$C$3)*N('10. Activity Data Log'!$P$7:$P$46))+SUMPRODUCT(ISNUMBER(SEARCH($C16,'11. Distribution Log'!$AH$7:$AH$46))*(IFERROR(VALUE(MID('11. Distribution Log'!$AI$7:$AI$46,2,1)),99)<='7. IPTT'!$C$3)*N('11. Distribution Log'!$R$7:$R$46))+SUMPRODUCT(ISNUMBER(SEARCH($C16,'10. Activity Data Log'!$AC$7:$AC$46))*(IFERROR(VALUE(MID('10. Activity Data Log'!$AD$7:$AD$46,2,1)),99)<='7. IPTT'!$C$3)*N('10. Activity Data Log'!$T$7:$T$46))+SUMPRODUCT(ISNUMBER(SEARCH($C16,'11. Distribution Log'!$AH$7:$AH$46))*(IFERROR(VALUE(MID('11. Distribution Log'!$AI$7:$AI$46,2,1)),99)<='7. IPTT'!$C$3)*N('11. Distribution Log'!$V$7:$V$46)),0) -> 0 | AK16: =IFERROR(SUMPRODUCT(ISNUMBER(SEARCH($C16,'10. Activity Data Log'!$AC$7:$AC$46))*(IFERROR(VALUE(MID('10. Activity Data Log'!$AD$7:$AD$46,2,1)),99)<='7. IPTT'!$C$3)*N('10. Activity Data Log'!$N$7:$N$46))+SUMPRODUCT(ISNUMBER(SEARCH($C16,'11. Distribution Log'!$AH$7:$AH$46))*(IFERROR(VALUE(MID('11. Distribution Log'!$AI$7:$AI$46,2,1)),99)<='7. IPTT'!$C$3)*N('11. Distribution Log'!$P$7:$P$46))+SUMPRODUCT(ISNUMBER(SEARCH($C16,'10. Activity Data Log'!$AC$7:$AC$46))*(IFERROR(VALUE(MID('10. Activity Data Log'!$AD$7:$AD$46,2,1)),99)<='7. IPTT'!$C$3)*N('10. Activity Data Log'!$R$7:$R$46))+SUMPRODUCT(ISNUMBER(SEARCH($C16,'11. Distribution Log'!$AH$7:$AH$46))*(IFERROR(VALUE(MID('11. Distribution Log'!$AI$7:$AI$46,2,1)),99)<='7. IPTT'!$C$3)*N('11. Distribution Log'!$T$7:$T$46)),0) -> 0
B17: Result 1 | C17: R1-I2 | D17: R1A2.6 | E17: R1A2.7, R1A2.8, INC-5, GEN-2 | F17: Number of learning spaces established or restored to minimum standards for safe learning | G17: Logframe (Annex I), Result 1 indicators - code R1-I2 | H17: Learning spaces reported as classroom units (or equivalent) where possible. Minimum standards for safe learning follow the Education Sector Standard guideline (INEE-aligned), covering DRR, safe routes to/from school, minimum accessibility/reasonable accommodation, GBV risk management, WASH standards and student perceptions of safety, with design/implementation gender- and age-responsive in line with the EU Gender-Age Marker. | I17: Site completion reports, infrastructure assessment and CBLF monitoring checklists, and teaching-volunteer/mentor supervision records, verified against the Education Sector Standard guideline (Annex - Education Sector's Standards). | J17: N/A (facility-level indicator) | K17: 0 | L17: - | M17: 51 | N17: Number | O17: =IF(1>'7. IPTT'!$C$3,"",IFERROR((SUMPRODUCT(ISNUMBER(SEARCH($C17,'8. Activity Tracker'!$J$7:$J$93))*N('8. Activity Tracker'!V$7:V$93))),0)) -> 0 | P17: =IF(2>'7. IPTT'!$C$3,"",IFERROR((SUMPRODUCT(ISNUMBER(SEARCH($C17,'8. Activity Tracker'!$J$7:$J$93))*N('8. Activity Tracker'!V$7:V$93))+SUMPRODUCT(ISNUMBER(SEARCH($C17,'8. Activity Tracker'!$J$7:$J$93))*N('8. Activity Tracker'!W$7:W$93))),0)) | Q17: =IF(3>'7. IPTT'!$C$3,"",IFERROR((SUMPRODUCT(ISNUMBER(SEARCH($C17,'8. Activity Tracker'!$J$7:$J$93))*N('8. Activity Tracker'!V$7:V$93))+SUMPRODUCT(ISNUMBER(SEARCH($C17,'8. Activity Tracker'!$J$7:$J$93))*N('8. Activity Tracker'!W$7:W$93))+SUMPRODUCT(ISNUMBER(SEARCH($C17,'8. Activity Tracker'!$J$7:$J$93))*N('8. Activity Tracker'!X$7:X$93))),0)) | R17: =IF(4>'7. IPTT'!$C$3,"",IFERROR((SUMPRODUCT(ISNUMBER(SEARCH($C17,'8. Activity Tracker'!$J$7:$J$93))*N('8. Activity Tracker'!V$7:V$93))+SUMPRODUCT(ISNUMBER(SEARCH($C17,'8. Activity Tracker'!$J$7:$J$93))*N('8. Activity Tracker'!W$7:W$93))+SUMPRODUCT(ISNUMBER(SEARCH($C17,'8. Activity Tracker'!$J$7:$J$93))*N('8. Activity Tracker'!X$7:X$93))+SUMPRODUCT(ISNUMBER(SEARCH($C17,'8. Activity Tracker'!$J$7:$J$93))*N('8. Activity Tracker'!Y$7:Y$93))),0)) | S17: =IF(5>'7. IPTT'!$C$3,"",IFERROR((SUMPRODUCT(ISNUMBER(SEARCH($C17,'8. Activity Tracker'!$J$7:$J$93))*N('8. Activity Tracker'!V$7:V$93))+SUMPRODUCT(ISNUMBER(SEARCH($C17,'8. Activity Tracker'!$J$7:$J$93))*N('8. Activity Tracker'!W$7:W$93))+SUMPRODUCT(ISNUMBER(SEARCH($C17,'8. Activity Tracker'!$J$7:$J$93))*N('8. Activity Tracker'!X$7:X$93))+SUMPRODUCT(ISNUMBER(SEARCH($C17,'8. Activity Tracker'!$J$7:$J$93))*N('8. Activity Tracker'!Y$7:Y$93))+SUMPRODUCT(ISNUMBER(SEARCH($C17,'8. Activity Tracker'!$J$7:$J$93))*N('8. Activity Tracker'!Z$7:Z$93))),0)) | T17: =IF(6>'7. IPTT'!$C$3,"",IFERROR((SUMPRODUCT(ISNUMBER(SEARCH($C17,'8. Activity Tracker'!$J$7:$J$93))*N('8. Activity Tracker'!V$7:V$93))+SUMPRODUCT(ISNUMBER(SEARCH($C17,'8. Activity Tracker'!$J$7:$J$93))*N('8. Activity Tracker'!W$7:W$93))+SUMPRODUCT(ISNUMBER(SEARCH($C17,'8. Activity Tracker'!$J$7:$J$93))*N('8. Activity Tracker'!X$7:X$93))+SUMPRODUCT(ISNUMBER(SEARCH($C17,'8. Activity Tracker'!$J$7:$J$93))*N('8. Activity Tracker'!Y$7:Y$93))+SUMPRODUCT(ISNUMBER(SEARCH($C17,'8. Activity Tracker'!$J$7:$J$93))*N('8. Activity Tracker'!Z$7:Z$93))+SUMPRODUCT(ISNUMBER(SEARCH($C17,'8. Activity Tracker'!$J$7:$J$93))*N('8. Activity Tracker'!AA$7:AA$93))),0)) | U17: =IF(7>'7. IPTT'!$C$3,"",IFERROR((SUMPRODUCT(ISNUMBER(SEARCH($C17,'8. Activity Tracker'!$J$7:$J$93))*N('8. Activity Tracker'!V$7:V$93))+SUMPRODUCT(ISNUMBER(SEARCH($C17,'8. Activity Tracker'!$J$7:$J$93))*N('8. Activity Tracker'!W$7:W$93))+SUMPRODUCT(ISNUMBER(SEARCH($C17,'8. Activity Tracker'!$J$7:$J$93))*N('8. Activity Tracker'!X$7:X$93))+SUMPRODUCT(ISNUMBER(SEARCH($C17,'8. Activity Tracker'!$J$7:$J$93))*N('8. Activity Tracker'!Y$7:Y$93))+SUMPRODUCT(ISNUMBER(SEARCH($C17,'8. Activity Tracker'!$J$7:$J$93))*N('8. Activity Tracker'!Z$7:Z$93))+SUMPRODUCT(ISNUMBER(SEARCH($C17,'8. Activity Tracker'!$J$7:$J$93))*N('8. Activity Tracker'!AA$7:AA$93))+SUMPRODUCT(ISNUMBER(SEARCH($C17,'8. Activity Tracker'!$J$7:$J$93))*N('8. Activity Tracker'!AB$7:AB$93))),0)) | V17: =IF(8>'7. IPTT'!$C$3,"",IFERROR((SUMPRODUCT(ISNUMBER(SEARCH($C17,'8. Activity Tracker'!$J$7:$J$93))*N('8. Activity Tracker'!V$7:V$93))+SUMPRODUCT(ISNUMBER(SEARCH($C17,'8. Activity Tracker'!$J$7:$J$93))*N('8. Activity Tracker'!W$7:W$93))+SUMPRODUCT(ISNUMBER(SEARCH($C17,'8. Activity Tracker'!$J$7:$J$93))*N('8. Activity Tracker'!X$7:X$93))+SUMPRODUCT(ISNUMBER(SEARCH($C17,'8. Activity Tracker'!$J$7:$J$93))*N('8. Activity Tracker'!Y$7:Y$93))+SUMPRODUCT(ISNUMBER(SEARCH($C17,'8. Activity Tracker'!$J$7:$J$93))*N('8. Activity Tracker'!Z$7:Z$93))+SUMPRODUCT(ISNUMBER(SEARCH($C17,'8. Activity Tracker'!$J$7:$J$93))*N('8. Activity Tracker'!AA$7:AA$93))+SUMPRODUCT(ISNUMBER(SEARCH($C17,'8. Activity Tracker'!$J$7:$J$93))*N('8. Activity Tracker'!AB$7:AB$93))+SUMPRODUCT(ISNUMBER(SEARCH($C17,'8. Activity Tracker'!$J$7:$J$93))*N('8. Activity Tracker'!AC$7:AC$93))),0)) | W17: =IFERROR(LOOKUP(2,1/(O17:V17<>""),O17:V17)/$M17,"") -> 0 | X17: =IFERROR(IF(COUNT(O17:V17)=0,"No data yet",IF(LOOKUP(2,1/(O17:V17<>""),O17:V17)>=INDEX(O10:V10,$C$3)*$M17,"On Track",IF(LOOKUP(2,1/(O17:V17<>""),O17:V17)>=INDEX(O10:V10,$C$3)*$M17*0.85,"Slightly Behind","Behind"))),"") -> Behind | Y17: Site completion reports, infrastructure assessment, CBLF monitoring checklists, photographic documentation | Z17: Source: site completion reports, infrastructure assessment, CBLF monitoring checklists, teaching-volunteer/mentor supervision records. Method: verified against the Education Sector Standard guideline (Annex - Education Sector's Standards). Frequency: regular site visits and monitoring visits by programme and MEAL teams; cross-checked through document review and field validation. | AA17: Quarterly joint FIVDB-PIB site visit against the Facility Monitoring Checklist; photographic evidence retained. | AB17: Regular site visits and monitoring visits by programme and MEAL teams; cross-checked through document review and field validation | AC17: Education Officer | AD17: Field data collection & first-line reporting | AE17: Delays in rehab/construction approvals or procurement of materials (solar, fencing) may push completion into later quarters. | AF17: =IFERROR("During the reporting period (cumulative through Q"&'7. IPTT'!$C$3&"), FIVDB reported "&TEXT(LOOKUP(2,1/(O17:V17<>""),O17:V17),"#,##0")&" against the indicator '"&$F17&"' - "&TEXT($W17,"0%")&" of the "&TEXT($M17,"#,##0")&" life-of-project target. "&"Disaggregated: "&TEXT($AH17,"#,##0")&" girls (<18), "&TEXT($AI17,"#,##0")&" boys (<18), "&TEXT($AJ17,"#,##0")&" women (18+), "&TEXT($AK17,"#,##0")&" men (18+).","During the reporting period, FIVDB reported progress against this indicator - see Cumulative Actual to Date and % of LOP Target Achieved.") -> During the reporting period (cumulative through Q1), FIVDB reported 0 against the indicator 'Number of learning spaces established or restored to minimum standards for safe learning' - 0% of the 51 life-of-project target. Disaggregated: 0 girls (<18), 0 boys (<18), 0 women (18+), 0 men (18+). | AG17: Narrative Proposal, Result 1 Indicator 2: consortium Baseline 66 (SC's existing CBLFs maintained since ECHO HIP 2023) / consortium Target 121 (SC 70: 62 CBLFs+5 GoLFs+1 girls club+1 boys club+1 MPC; PLAN/FIVDB 51 new CBLFs). FIVDB's own baseline is 0 (all 51 CBLFs newly established under this action). CLARIFICATION: 51 = 16 (Camp 1W) + 15 (Camp 6) + 10 (Camp 21) + 10 (Camp 24), per Annex 3 site mapping. All 51 are NEW facilities (FIVDB's own baseline = 0); SC's 70 are separately maintained/continuing facilities from a prior phase, not part of FIVDB's count. | AH17: =IFERROR(SUMPRODUCT(ISNUMBER(SEARCH($C17,'10. Activity Data Log'!$AC$7:$AC$46))*(IFERROR(VALUE(MID('10. Activity Data Log'!$AD$7:$AD$46,2,1)),99)<='7. IPTT'!$C$3)*N('10. Activity Data Log'!$O$7:$O$46))+SUMPRODUCT(ISNUMBER(SEARCH($C17,'11. Distribution Log'!$AH$7:$AH$46))*(IFERROR(VALUE(MID('11. Distribution Log'!$AI$7:$AI$46,2,1)),99)<='7. IPTT'!$C$3)*N('11. Distribution Log'!$Q$7:$Q$46))+SUMPRODUCT(ISNUMBER(SEARCH($C17,'10. Activity Data Log'!$AC$7:$AC$46))*(IFERROR(VALUE(MID('10. Activity Data Log'!$AD$7:$AD$46,2,1)),99)<='7. IPTT'!$C$3)*N('10. Activity Data Log'!$S$7:$S$46))+SUMPRODUCT(ISNUMBER(SEARCH($C17,'11. Distribution Log'!$AH$7:$AH$46))*(IFERROR(VALUE(MID('11. Distribution Log'!$AI$7:$AI$46,2,1)),99)<='7. IPTT'!$C$3)*N('11. Distribution Log'!$U$7:$U$46)),0) -> 0 | AI17: =IFERROR(SUMPRODUCT(ISNUMBER(SEARCH($C17,'10. Activity Data Log'!$AC$7:$AC$46))*(IFERROR(VALUE(MID('10. Activity Data Log'!$AD$7:$AD$46,2,1)),99)<='7. IPTT'!$C$3)*N('10. Activity Data Log'!$M$7:$M$46))+SUMPRODUCT(ISNUMBER(SEARCH($C17,'11. Distribution Log'!$AH$7:$AH$46))*(IFERROR(VALUE(MID('11. Distribution Log'!$AI$7:$AI$46,2,1)),99)<='7. IPTT'!$C$3)*N('11. Distribution Log'!$O$7:$O$46))+SUMPRODUCT(ISNUMBER(SEARCH($C17,'10. Activity Data Log'!$AC$7:$AC$46))*(IFERROR(VALUE(MID('10. Activity Data Log'!$AD$7:$AD$46,2,1)),99)<='7. IPTT'!$C$3)*N('10. Activity Data Log'!$Q$7:$Q$46))+SUMPRODUCT(ISNUMBER(SEARCH($C17,'11. Distribution Log'!$AH$7:$AH$46))*(IFERROR(VALUE(MID('11. Distribution Log'!$AI$7:$AI$46,2,1)),99)<='7. IPTT'!$C$3)*N('11. Distribution Log'!$S$7:$S$46)),0) -> 0 | AJ17: =IFERROR(SUMPRODUCT(ISNUMBER(SEARCH($C17,'10. Activity Data Log'!$AC$7:$AC$46))*(IFERROR(VALUE(MID('10. Activity Data Log'!$AD$7:$AD$46,2,1)),99)<='7. IPTT'!$C$3)*N('10. Activity Data Log'!$P$7:$P$46))+SUMPRODUCT(ISNUMBER(SEARCH($C17,'11. Distribution Log'!$AH$7:$AH$46))*(IFERROR(VALUE(MID('11. Distribution Log'!$AI$7:$AI$46,2,1)),99)<='7. IPTT'!$C$3)*N('11. Distribution Log'!$R$7:$R$46))+SUMPRODUCT(ISNUMBER(SEARCH($C17,'10. Activity Data Log'!$AC$7:$AC$46))*(IFERROR(VALUE(MID('10. Activity Data Log'!$AD$7:$AD$46,2,1)),99)<='7. IPTT'!$C$3)*N('10. Activity Data Log'!$T$7:$T$46))+SUMPRODUCT(ISNUMBER(SEARCH($C17,'11. Distribution Log'!$AH$7:$AH$46))*(IFERROR(VALUE(MID('11. Distribution Log'!$AI$7:$AI$46,2,1)),99)<='7. IPTT'!$C$3)*N('11. Distribution Log'!$V$7:$V$46)),0) -> 0 | AK17: =IFERROR(SUMPRODUCT(ISNUMBER(SEARCH($C17,'10. Activity Data Log'!$AC$7:$AC$46))*(IFERROR(VALUE(MID('10. Activity Data Log'!$AD$7:$AD$46,2,1)),99)<='7. IPTT'!$C$3)*N('10. Activity Data Log'!$N$7:$N$46))+SUMPRODUCT(ISNUMBER(SEARCH($C17,'11. Distribution Log'!$AH$7:$AH$46))*(IFERROR(VALUE(MID('11. Distribution Log'!$AI$7:$AI$46,2,1)),99)<='7. IPTT'!$C$3)*N('11. Distribution Log'!$P$7:$P$46))+SUMPRODUCT(ISNUMBER(SEARCH($C17,'10. Activity Data Log'!$AC$7:$AC$46))*(IFERROR(VALUE(MID('10. Activity Data Log'!$AD$7:$AD$46,2,1)),99)<='7. IPTT'!$C$3)*N('10. Activity Data Log'!$R$7:$R$46))+SUMPRODUCT(ISNUMBER(SEARCH($C17,'11. Distribution Log'!$AH$7:$AH$46))*(IFERROR(VALUE(MID('11. Distribution Log'!$AI$7:$AI$46,2,1)),99)<='7. IPTT'!$C$3)*N('11. Distribution Log'!$T$7:$T$46)),0) -> 0
B18: Result 1 | C18: R1-I3 | D18: R1A2.1 | E18: R1A2.2, R1A2.10, R1A2.11 | F18: Number of teachers provided with teaching aids/materials | G18: Logframe (Annex I), Result 1 indicators - code R1-I3 | H18: Minimum package = blackboard (or equivalent), textbooks/teaching guides and stationery, including adaptations for teachers/learners with disabilities and materials tailored to identified language needs. Materials may be supplied directly or via logistical/technical/advocacy support to education authorities. Disaggregate by sex, NFE type/level of education and disability. | I18: Distribution lists, signed receipt forms, muster rolls, attendance sheets and inventory records maintained at partner and learning-facility level, documenting provision of teaching aids/materials to targeted teachers. | J18: Sex, level of education, disability | K18: 0 | L18: - | M18: 68 | N18: Number | O18: =IF(1>'7. IPTT'!$C$3,"",IFERROR((SUMPRODUCT(ISNUMBER(SEARCH($C18,'8. Activity Tracker'!$J$7:$J$93))*N('8. Activity Tracker'!V$7:V$93))),0)) -> 0 | P18: =IF(2>'7. IPTT'!$C$3,"",IFERROR((SUMPRODUCT(ISNUMBER(SEARCH($C18,'8. Activity Tracker'!$J$7:$J$93))*N('8. Activity Tracker'!V$7:V$93))+SUMPRODUCT(ISNUMBER(SEARCH($C18,'8. Activity Tracker'!$J$7:$J$93))*N('8. Activity Tracker'!W$7:W$93))),0)) | Q18: =IF(3>'7. IPTT'!$C$3,"",IFERROR((SUMPRODUCT(ISNUMBER(SEARCH($C18,'8. Activity Tracker'!$J$7:$J$93))*N('8. Activity Tracker'!V$7:V$93))+SUMPRODUCT(ISNUMBER(SEARCH($C18,'8. Activity Tracker'!$J$7:$J$93))*N('8. Activity Tracker'!W$7:W$93))+SUMPRODUCT(ISNUMBER(SEARCH($C18,'8. Activity Tracker'!$J$7:$J$93))*N('8. Activity Tracker'!X$7:X$93))),0)) | R18: =IF(4>'7. IPTT'!$C$3,"",IFERROR((SUMPRODUCT(ISNUMBER(SEARCH($C18,'8. Activity Tracker'!$J$7:$J$93))*N('8. Activity Tracker'!V$7:V$93))+SUMPRODUCT(ISNUMBER(SEARCH($C18,'8. Activity Tracker'!$J$7:$J$93))*N('8. Activity Tracker'!W$7:W$93))+SUMPRODUCT(ISNUMBER(SEARCH($C18,'8. Activity Tracker'!$J$7:$J$93))*N('8. Activity Tracker'!X$7:X$93))+SUMPRODUCT(ISNUMBER(SEARCH($C18,'8. Activity Tracker'!$J$7:$J$93))*N('8. Activity Tracker'!Y$7:Y$93))),0)) | S18: =IF(5>'7. IPTT'!$C$3,"",IFERROR((SUMPRODUCT(ISNUMBER(SEARCH($C18,'8. Activity Tracker'!$J$7:$J$93))*N('8. Activity Tracker'!V$7:V$93))+SUMPRODUCT(ISNUMBER(SEARCH($C18,'8. Activity Tracker'!$J$7:$J$93))*N('8. Activity Tracker'!W$7:W$93))+SUMPRODUCT(ISNUMBER(SEARCH($C18,'8. Activity Tracker'!$J$7:$J$93))*N('8. Activity Tracker'!X$7:X$93))+SUMPRODUCT(ISNUMBER(SEARCH($C18,'8. Activity Tracker'!$J$7:$J$93))*N('8. Activity Tracker'!Y$7:Y$93))+SUMPRODUCT(ISNUMBER(SEARCH($C18,'8. Activity Tracker'!$J$7:$J$93))*N('8. Activity Tracker'!Z$7:Z$93))),0)) | T18: =IF(6>'7. IPTT'!$C$3,"",IFERROR((SUMPRODUCT(ISNUMBER(SEARCH($C18,'8. Activity Tracker'!$J$7:$J$93))*N('8. Activity Tracker'!V$7:V$93))+SUMPRODUCT(ISNUMBER(SEARCH($C18,'8. Activity Tracker'!$J$7:$J$93))*N('8. Activity Tracker'!W$7:W$93))+SUMPRODUCT(ISNUMBER(SEARCH($C18,'8. Activity Tracker'!$J$7:$J$93))*N('8. Activity Tracker'!X$7:X$93))+SUMPRODUCT(ISNUMBER(SEARCH($C18,'8. Activity Tracker'!$J$7:$J$93))*N('8. Activity Tracker'!Y$7:Y$93))+SUMPRODUCT(ISNUMBER(SEARCH($C18,'8. Activity Tracker'!$J$7:$J$93))*N('8. Activity Tracker'!Z$7:Z$93))+SUMPRODUCT(ISNUMBER(SEARCH($C18,'8. Activity Tracker'!$J$7:$J$93))*N('8. Activity Tracker'!AA$7:AA$93))),0)) | U18: =IF(7>'7. IPTT'!$C$3,"",IFERROR((SUMPRODUCT(ISNUMBER(SEARCH($C18,'8. Activity Tracker'!$J$7:$J$93))*N('8. Activity Tracker'!V$7:V$93))+SUMPRODUCT(ISNUMBER(SEARCH($C18,'8. Activity Tracker'!$J$7:$J$93))*N('8. Activity Tracker'!W$7:W$93))+SUMPRODUCT(ISNUMBER(SEARCH($C18,'8. Activity Tracker'!$J$7:$J$93))*N('8. Activity Tracker'!X$7:X$93))+SUMPRODUCT(ISNUMBER(SEARCH($C18,'8. Activity Tracker'!$J$7:$J$93))*N('8. Activity Tracker'!Y$7:Y$93))+SUMPRODUCT(ISNUMBER(SEARCH($C18,'8. Activity Tracker'!$J$7:$J$93))*N('8. Activity Tracker'!Z$7:Z$93))+SUMPRODUCT(ISNUMBER(SEARCH($C18,'8. Activity Tracker'!$J$7:$J$93))*N('8. Activity Tracker'!AA$7:AA$93))+SUMPRODUCT(ISNUMBER(SEARCH($C18,'8. Activity Tracker'!$J$7:$J$93))*N('8. Activity Tracker'!AB$7:AB$93))),0)) | V18: =IF(8>'7. IPTT'!$C$3,"",IFERROR((SUMPRODUCT(ISNUMBER(SEARCH($C18,'8. Activity Tracker'!$J$7:$J$93))*N('8. Activity Tracker'!V$7:V$93))+SUMPRODUCT(ISNUMBER(SEARCH($C18,'8. Activity Tracker'!$J$7:$J$93))*N('8. Activity Tracker'!W$7:W$93))+SUMPRODUCT(ISNUMBER(SEARCH($C18,'8. Activity Tracker'!$J$7:$J$93))*N('8. Activity Tracker'!X$7:X$93))+SUMPRODUCT(ISNUMBER(SEARCH($C18,'8. Activity Tracker'!$J$7:$J$93))*N('8. Activity Tracker'!Y$7:Y$93))+SUMPRODUCT(ISNUMBER(SEARCH($C18,'8. Activity Tracker'!$J$7:$J$93))*N('8. Activity Tracker'!Z$7:Z$93))+SUMPRODUCT(ISNUMBER(SEARCH($C18,'8. Activity Tracker'!$J$7:$J$93))*N('8. Activity Tracker'!AA$7:AA$93))+SUMPRODUCT(ISNUMBER(SEARCH($C18,'8. Activity Tracker'!$J$7:$J$93))*N('8. Activity Tracker'!AB$7:AB$93))+SUMPRODUCT(ISNUMBER(SEARCH($C18,'8. Activity Tracker'!$J$7:$J$93))*N('8. Activity Tracker'!AC$7:AC$93))),0)) | W18: =IFERROR(LOOKUP(2,1/(O18:V18<>""),O18:V18)/$M18,"") -> 0 | X18: =IFERROR(IF(COUNT(O18:V18)=0,"No data yet",IF(LOOKUP(2,1/(O18:V18<>""),O18:V18)>=INDEX(O10:V10,$C$3)*$M18,"On Track",IF(LOOKUP(2,1/(O18:V18<>""),O18:V18)>=INDEX(O10:V10,$C$3)*$M18*0.85,"Slightly Behind","Behind"))),"") -> Behind | Y18: Distribution lists, signed receipt forms, muster rolls, inventory records | Z18: Source: distribution lists, signed receipt forms, muster rolls, attendance sheets, inventory records. Method: maintained at partner and learning-facility level. Frequency: compiled and validated by programme/MEAL staff prior to reporting; verified through routine monitoring visits and spot checks. | AA18: Signed waybills cross-checked against teacher roster; PIB logistics spot-check per distribution round. | AB18: Compiled and validated by programme/MEAL staff prior to reporting; verified through routine monitoring visits and spot checks | AC18: Education Officer | AD18: Field data collection & first-line reporting | AE18: Procurement/supply-chain delays (printing, customs/import for specialised materials) may delay distribution. | AF18: =IFERROR("During the reporting period (cumulative through Q"&'7. IPTT'!$C$3&"), FIVDB reported "&TEXT(LOOKUP(2,1/(O18:V18<>""),O18:V18),"#,##0")&" against the indicator '"&$F18&"' - "&TEXT($W18,"0%")&" of the "&TEXT($M18,"#,##0")&" life-of-project target. "&"Disaggregated: "&TEXT($AH18,"#,##0")&" girls (<18), "&TEXT($AI18,"#,##0")&" boys (<18), "&TEXT($AJ18,"#,##0")&" women (18+), "&TEXT($AK18,"#,##0")&" men (18+).","During the reporting period, FIVDB reported progress against this indicator - see Cumulative Actual to Date and % of LOP Target Achieved.") -> During the reporting period (cumulative through Q1), FIVDB reported 0 against the indicator 'Number of teachers provided with teaching aids/materials' - 0% of the 68 life-of-project target. Disaggregated: 0 girls (<18), 0 boys (<18), 0 women (18+), 0 men (18+). | AG18: Narrative Proposal, Result 1 Indicator 3: consortium Baseline 93 (SC's continuing teachers from prior action) / consortium Target 168 (SC 100: 79 female, 21 male; PLAN/FIVDB 68: 45 female, 23 male - 51 Rohingya + 17 host). FIVDB's own baseline is 0 (all 68 teachers newly supported under this action). CLARIFICATION: 68 = 1 teacher per CBLF x 51 CBLFs + 17 additional host-community teachers = 45 female + 23 male. | AH18: =IFERROR(SUMPRODUCT(ISNUMBER(SEARCH($C18,'10. Activity Data Log'!$AC$7:$AC$46))*(IFERROR(VALUE(MID('10. Activity Data Log'!$AD$7:$AD$46,2,1)),99)<='7. IPTT'!$C$3)*N('10. Activity Data Log'!$O$7:$O$46))+SUMPRODUCT(ISNUMBER(SEARCH($C18,'11. Distribution Log'!$AH$7:$AH$46))*(IFERROR(VALUE(MID('11. Distribution Log'!$AI$7:$AI$46,2,1)),99)<='7. IPTT'!$C$3)*N('11. Distribution Log'!$Q$7:$Q$46))+SUMPRODUCT(ISNUMBER(SEARCH($C18,'10. Activity Data Log'!$AC$7:$AC$46))*(IFERROR(VALUE(MID('10. Activity Data Log'!$AD$7:$AD$46,2,1)),99)<='7. IPTT'!$C$3)*N('10. Activity Data Log'!$S$7:$S$46))+SUMPRODUCT(ISNUMBER(SEARCH($C18,'11. Distribution Log'!$AH$7:$AH$46))*(IFERROR(VALUE(MID('11. Distribution Log'!$AI$7:$AI$46,2,1)),99)<='7. IPTT'!$C$3)*N('11. Distribution Log'!$U$7:$U$46)),0) -> 0 | AI18: =IFERROR(SUMPRODUCT(ISNUMBER(SEARCH($C18,'10. Activity Data Log'!$AC$7:$AC$46))*(IFERROR(VALUE(MID('10. Activity Data Log'!$AD$7:$AD$46,2,1)),99)<='7. IPTT'!$C$3)*N('10. Activity Data Log'!$M$7:$M$46))+SUMPRODUCT(ISNUMBER(SEARCH($C18,'11. Distribution Log'!$AH$7:$AH$46))*(IFERROR(VALUE(MID('11. Distribution Log'!$AI$7:$AI$46,2,1)),99)<='7. IPTT'!$C$3)*N('11. Distribution Log'!$O$7:$O$46))+SUMPRODUCT(ISNUMBER(SEARCH($C18,'10. Activity Data Log'!$AC$7:$AC$46))*(IFERROR(VALUE(MID('10. Activity Data Log'!$AD$7:$AD$46,2,1)),99)<='7. IPTT'!$C$3)*N('10. Activity Data Log'!$Q$7:$Q$46))+SUMPRODUCT(ISNUMBER(SEARCH($C18,'11. Distribution Log'!$AH$7:$AH$46))*(IFERROR(VALUE(MID('11. Distribution Log'!$AI$7:$AI$46,2,1)),99)<='7. IPTT'!$C$3)*N('11. Distribution Log'!$S$7:$S$46)),0) -> 0 | AJ18: =IFERROR(SUMPRODUCT(ISNUMBER(SEARCH($C18,'10. Activity Data Log'!$AC$7:$AC$46))*(IFERROR(VALUE(MID('10. Activity Data Log'!$AD$7:$AD$46,2,1)),99)<='7. IPTT'!$C$3)*N('10. Activity Data Log'!$P$7:$P$46))+SUMPRODUCT(ISNUMBER(SEARCH($C18,'11. Distribution Log'!$AH$7:$AH$46))*(IFERROR(VALUE(MID('11. Distribution Log'!$AI$7:$AI$46,2,1)),99)<='7. IPTT'!$C$3)*N('11. Distribution Log'!$R$7:$R$46))+SUMPRODUCT(ISNUMBER(SEARCH($C18,'10. Activity Data Log'!$AC$7:$AC$46))*(IFERROR(VALUE(MID('10. Activity Data Log'!$AD$7:$AD$46,2,1)),99)<='7. IPTT'!$C$3)*N('10. Activity Data Log'!$T$7:$T$46))+SUMPRODUCT(ISNUMBER(SEARCH($C18,'11. Distribution Log'!$AH$7:$AH$46))*(IFERROR(VALUE(MID('11. Distribution Log'!$AI$7:$AI$46,2,1)),99)<='7. IPTT'!$C$3)*N('11. Distribution Log'!$V$7:$V$46)),0) -> 0 | AK18: =IFERROR(SUMPRODUCT(ISNUMBER(SEARCH($C18,'10. Activity Data Log'!$AC$7:$AC$46))*(IFERROR(VALUE(MID('10. Activity Data Log'!$AD$7:$AD$46,2,1)),99)<='7. IPTT'!$C$3)*N('10. Activity Data Log'!$N$7:$N$46))+SUMPRODUCT(ISNUMBER(SEARCH($C18,'11. Distribution Log'!$AH$7:$AH$46))*(IFERROR(VALUE(MID('11. Distribution Log'!$AI$7:$AI$46,2,1)),99)<='7. IPTT'!$C$3)*N('11. Distribution Log'!$P$7:$P$46))+SUMPRODUCT(ISNUMBER(SEARCH($C18,'10. Activity Data Log'!$AC$7:$AC$46))*(IFERROR(VALUE(MID('10. Activity Data Log'!$AD$7:$AD$46,2,1)),99)<='7. IPTT'!$C$3)*N('10. Activity Data Log'!$R$7:$R$46))+SUMPRODUCT(ISNUMBER(SEARCH($C18,'11. Distribution Log'!$AH$7:$AH$46))*(IFERROR(VALUE(MID('11. Distribution Log'!$AI$7:$AI$46,2,1)),99)<='7. IPTT'!$C$3)*N('11. Distribution Log'!$T$7:$T$46)),0) -> 0
B19: Result 1 | C19: R1-I4 | D19: R1A2.3 | E19: R1A2.4, R1A2.5, R1A3.1 | F19: Number of girls and boys provided with learning materials | G19: Logframe (Annex I), Result 1 indicators - code R1-I4 | H19: Minimum package = textbooks (or equivalent), reading materials and stationery, including adaptations for learners with disabilities and materials tailored to identified language needs. Where kits are provided per classroom, a content breakdown must justify reasonable provision per child. Disaggregate by sex, NFE type/level of education and disability. | I19: Distribution lists and learner registers at facility level, with signed beneficiary receipts as primary evidence, verified through Post-Distribution Monitoring (PDM) surveys including PM KOI questions and CBLF monitoring reports. | J19: Sex, level of education, disability | K19: 0 | L19: - | M19: 1224 | N19: Number | O19: =IF(1>'7. IPTT'!$C$3,"",IFERROR((SUMPRODUCT(ISNUMBER(SEARCH($C19,'8. Activity Tracker'!$J$7:$J$93))*N('8. Activity Tracker'!V$7:V$93))),0)) -> 0 | P19: =IF(2>'7. IPTT'!$C$3,"",IFERROR((SUMPRODUCT(ISNUMBER(SEARCH($C19,'8. Activity Tracker'!$J$7:$J$93))*N('8. Activity Tracker'!V$7:V$93))+SUMPRODUCT(ISNUMBER(SEARCH($C19,'8. Activity Tracker'!$J$7:$J$93))*N('8. Activity Tracker'!W$7:W$93))),0)) | Q19: =IF(3>'7. IPTT'!$C$3,"",IFERROR((SUMPRODUCT(ISNUMBER(SEARCH($C19,'8. Activity Tracker'!$J$7:$J$93))*N('8. Activity Tracker'!V$7:V$93))+SUMPRODUCT(ISNUMBER(SEARCH($C19,'8. Activity Tracker'!$J$7:$J$93))*N('8. Activity Tracker'!W$7:W$93))+SUMPRODUCT(ISNUMBER(SEARCH($C19,'8. Activity Tracker'!$J$7:$J$93))*N('8. Activity Tracker'!X$7:X$93))),0)) | R19: =IF(4>'7. IPTT'!$C$3,"",IFERROR((SUMPRODUCT(ISNUMBER(SEARCH($C19,'8. Activity Tracker'!$J$7:$J$93))*N('8. Activity Tracker'!V$7:V$93))+SUMPRODUCT(ISNUMBER(SEARCH($C19,'8. Activity Tracker'!$J$7:$J$93))*N('8. Activity Tracker'!W$7:W$93))+SUMPRODUCT(ISNUMBER(SEARCH($C19,'8. Activity Tracker'!$J$7:$J$93))*N('8. Activity Tracker'!X$7:X$93))+SUMPRODUCT(ISNUMBER(SEARCH($C19,'8. Activity Tracker'!$J$7:$J$93))*N('8. Activity Tracker'!Y$7:Y$93))),0)) | S19: =IF(5>'7. IPTT'!$C$3,"",IFERROR((SUMPRODUCT(ISNUMBER(SEARCH($C19,'8. Activity Tracker'!$J$7:$J$93))*N('8. Activity Tracker'!V$7:V$93))+SUMPRODUCT(ISNUMBER(SEARCH($C19,'8. Activity Tracker'!$J$7:$J$93))*N('8. Activity Tracker'!W$7:W$93))+SUMPRODUCT(ISNUMBER(SEARCH($C19,'8. Activity Tracker'!$J$7:$J$93))*N('8. Activity Tracker'!X$7:X$93))+SUMPRODUCT(ISNUMBER(SEARCH($C19,'8. Activity Tracker'!$J$7:$J$93))*N('8. Activity Tracker'!Y$7:Y$93))+SUMPRODUCT(ISNUMBER(SEARCH($C19,'8. Activity Tracker'!$J$7:$J$93))*N('8. Activity Tracker'!Z$7:Z$93))),0)) | T19: =IF(6>'7. IPTT'!$C$3,"",IFERROR((SUMPRODUCT(ISNUMBER(SEARCH($C19,'8. Activity Tracker'!$J$7:$J$93))*N('8. Activity Tracker'!V$7:V$93))+SUMPRODUCT(ISNUMBER(SEARCH($C19,'8. Activity Tracker'!$J$7:$J$93))*N('8. Activity Tracker'!W$7:W$93))+SUMPRODUCT(ISNUMBER(SEARCH($C19,'8. Activity Tracker'!$J$7:$J$93))*N('8. Activity Tracker'!X$7:X$93))+SUMPRODUCT(ISNUMBER(SEARCH($C19,'8. Activity Tracker'!$J$7:$J$93))*N('8. Activity Tracker'!Y$7:Y$93))+SUMPRODUCT(ISNUMBER(SEARCH($C19,'8. Activity Tracker'!$J$7:$J$93))*N('8. Activity Tracker'!Z$7:Z$93))+SUMPRODUCT(ISNUMBER(SEARCH($C19,'8. Activity Tracker'!$J$7:$J$93))*N('8. Activity Tracker'!AA$7:AA$93))),0)) | U19: =IF(7>'7. IPTT'!$C$3,"",IFERROR((SUMPRODUCT(ISNUMBER(SEARCH($C19,'8. Activity Tracker'!$J$7:$J$93))*N('8. Activity Tracker'!V$7:V$93))+SUMPRODUCT(ISNUMBER(SEARCH($C19,'8. Activity Tracker'!$J$7:$J$93))*N('8. Activity Tracker'!W$7:W$93))+SUMPRODUCT(ISNUMBER(SEARCH($C19,'8. Activity Tracker'!$J$7:$J$93))*N('8. Activity Tracker'!X$7:X$93))+SUMPRODUCT(ISNUMBER(SEARCH($C19,'8. Activity Tracker'!$J$7:$J$93))*N('8. Activity Tracker'!Y$7:Y$93))+SUMPRODUCT(ISNUMBER(SEARCH($C19,'8. Activity Tracker'!$J$7:$J$93))*N('8. Activity Tracker'!Z$7:Z$93))+SUMPRODUCT(ISNUMBER(SEARCH($C19,'8. Activity Tracker'!$J$7:$J$93))*N('8. Activity Tracker'!AA$7:AA$93))+SUMPRODUCT(ISNUMBER(SEARCH($C19,'8. Activity Tracker'!$J$7:$J$93))*N('8. Activity Tracker'!AB$7:AB$93))),0)) | V19: =IF(8>'7. IPTT'!$C$3,"",IFERROR((SUMPRODUCT(ISNUMBER(SEARCH($C19,'8. Activity Tracker'!$J$7:$J$93))*N('8. Activity Tracker'!V$7:V$93))+SUMPRODUCT(ISNUMBER(SEARCH($C19,'8. Activity Tracker'!$J$7:$J$93))*N('8. Activity Tracker'!W$7:W$93))+SUMPRODUCT(ISNUMBER(SEARCH($C19,'8. Activity Tracker'!$J$7:$J$93))*N('8. Activity Tracker'!X$7:X$93))+SUMPRODUCT(ISNUMBER(SEARCH($C19,'8. Activity Tracker'!$J$7:$J$93))*N('8. Activity Tracker'!Y$7:Y$93))+SUMPRODUCT(ISNUMBER(SEARCH($C19,'8. Activity Tracker'!$J$7:$J$93))*N('8. Activity Tracker'!Z$7:Z$93))+SUMPRODUCT(ISNUMBER(SEARCH($C19,'8. Activity Tracker'!$J$7:$J$93))*N('8. Activity Tracker'!AA$7:AA$93))+SUMPRODUCT(ISNUMBER(SEARCH($C19,'8. Activity Tracker'!$J$7:$J$93))*N('8. Activity Tracker'!AB$7:AB$93))+SUMPRODUCT(ISNUMBER(SEARCH($C19,'8. Activity Tracker'!$J$7:$J$93))*N('8. Activity Tracker'!AC$7:AC$93))),0)) | W19: =IFERROR(LOOKUP(2,1/(O19:V19<>""),O19:V19)/$M19,"") -> 0 | X19: =IFERROR(IF(COUNT(O19:V19)=0,"No data yet",IF(LOOKUP(2,1/(O19:V19<>""),O19:V19)>=INDEX(O10:V10,$C$3)*$M19,"On Track",IF(LOOKUP(2,1/(O19:V19<>""),O19:V19)>=INDEX(O10:V10,$C$3)*$M19*0.85,"Slightly Behind","Behind"))),"") -> Behind | Y19: Distribution lists, learner registers, signed beneficiary receipts, PDM survey | Z19: Source: distribution lists, learner registers at facility level, signed beneficiary receipts. Method: verified through Post-Distribution Monitoring (PDM) surveys including PM KOI questions and CBLF monitoring reports. Frequency: consolidated, cross-checked and validated by programme/MEAL staff prior to reporting; routine monitoring visits validate the distribution process. | AA19: Distribution records cross-checked against enrolment register to confirm no double-counting or non-enrolled recipients. | AB19: Consolidated, cross-checked and validated by programme/MEAL staff prior to reporting; routine monitoring visits validate the distribution process | AC19: MEAL Officer | AD19: Data consolidation, quality assurance & reporting | AE19: Procurement/supply-chain delays affecting print runs; new enrolments after a distribution round may require top-up kits. | AF19: =IFERROR("During the reporting period (cumulative through Q"&'7. IPTT'!$C$3&"), FIVDB reported "&TEXT(LOOKUP(2,1/(O19:V19<>""),O19:V19),"#,##0")&" against the indicator '"&$F19&"' - "&TEXT($W19,"0%")&" of the "&TEXT($M19,"#,##0")&" life-of-project target. "&"Disaggregated: "&TEXT($AH19,"#,##0")&" girls (<18), "&TEXT($AI19,"#,##0")&" boys (<18), "&TEXT($AJ19,"#,##0")&" women (18+), "&TEXT($AK19,"#,##0")&" men (18+).","During the reporting period, FIVDB reported progress against this indicator - see Cumulative Actual to Date and % of LOP Target Achieved.") -> During the reporting period (cumulative through Q1), FIVDB reported 0 against the indicator 'Number of girls and boys provided with learning materials' - 0% of the 1,224 life-of-project target. Disaggregated: 0 girls (<18), 0 boys (<18), 0 women (18+), 0 men (18+). | AG19: Narrative Proposal, Result 1 Indicator 4: consortium Baseline 0 (explicit - 'new materials will be distributed under this phase') / consortium Target 4,067 (SC 2,843: 2,293 girls, 550 boys; PLAN/FIVDB all 1,224 unique enrolled learners: 816 girls, 408 boys), aligned with ESWG guidance and the Myanmar Curriculum/ALP levels I-II. CLARIFICATION: Same 1,224 learners as R1-I1 (every enrolled learner receives materials - not an additional/separate group). FIVDB's own baseline = 0 (all new distribution this action). | AH19: =IFERROR(SUMPRODUCT(ISNUMBER(SEARCH($C19,'10. Activity Data Log'!$AC$7:$AC$46))*(IFERROR(VALUE(MID('10. Activity Data Log'!$AD$7:$AD$46,2,1)),99)<='7. IPTT'!$C$3)*N('10. Activity Data Log'!$O$7:$O$46))+SUMPRODUCT(ISNUMBER(SEARCH($C19,'11. Distribution Log'!$AH$7:$AH$46))*(IFERROR(VALUE(MID('11. Distribution Log'!$AI$7:$AI$46,2,1)),99)<='7. IPTT'!$C$3)*N('11. Distribution Log'!$Q$7:$Q$46))+SUMPRODUCT(ISNUMBER(SEARCH($C19,'10. Activity Data Log'!$AC$7:$AC$46))*(IFERROR(VALUE(MID('10. Activity Data Log'!$AD$7:$AD$46,2,1)),99)<='7. IPTT'!$C$3)*N('10. Activity Data Log'!$S$7:$S$46))+SUMPRODUCT(ISNUMBER(SEARCH($C19,'11. Distribution Log'!$AH$7:$AH$46))*(IFERROR(VALUE(MID('11. Distribution Log'!$AI$7:$AI$46,2,1)),99)<='7. IPTT'!$C$3)*N('11. Distribution Log'!$U$7:$U$46)),0) -> 0 | AI19: =IFERROR(SUMPRODUCT(ISNUMBER(SEARCH($C19,'10. Activity Data Log'!$AC$7:$AC$46))*(IFERROR(VALUE(MID('10. Activity Data Log'!$AD$7:$AD$46,2,1)),99)<='7. IPTT'!$C$3)*N('10. Activity Data Log'!$M$7:$M$46))+SUMPRODUCT(ISNUMBER(SEARCH($C19,'11. Distribution Log'!$AH$7:$AH$46))*(IFERROR(VALUE(MID('11. Distribution Log'!$AI$7:$AI$46,2,1)),99)<='7. IPTT'!$C$3)*N('11. Distribution Log'!$O$7:$O$46))+SUMPRODUCT(ISNUMBER(SEARCH($C19,'10. Activity Data Log'!$AC$7:$AC$46))*(IFERROR(VALUE(MID('10. Activity Data Log'!$AD$7:$AD$46,2,1)),99)<='7. IPTT'!$C$3)*N('10. Activity Data Log'!$Q$7:$Q$46))+SUMPRODUCT(ISNUMBER(SEARCH($C19,'11. Distribution Log'!$AH$7:$AH$46))*(IFERROR(VALUE(MID('11. Distribution Log'!$AI$7:$AI$46,2,1)),99)<='7. IPTT'!$C$3)*N('11. Distribution Log'!$S$7:$S$46)),0) -> 0 | AJ19: =IFERROR(SUMPRODUCT(ISNUMBER(SEARCH($C19,'10. Activity Data Log'!$AC$7:$AC$46))*(IFERROR(VALUE(MID('10. Activity Data Log'!$AD$7:$AD$46,2,1)),99)<='7. IPTT'!$C$3)*N('10. Activity Data Log'!$P$7:$P$46))+SUMPRODUCT(ISNUMBER(SEARCH($C19,'11. Distribution Log'!$AH$7:$AH$46))*(IFERROR(VALUE(MID('11. Distribution Log'!$AI$7:$AI$46,2,1)),99)<='7. IPTT'!$C$3)*N('11. Distribution Log'!$R$7:$R$46))+SUMPRODUCT(ISNUMBER(SEARCH($C19,'10. Activity Data Log'!$AC$7:$AC$46))*(IFERROR(VALUE(MID('10. Activity Data Log'!$AD$7:$AD$46,2,1)),99)<='7. IPTT'!$C$3)*N('10. Activity Data Log'!$T$7:$T$46))+SUMPRODUCT(ISNUMBER(SEARCH($C19,'11. Distribution Log'!$AH$7:$AH$46))*(IFERROR(VALUE(MID('11. Distribution Log'!$AI$7:$AI$46,2,1)),99)<='7. IPTT'!$C$3)*N('11. Distribution Log'!$V$7:$V$46)),0) -> 0 | AK19: =IFERROR(SUMPRODUCT(ISNUMBER(SEARCH($C19,'10. Activity Data Log'!$AC$7:$AC$46))*(IFERROR(VALUE(MID('10. Activity Data Log'!$AD$7:$AD$46,2,1)),99)<='7. IPTT'!$C$3)*N('10. Activity Data Log'!$N$7:$N$46))+SUMPRODUCT(ISNUMBER(SEARCH($C19,'11. Distribution Log'!$AH$7:$AH$46))*(IFERROR(VALUE(MID('11. Distribution Log'!$AI$7:$AI$46,2,1)),99)<='7. IPTT'!$C$3)*N('11. Distribution Log'!$P$7:$P$46))+SUMPRODUCT(ISNUMBER(SEARCH($C19,'10. Activity Data Log'!$AC$7:$AC$46))*(IFERROR(VALUE(MID('10. Activity Data Log'!$AD$7:$AD$46,2,1)),99)<='7. IPTT'!$C$3)*N('10. Activity Data Log'!$R$7:$R$46))+SUMPRODUCT(ISNUMBER(SEARCH($C19,'11. Distribution Log'!$AH$7:$AH$46))*(IFERROR(VALUE(MID('11. Distribution Log'!$AI$7:$AI$46,2,1)),99)<='7. IPTT'!$C$3)*N('11. Distribution Log'!$T$7:$T$46)),0) -> 0
B20: Result 1 | C20: R1-I5 | D20: R1A4.1 | E20: R1A4.2, R1A4.3, R1A4.6, R1A4.7, R1A4.11, R1A4.12 | F20: Number of teachers/education personnel showing increased knowledge and teaching skills to address children's learning needs | G20: Logframe (Annex I), Result 1 indicators - code R1-I5 | H20: Support = training, mentoring and coaching on skills/strategies to address identified learning needs (e.g. mixed-ability pedagogy, specific course content, basic literacy/numeracy, language pedagogy). Learning needs specified in the comments field. Disaggregate by sex, NFE type/level of education and disability. | I20: Structured pre- and post-training assessments using a consortium-wide Teacher Assessment Tool aligned with training content, applied during Outcome Assessments; supplemented by classroom observation reports and teacher/student/mentor surveys. | J20: Sex, role (teacher/other personnel) | K20: 0 | L20: 68 teachers/facilitators (training pool) | M20: 68 | N20: Number | O20: =IF(1>'7. IPTT'!$C$3,"",IFERROR((SUMPRODUCT(ISNUMBER(SEARCH($C20,'8. Activity Tracker'!$J$7:$J$93))*N('8. Activity Tracker'!V$7:V$93))),0)) -> 0 | P20: =IF(2>'7. IPTT'!$C$3,"",IFERROR((SUMPRODUCT(ISNUMBER(SEARCH($C20,'8. Activity Tracker'!$J$7:$J$93))*N('8. Activity Tracker'!V$7:V$93))+SUMPRODUCT(ISNUMBER(SEARCH($C20,'8. Activity Tracker'!$J$7:$J$93))*N('8. Activity Tracker'!W$7:W$93))),0)) | Q20: =IF(3>'7. IPTT'!$C$3,"",IFERROR((SUMPRODUCT(ISNUMBER(SEARCH($C20,'8. Activity Tracker'!$J$7:$J$93))*N('8. Activity Tracker'!V$7:V$93))+SUMPRODUCT(ISNUMBER(SEARCH($C20,'8. Activity Tracker'!$J$7:$J$93))*N('8. Activity Tracker'!W$7:W$93))+SUMPRODUCT(ISNUMBER(SEARCH($C20,'8. Activity Tracker'!$J$7:$J$93))*N('8. Activity Tracker'!X$7:X$93))),0)) | R20: =IF(4>'7. IPTT'!$C$3,"",IFERROR((SUMPRODUCT(ISNUMBER(SEARCH($C20,'8. Activity Tracker'!$J$7:$J$93))*N('8. Activity Tracker'!V$7:V$93))+SUMPRODUCT(ISNUMBER(SEARCH($C20,'8. Activity Tracker'!$J$7:$J$93))*N('8. Activity Tracker'!W$7:W$93))+SUMPRODUCT(ISNUMBER(SEARCH($C20,'8. Activity Tracker'!$J$7:$J$93))*N('8. Activity Tracker'!X$7:X$93))+SUMPRODUCT(ISNUMBER(SEARCH($C20,'8. Activity Tracker'!$J$7:$J$93))*N('8. Activity Tracker'!Y$7:Y$93))),0)) | S20: =IF(5>'7. IPTT'!$C$3,"",IFERROR((SUMPRODUCT(ISNUMBER(SEARCH($C20,'8. Activity Tracker'!$J$7:$J$93))*N('8. Activity Tracker'!V$7:V$93))+SUMPRODUCT(ISNUMBER(SEARCH($C20,'8. Activity Tracker'!$J$7:$J$93))*N('8. Activity Tracker'!W$7:W$93))+SUMPRODUCT(ISNUMBER(SEARCH($C20,'8. Activity Tracker'!$J$7:$J$93))*N('8. Activity Tracker'!X$7:X$93))+SUMPRODUCT(ISNUMBER(SEARCH($C20,'8. Activity Tracker'!$J$7:$J$93))*N('8. Activity Tracker'!Y$7:Y$93))+SUMPRODUCT(ISNUMBER(SEARCH($C20,'8. Activity Tracker'!$J$7:$J$93))*N('8. Activity Tracker'!Z$7:Z$93))),0)) | T20: =IF(6>'7. IPTT'!$C$3,"",IFERROR((SUMPRODUCT(ISNUMBER(SEARCH($C20,'8. Activity Tracker'!$J$7:$J$93))*N('8. Activity Tracker'!V$7:V$93))+SUMPRODUCT(ISNUMBER(SEARCH($C20,'8. Activity Tracker'!$J$7:$J$93))*N('8. Activity Tracker'!W$7:W$93))+SUMPRODUCT(ISNUMBER(SEARCH($C20,'8. Activity Tracker'!$J$7:$J$93))*N('8. Activity Tracker'!X$7:X$93))+SUMPRODUCT(ISNUMBER(SEARCH($C20,'8. Activity Tracker'!$J$7:$J$93))*N('8. Activity Tracker'!Y$7:Y$93))+SUMPRODUCT(ISNUMBER(SEARCH($C20,'8. Activity Tracker'!$J$7:$J$93))*N('8. Activity Tracker'!Z$7:Z$93))+SUMPRODUCT(ISNUMBER(SEARCH($C20,'8. Activity Tracker'!$J$7:$J$93))*N('8. Activity Tracker'!AA$7:AA$93))),0)) | U20: =IF(7>'7. IPTT'!$C$3,"",IFERROR((SUMPRODUCT(ISNUMBER(SEARCH($C20,'8. Activity Tracker'!$J$7:$J$93))*N('8. Activity Tracker'!V$7:V$93))+SUMPRODUCT(ISNUMBER(SEARCH($C20,'8. Activity Tracker'!$J$7:$J$93))*N('8. Activity Tracker'!W$7:W$93))+SUMPRODUCT(ISNUMBER(SEARCH($C20,'8. Activity Tracker'!$J$7:$J$93))*N('8. Activity Tracker'!X$7:X$93))+SUMPRODUCT(ISNUMBER(SEARCH($C20,'8. Activity Tracker'!$J$7:$J$93))*N('8. Activity Tracker'!Y$7:Y$93))+SUMPRODUCT(ISNUMBER(SEARCH($C20,'8. Activity Tracker'!$J$7:$J$93))*N('8. Activity Tracker'!Z$7:Z$93))+SUMPRODUCT(ISNUMBER(SEARCH($C20,'8. Activity Tracker'!$J$7:$J$93))*N('8. Activity Tracker'!AA$7:AA$93))+SUMPRODUCT(ISNUMBER(SEARCH($C20,'8. Activity Tracker'!$J$7:$J$93))*N('8. Activity Tracker'!AB$7:AB$93))),0)) | V20: =IF(8>'7. IPTT'!$C$3,"",IFERROR((SUMPRODUCT(ISNUMBER(SEARCH($C20,'8. Activity Tracker'!$J$7:$J$93))*N('8. Activity Tracker'!V$7:V$93))+SUMPRODUCT(ISNUMBER(SEARCH($C20,'8. Activity Tracker'!$J$7:$J$93))*N('8. Activity Tracker'!W$7:W$93))+SUMPRODUCT(ISNUMBER(SEARCH($C20,'8. Activity Tracker'!$J$7:$J$93))*N('8. Activity Tracker'!X$7:X$93))+SUMPRODUCT(ISNUMBER(SEARCH($C20,'8. Activity Tracker'!$J$7:$J$93))*N('8. Activity Tracker'!Y$7:Y$93))+SUMPRODUCT(ISNUMBER(SEARCH($C20,'8. Activity Tracker'!$J$7:$J$93))*N('8. Activity Tracker'!Z$7:Z$93))+SUMPRODUCT(ISNUMBER(SEARCH($C20,'8. Activity Tracker'!$J$7:$J$93))*N('8. Activity Tracker'!AA$7:AA$93))+SUMPRODUCT(ISNUMBER(SEARCH($C20,'8. Activity Tracker'!$J$7:$J$93))*N('8. Activity Tracker'!AB$7:AB$93))+SUMPRODUCT(ISNUMBER(SEARCH($C20,'8. Activity Tracker'!$J$7:$J$93))*N('8. Activity Tracker'!AC$7:AC$93))),0)) | W20: =IFERROR(LOOKUP(2,1/(O20:V20<>""),O20:V20)/$M20,"") -> 0 | X20: =IFERROR(IF(COUNT(O20:V20)=0,"No data yet",IF(LOOKUP(2,1/(O20:V20<>""),O20:V20)>=INDEX(O9:V9,$C$3)*$M20,"On Track",IF(LOOKUP(2,1/(O20:V20<>""),O20:V20)>=INDEX(O9:V9,$C$3)*$M20*0.85,"Slightly Behind","Behind"))),"") -> Behind | Y20: Teacher Assessment Tool (pre/post), classroom observation reports, OA survey | Z20: Source: Teacher Assessment Tool (structured pre/post training assessment). Method: applied during Outcome Assessments, supplemented by classroom observation reports and teacher/student/mentor surveys. Frequency: training data compiled quarterly; Outcome Assessment data collected periodically, reviewed through routine monitoring. | AA20: Pre/post test scoring reviewed by Education Coordinator; PIB samples a subset of assessment sheets each quarter. | AB20: Training data compiled quarterly; Outcome Assessment data collected periodically, reviewed through routine monitoring | AC20: Education Officer | AD20: Field data collection & first-line reporting | AE20: Training attendance may be disrupted by seasonal access constraints, competing duties, or facilitator turnover. | AF20: =IFERROR("During the reporting period (cumulative through Q"&'7. IPTT'!$C$3&"), FIVDB reported "&TEXT(LOOKUP(2,1/(O20:V20<>""),O20:V20),"#,##0")&" against the indicator '"&$F20&"' - "&TEXT($W20,"0%")&" of the "&TEXT($M20,"#,##0")&" life-of-project target. "&"Disaggregated: "&TEXT($AH20,"#,##0")&" girls (<18), "&TEXT($AI20,"#,##0")&" boys (<18), "&TEXT($AJ20,"#,##0")&" women (18+), "&TEXT($AK20,"#,##0")&" men (18+).","During the reporting period, FIVDB reported progress against this indicator - see Cumulative Actual to Date and % of LOP Target Achieved.") -> During the reporting period (cumulative through Q1), FIVDB reported 0 against the indicator 'Number of teachers/education personnel showing increased knowledge and teaching skills to address children's learning needs' - 0% of the 68 life-of-project target. Disaggregated: 0 girls (<18), 0 boys (<18), 0 women (18+), 0 men (18+). | AG20: Narrative Proposal, Result 1 Indicator 5: consortium Baseline 84 (SC-supported teachers who demonstrated improved knowledge/skills under ECHO HIP 2023, per the Teacher Assessment Tool) / consortium Target 140 (83% of the pooled 168 teachers: SC 100 + PLAN/FIVDB 68). FIVDB will recruit new teaching volunteers; all receive additional training to strengthen competencies. CLARIFICATION: 68 = all of FIVDB's teachers (same 68 as R1-I3) - FIVDB targets 100% of its own teachers to show improved knowledge/skills. The consortium's 140 (83% of 168) blends SC's lower pass-rate assumption with FIVDB's full-cohort target; the two are not directly comparable 1:1. | AH20: =IFERROR(SUMPRODUCT(ISNUMBER(SEARCH($C20,'10. Activity Data Log'!$AC$7:$AC$46))*(IFERROR(VALUE(MID('10. Activity Data Log'!$AD$7:$AD$46,2,1)),99)<='7. IPTT'!$C$3)*N('10. Activity Data Log'!$O$7:$O$46))+SUMPRODUCT(ISNUMBER(SEARCH($C20,'11. Distribution Log'!$AH$7:$AH$46))*(IFERROR(VALUE(MID('11. Distribution Log'!$AI$7:$AI$46,2,1)),99)<='7. IPTT'!$C$3)*N('11. Distribution Log'!$Q$7:$Q$46))+SUMPRODUCT(ISNUMBER(SEARCH($C20,'10. Activity Data Log'!$AC$7:$AC$46))*(IFERROR(VALUE(MID('10. Activity Data Log'!$AD$7:$AD$46,2,1)),99)<='7. IPTT'!$C$3)*N('10. Activity Data Log'!$S$7:$S$46))+SUMPRODUCT(ISNUMBER(SEARCH($C20,'11. Distribution Log'!$AH$7:$AH$46))*(IFERROR(VALUE(MID('11. Distribution Log'!$AI$7:$AI$46,2,1)),99)<='7. IPTT'!$C$3)*N('11. Distribution Log'!$U$7:$U$46)),0) -> 0 | AI20: =IFERROR(SUMPRODUCT(ISNUMBER(SEARCH($C20,'10. Activity Data Log'!$AC$7:$AC$46))*(IFERROR(VALUE(MID('10. Activity Data Log'!$AD$7:$AD$46,2,1)),99)<='7. IPTT'!$C$3)*N('10. Activity Data Log'!$M$7:$M$46))+SUMPRODUCT(ISNUMBER(SEARCH($C20,'11. Distribution Log'!$AH$7:$AH$46))*(IFERROR(VALUE(MID('11. Distribution Log'!$AI$7:$AI$46,2,1)),99)<='7. IPTT'!$C$3)*N('11. Distribution Log'!$O$7:$O$46))+SUMPRODUCT(ISNUMBER(SEARCH($C20,'10. Activity Data Log'!$AC$7:$AC$46))*(IFERROR(VALUE(MID('10. Activity Data Log'!$AD$7:$AD$46,2,1)),99)<='7. IPTT'!$C$3)*N('10. Activity Data Log'!$Q$7:$Q$46))+SUMPRODUCT(ISNUMBER(SEARCH($C20,'11. Distribution Log'!$AH$7:$AH$46))*(IFERROR(VALUE(MID('11. Distribution Log'!$AI$7:$AI$46,2,1)),99)<='7. IPTT'!$C$3)*N('11. Distribution Log'!$S$7:$S$46)),0) -> 0 | AJ20: =IFERROR(SUMPRODUCT(ISNUMBER(SEARCH($C20,'10. Activity Data Log'!$AC$7:$AC$46))*(IFERROR(VALUE(MID('10. Activity Data Log'!$AD$7:$AD$46,2,1)),99)<='7. IPTT'!$C$3)*N('10. Activity Data Log'!$P$7:$P$46))+SUMPRODUCT(ISNUMBER(SEARCH($C20,'11. Distribution Log'!$AH$7:$AH$46))*(IFERROR(VALUE(MID('11. Distribution Log'!$AI$7:$AI$46,2,1)),99)<='7. IPTT'!$C$3)*N('11. Distribution Log'!$R$7:$R$46))+SUMPRODUCT(ISNUMBER(SEARCH($C20,'10. Activity Data Log'!$AC$7:$AC$46))*(IFERROR(VALUE(MID('10. Activity Data Log'!$AD$7:$AD$46,2,1)),99)<='7. IPTT'!$C$3)*N('10. Activity Data Log'!$T$7:$T$46))+SUMPRODUCT(ISNUMBER(SEARCH($C20,'11. Distribution Log'!$AH$7:$AH$46))*(IFERROR(VALUE(MID('11. Distribution Log'!$AI$7:$AI$46,2,1)),99)<='7. IPTT'!$C$3)*N('11. Distribution Log'!$V$7:$V$46)),0) -> 0 | AK20: =IFERROR(SUMPRODUCT(ISNUMBER(SEARCH($C20,'10. Activity Data Log'!$AC$7:$AC$46))*(IFERROR(VALUE(MID('10. Activity Data Log'!$AD$7:$AD$46,2,1)),99)<='7. IPTT'!$C$3)*N('10. Activity Data Log'!$N$7:$N$46))+SUMPRODUCT(ISNUMBER(SEARCH($C20,'11. Distribution Log'!$AH$7:$AH$46))*(IFERROR(VALUE(MID('11. Distribution Log'!$AI$7:$AI$46,2,1)),99)<='7. IPTT'!$C$3)*N('11. Distribution Log'!$P$7:$P$46))+SUMPRODUCT(ISNUMBER(SEARCH($C20,'10. Activity Data Log'!$AC$7:$AC$46))*(IFERROR(VALUE(MID('10. Activity Data Log'!$AD$7:$AD$46,2,1)),99)<='7. IPTT'!$C$3)*N('10. Activity Data Log'!$R$7:$R$46))+SUMPRODUCT(ISNUMBER(SEARCH($C20,'11. Distribution Log'!$AH$7:$AH$46))*(IFERROR(VALUE(MID('11. Distribution Log'!$AI$7:$AI$46,2,1)),99)<='7. IPTT'!$C$3)*N('11. Distribution Log'!$T$7:$T$46)),0) -> 0
B21: Result 1 | C21: R1-I6 | D21: R1A4.13 | E21: R1A5.1 | F21: Number of students, teachers and other education personnel provided with psycho-social support services | G21: Logframe (Annex I), Result 1 indicators - code R1-I6 | H21: Psychosocial support (PSS) helps individuals recover after a crisis has disrupted their lives and return to normality after adverse events; limited to non-specialised service provision (not specialised mental health or CP case management). Education personnel may include parent-teacher associations, mothers-students associations, school management associations. Disaggregate by sex, NFE type/level of education, beneficiary type (student/teacher/other) and disability. | I21: Beneficiary lists, attendance sheets, learning-material distribution registers, and PSS participation reports, compiled by CBLF facilitators and implementing-partner staff. | J21: Sex, beneficiary type (student/teacher/other), disability | K21: 0 | L21: - | M21: 2516 | N21: Number | O21: =IF(1>'7. IPTT'!$C$3,"",IFERROR((SUMPRODUCT(ISNUMBER(SEARCH($C21,'8. Activity Tracker'!$J$7:$J$93))*N('8. Activity Tracker'!V$7:V$93))),0)) -> 0 | P21: =IF(2>'7. IPTT'!$C$3,"",IFERROR((SUMPRODUCT(ISNUMBER(SEARCH($C21,'8. Activity Tracker'!$J$7:$J$93))*N('8. Activity Tracker'!V$7:V$93))+SUMPRODUCT(ISNUMBER(SEARCH($C21,'8. Activity Tracker'!$J$7:$J$93))*N('8. Activity Tracker'!W$7:W$93))),0)) | Q21: =IF(3>'7. IPTT'!$C$3,"",IFERROR((SUMPRODUCT(ISNUMBER(SEARCH($C21,'8. Activity Tracker'!$J$7:$J$93))*N('8. Activity Tracker'!V$7:V$93))+SUMPRODUCT(ISNUMBER(SEARCH($C21,'8. Activity Tracker'!$J$7:$J$93))*N('8. Activity Tracker'!W$7:W$93))+SUMPRODUCT(ISNUMBER(SEARCH($C21,'8. Activity Tracker'!$J$7:$J$93))*N('8. Activity Tracker'!X$7:X$93))),0)) | R21: =IF(4>'7. IPTT'!$C$3,"",IFERROR((SUMPRODUCT(ISNUMBER(SEARCH($C21,'8. Activity Tracker'!$J$7:$J$93))*N('8. Activity Tracker'!V$7:V$93))+SUMPRODUCT(ISNUMBER(SEARCH($C21,'8. Activity Tracker'!$J$7:$J$93))*N('8. Activity Tracker'!W$7:W$93))+SUMPRODUCT(ISNUMBER(SEARCH($C21,'8. Activity Tracker'!$J$7:$J$93))*N('8. Activity Tracker'!X$7:X$93))+SUMPRODUCT(ISNUMBER(SEARCH($C21,'8. Activity Tracker'!$J$7:$J$93))*N('8. Activity Tracker'!Y$7:Y$93))),0)) | S21: =IF(5>'7. IPTT'!$C$3,"",IFERROR((SUMPRODUCT(ISNUMBER(SEARCH($C21,'8. Activity Tracker'!$J$7:$J$93))*N('8. Activity Tracker'!V$7:V$93))+SUMPRODUCT(ISNUMBER(SEARCH($C21,'8. Activity Tracker'!$J$7:$J$93))*N('8. Activity Tracker'!W$7:W$93))+SUMPRODUCT(ISNUMBER(SEARCH($C21,'8. Activity Tracker'!$J$7:$J$93))*N('8. Activity Tracker'!X$7:X$93))+SUMPRODUCT(ISNUMBER(SEARCH($C21,'8. Activity Tracker'!$J$7:$J$93))*N('8. Activity Tracker'!Y$7:Y$93))+SUMPRODUCT(ISNUMBER(SEARCH($C21,'8. Activity Tracker'!$J$7:$J$93))*N('8. Activity Tracker'!Z$7:Z$93))),0)) | T21: =IF(6>'7. IPTT'!$C$3,"",IFERROR((SUMPRODUCT(ISNUMBER(SEARCH($C21,'8. Activity Tracker'!$J$7:$J$93))*N('8. Activity Tracker'!V$7:V$93))+SUMPRODUCT(ISNUMBER(SEARCH($C21,'8. Activity Tracker'!$J$7:$J$93))*N('8. Activity Tracker'!W$7:W$93))+SUMPRODUCT(ISNUMBER(SEARCH($C21,'8. Activity Tracker'!$J$7:$J$93))*N('8. Activity Tracker'!X$7:X$93))+SUMPRODUCT(ISNUMBER(SEARCH($C21,'8. Activity Tracker'!$J$7:$J$93))*N('8. Activity Tracker'!Y$7:Y$93))+SUMPRODUCT(ISNUMBER(SEARCH($C21,'8. Activity Tracker'!$J$7:$J$93))*N('8. Activity Tracker'!Z$7:Z$93))+SUMPRODUCT(ISNUMBER(SEARCH($C21,'8. Activity Tracker'!$J$7:$J$93))*N('8. Activity Tracker'!AA$7:AA$93))),0)) | U21: =IF(7>'7. IPTT'!$C$3,"",IFERROR((SUMPRODUCT(ISNUMBER(SEARCH($C21,'8. Activity Tracker'!$J$7:$J$93))*N('8. Activity Tracker'!V$7:V$93))+SUMPRODUCT(ISNUMBER(SEARCH($C21,'8. Activity Tracker'!$J$7:$J$93))*N('8. Activity Tracker'!W$7:W$93))+SUMPRODUCT(ISNUMBER(SEARCH($C21,'8. Activity Tracker'!$J$7:$J$93))*N('8. Activity Tracker'!X$7:X$93))+SUMPRODUCT(ISNUMBER(SEARCH($C21,'8. Activity Tracker'!$J$7:$J$93))*N('8. Activity Tracker'!Y$7:Y$93))+SUMPRODUCT(ISNUMBER(SEARCH($C21,'8. Activity Tracker'!$J$7:$J$93))*N('8. Activity Tracker'!Z$7:Z$93))+SUMPRODUCT(ISNUMBER(SEARCH($C21,'8. Activity Tracker'!$J$7:$J$93))*N('8. Activity Tracker'!AA$7:AA$93))+SUMPRODUCT(ISNUMBER(SEARCH($C21,'8. Activity Tracker'!$J$7:$J$93))*N('8. Activity Tracker'!AB$7:AB$93))),0)) | V21: =IF(8>'7. IPTT'!$C$3,"",IFERROR((SUMPRODUCT(ISNUMBER(SEARCH($C21,'8. Activity Tracker'!$J$7:$J$93))*N('8. Activity Tracker'!V$7:V$93))+SUMPRODUCT(ISNUMBER(SEARCH($C21,'8. Activity Tracker'!$J$7:$J$93))*N('8. Activity Tracker'!W$7:W$93))+SUMPRODUCT(ISNUMBER(SEARCH($C21,'8. Activity Tracker'!$J$7:$J$93))*N('8. Activity Tracker'!X$7:X$93))+SUMPRODUCT(ISNUMBER(SEARCH($C21,'8. Activity Tracker'!$J$7:$J$93))*N('8. Activity Tracker'!Y$7:Y$93))+SUMPRODUCT(ISNUMBER(SEARCH($C21,'8. Activity Tracker'!$J$7:$J$93))*N('8. Activity Tracker'!Z$7:Z$93))+SUMPRODUCT(ISNUMBER(SEARCH($C21,'8. Activity Tracker'!$J$7:$J$93))*N('8. Activity Tracker'!AA$7:AA$93))+SUMPRODUCT(ISNUMBER(SEARCH($C21,'8. Activity Tracker'!$J$7:$J$93))*N('8. Activity Tracker'!AB$7:AB$93))+SUMPRODUCT(ISNUMBER(SEARCH($C21,'8. Activity Tracker'!$J$7:$J$93))*N('8. Activity Tracker'!AC$7:AC$93))),0)) | W21: =IFERROR(LOOKUP(2,1/(O21:V21<>""),O21:V21)/$M21,"") -> 0 | X21: =IFERROR(IF(COUNT(O21:V21)=0,"No data yet",IF(LOOKUP(2,1/(O21:V21<>""),O21:V21)>=INDEX(O9:V9,$C$3)*$M21,"On Track",IF(LOOKUP(2,1/(O21:V21<>""),O21:V21)>=INDEX(O9:V9,$C$3)*$M21*0.85,"Slightly Behind","Behind"))),"") -> Behind | Y21: Beneficiary lists, attendance sheets, PSS participation reports | Z21: Source: beneficiary lists, attendance sheets, learning-material distribution registers, PSS participation reports. Method: compiled by CBLF facilitators and implementing-partner staff. Frequency: monthly monitoring and document checks. | AA21: PSS attendance logs reconciled monthly against enrolment/staff rosters to avoid duplicate counting across sessions. | AB21: Monthly monitoring and document checks | AC21: MEAL Officer | AD21: Data consolidation, quality assurance & reporting | AE21: Uptake may be affected by stigma around PSS/MHPSS or scheduling conflicts with academic sessions. | AF21: =IFERROR("During the reporting period (cumulative through Q"&'7. IPTT'!$C$3&"), FIVDB reported "&TEXT(LOOKUP(2,1/(O21:V21<>""),O21:V21),"#,##0")&" against the indicator '"&$F21&"' - "&TEXT($W21,"0%")&" of the "&TEXT($M21,"#,##0")&" life-of-project target. "&"Disaggregated: "&TEXT($AH21,"#,##0")&" girls (<18), "&TEXT($AI21,"#,##0")&" boys (<18), "&TEXT($AJ21,"#,##0")&" women (18+), "&TEXT($AK21,"#,##0")&" men (18+).","During the reporting period, FIVDB reported progress against this indicator - see Cumulative Actual to Date and % of LOP Target Achieved.") -> During the reporting period (cumulative through Q1), FIVDB reported 0 against the indicator 'Number of students, teachers and other education personnel provided with psycho-social support services' - 0% of the 2,516 life-of-project target. Disaggregated: 0 girls (<18), 0 boys (<18), 0 women (18+), 0 men (18+). | AG21: Narrative Proposal, Result 1 Indicator 6: consortium Baseline 2,781 (beneficiaries oriented on PFA during ECHO HIP 2023) / consortium Target 8,302 (SC ~5,786: 2,843 learners w/ SEL + 100 teachers w/ PFA/PSS training + 2,843 parents w/ PFA orientation; PLAN/FIVDB 2,516: 68 teachers + 1,224 learners w/ Playful Minds for Wellbeing + 1,224 parents: 612 women, 612 men, via bi-monthly parenting sessions). Corrected from an earlier internal draft that showed 2,741 - the breakdown always summed to 2,516; the LOP Target has been aligned to match. CLARIFICATION: 2,516 = 68 teachers + 1,224 learners (all of R1-I1) + 1,224 parents/caregivers (1 per enrolled learner, 612 women + 612 men via bi-monthly parenting sessions). This LOP target was corrected from an earlier internal draft that showed 2,741 - the breakdown always summed to 2,516; the target figure is now aligned to match. | AH21: =IFERROR(SUMPRODUCT(ISNUMBER(SEARCH($C21,'10. Activity Data Log'!$AC$7:$AC$46))*(IFERROR(VALUE(MID('10. Activity Data Log'!$AD$7:$AD$46,2,1)),99)<='7. IPTT'!$C$3)*N('10. Activity Data Log'!$O$7:$O$46))+SUMPRODUCT(ISNUMBER(SEARCH($C21,'11. Distribution Log'!$AH$7:$AH$46))*(IFERROR(VALUE(MID('11. Distribution Log'!$AI$7:$AI$46,2,1)),99)<='7. IPTT'!$C$3)*N('11. Distribution Log'!$Q$7:$Q$46))+SUMPRODUCT(ISNUMBER(SEARCH($C21,'10. Activity Data Log'!$AC$7:$AC$46))*(IFERROR(VALUE(MID('10. Activity Data Log'!$AD$7:$AD$46,2,1)),99)<='7. IPTT'!$C$3)*N('10. Activity Data Log'!$S$7:$S$46))+SUMPRODUCT(ISNUMBER(SEARCH($C21,'11. Distribution Log'!$AH$7:$AH$46))*(IFERROR(VALUE(MID('11. Distribution Log'!$AI$7:$AI$46,2,1)),99)<='7. IPTT'!$C$3)*N('11. Distribution Log'!$U$7:$U$46)),0) -> 0 | AI21: =IFERROR(SUMPRODUCT(ISNUMBER(SEARCH($C21,'10. Activity Data Log'!$AC$7:$AC$46))*(IFERROR(VALUE(MID('10. Activity Data Log'!$AD$7:$AD$46,2,1)),99)<='7. IPTT'!$C$3)*N('10. Activity Data Log'!$M$7:$M$46))+SUMPRODUCT(ISNUMBER(SEARCH($C21,'11. Distribution Log'!$AH$7:$AH$46))*(IFERROR(VALUE(MID('11. Distribution Log'!$AI$7:$AI$46,2,1)),99)<='7. IPTT'!$C$3)*N('11. Distribution Log'!$O$7:$O$46))+SUMPRODUCT(ISNUMBER(SEARCH($C21,'10. Activity Data Log'!$AC$7:$AC$46))*(IFERROR(VALUE(MID('10. Activity Data Log'!$AD$7:$AD$46,2,1)),99)<='7. IPTT'!$C$3)*N('10. Activity Data Log'!$Q$7:$Q$46))+SUMPRODUCT(ISNUMBER(SEARCH($C21,'11. Distribution Log'!$AH$7:$AH$46))*(IFERROR(VALUE(MID('11. Distribution Log'!$AI$7:$AI$46,2,1)),99)<='7. IPTT'!$C$3)*N('11. Distribution Log'!$S$7:$S$46)),0) -> 0 | AJ21: =IFERROR(SUMPRODUCT(ISNUMBER(SEARCH($C21,'10. Activity Data Log'!$AC$7:$AC$46))*(IFERROR(VALUE(MID('10. Activity Data Log'!$AD$7:$AD$46,2,1)),99)<='7. IPTT'!$C$3)*N('10. Activity Data Log'!$P$7:$P$46))+SUMPRODUCT(ISNUMBER(SEARCH($C21,'11. Distribution Log'!$AH$7:$AH$46))*(IFERROR(VALUE(MID('11. Distribution Log'!$AI$7:$AI$46,2,1)),99)<='7. IPTT'!$C$3)*N('11. Distribution Log'!$R$7:$R$46))+SUMPRODUCT(ISNUMBER(SEARCH($C21,'10. Activity Data Log'!$AC$7:$AC$46))*(IFERROR(VALUE(MID('10. Activity Data Log'!$AD$7:$AD$46,2,1)),99)<='7. IPTT'!$C$3)*N('10. Activity Data Log'!$T$7:$T$46))+SUMPRODUCT(ISNUMBER(SEARCH($C21,'11. Distribution Log'!$AH$7:$AH$46))*(IFERROR(VALUE(MID('11. Distribution Log'!$AI$7:$AI$46,2,1)),99)<='7. IPTT'!$C$3)*N('11. Distribution Log'!$V$7:$V$46)),0) -> 0 | AK21: =IFERROR(SUMPRODUCT(ISNUMBER(SEARCH($C21,'10. Activity Data Log'!$AC$7:$AC$46))*(IFERROR(VALUE(MID('10. Activity Data Log'!$AD$7:$AD$46,2,1)),99)<='7. IPTT'!$C$3)*N('10. Activity Data Log'!$N$7:$N$46))+SUMPRODUCT(ISNUMBER(SEARCH($C21,'11. Distribution Log'!$AH$7:$AH$46))*(IFERROR(VALUE(MID('11. Distribution Log'!$AI$7:$AI$46,2,1)),99)<='7. IPTT'!$C$3)*N('11. Distribution Log'!$P$7:$P$46))+SUMPRODUCT(ISNUMBER(SEARCH($C21,'10. Activity Data Log'!$AC$7:$AC$46))*(IFERROR(VALUE(MID('10. Activity Data Log'!$AD$7:$AD$46,2,1)),99)<='7. IPTT'!$C$3)*N('10. Activity Data Log'!$R$7:$R$46))+SUMPRODUCT(ISNUMBER(SEARCH($C21,'11. Distribution Log'!$AH$7:$AH$46))*(IFERROR(VALUE(MID('11. Distribution Log'!$AI$7:$AI$46,2,1)),99)<='7. IPTT'!$C$3)*N('11. Distribution Log'!$T$7:$T$46)),0) -> 0
B22: Result 1 | C22: R1-I7 | D22: R1A4.4 | E22: R1A4.5 | F22: Number of teachers and other education personnel showing increased knowledge and skills to address the protection needs of girls and boys | G22: Logframe (Annex I), Result 1 indicators - code R1-I7 | H22: Other education personnel may include parent-teacher associations, mothers-students associations, school management associations. Protection needs defined per context (child protection, PSS, SGBV information, mine/UXO risk education, HIV/AIDS, nutrition, health/hygiene, gender-sensitive and conflict-sensitive education). Disaggregate by sex, NFE type/level of education and disability. | I22: Pre- and post-training assessment records, observation checklists, and supervision visit reports, compiled by CBLF teaching volunteers, implementing partners and Education Officers. | J22: Sex, role | K22: 0 | L22: 68 teachers/facilitators (training pool) | M22: 68 | N22: Number | O22: =IF(1>'7. IPTT'!$C$3,"",IFERROR((SUMPRODUCT(ISNUMBER(SEARCH($C22,'8. Activity Tracker'!$J$7:$J$93))*N('8. Activity Tracker'!V$7:V$93))),0)) -> 0 | P22: =IF(2>'7. IPTT'!$C$3,"",IFERROR((SUMPRODUCT(ISNUMBER(SEARCH($C22,'8. Activity Tracker'!$J$7:$J$93))*N('8. Activity Tracker'!V$7:V$93))+SUMPRODUCT(ISNUMBER(SEARCH($C22,'8. Activity Tracker'!$J$7:$J$93))*N('8. Activity Tracker'!W$7:W$93))),0)) | Q22: =IF(3>'7. IPTT'!$C$3,"",IFERROR((SUMPRODUCT(ISNUMBER(SEARCH($C22,'8. Activity Tracker'!$J$7:$J$93))*N('8. Activity Tracker'!V$7:V$93))+SUMPRODUCT(ISNUMBER(SEARCH($C22,'8. Activity Tracker'!$J$7:$J$93))*N('8. Activity Tracker'!W$7:W$93))+SUMPRODUCT(ISNUMBER(SEARCH($C22,'8. Activity Tracker'!$J$7:$J$93))*N('8. Activity Tracker'!X$7:X$93))),0)) | R22: =IF(4>'7. IPTT'!$C$3,"",IFERROR((SUMPRODUCT(ISNUMBER(SEARCH($C22,'8. Activity Tracker'!$J$7:$J$93))*N('8. Activity Tracker'!V$7:V$93))+SUMPRODUCT(ISNUMBER(SEARCH($C22,'8. Activity Tracker'!$J$7:$J$93))*N('8. Activity Tracker'!W$7:W$93))+SUMPRODUCT(ISNUMBER(SEARCH($C22,'8. Activity Tracker'!$J$7:$J$93))*N('8. Activity Tracker'!X$7:X$93))+SUMPRODUCT(ISNUMBER(SEARCH($C22,'8. Activity Tracker'!$J$7:$J$93))*N('8. Activity Tracker'!Y$7:Y$93))),0)) | S22: =IF(5>'7. IPTT'!$C$3,"",IFERROR((SUMPRODUCT(ISNUMBER(SEARCH($C22,'8. Activity Tracker'!$J$7:$J$93))*N('8. Activity Tracker'!V$7:V$93))+SUMPRODUCT(ISNUMBER(SEARCH($C22,'8. Activity Tracker'!$J$7:$J$93))*N('8. Activity Tracker'!W$7:W$93))+SUMPRODUCT(ISNUMBER(SEARCH($C22,'8. Activity Tracker'!$J$7:$J$93))*N('8. Activity Tracker'!X$7:X$93))+SUMPRODUCT(ISNUMBER(SEARCH($C22,'8. Activity Tracker'!$J$7:$J$93))*N('8. Activity Tracker'!Y$7:Y$93))+SUMPRODUCT(ISNUMBER(SEARCH($C22,'8. Activity Tracker'!$J$7:$J$93))*N('8. Activity Tracker'!Z$7:Z$93))),0)) | T22: =IF(6>'7. IPTT'!$C$3,"",IFERROR((SUMPRODUCT(ISNUMBER(SEARCH($C22,'8. Activity Tracker'!$J$7:$J$93))*N('8. Activity Tracker'!V$7:V$93))+SUMPRODUCT(ISNUMBER(SEARCH($C22,'8. Activity Tracker'!$J$7:$J$93))*N('8. Activity Tracker'!W$7:W$93))+SUMPRODUCT(ISNUMBER(SEARCH($C22,'8. Activity Tracker'!$J$7:$J$93))*N('8. Activity Tracker'!X$7:X$93))+SUMPRODUCT(ISNUMBER(SEARCH($C22,'8. Activity Tracker'!$J$7:$J$93))*N('8. Activity Tracker'!Y$7:Y$93))+SUMPRODUCT(ISNUMBER(SEARCH($C22,'8. Activity Tracker'!$J$7:$J$93))*N('8. Activity Tracker'!Z$7:Z$93))+SUMPRODUCT(ISNUMBER(SEARCH($C22,'8. Activity Tracker'!$J$7:$J$93))*N('8. Activity Tracker'!AA$7:AA$93))),0)) | U22: =IF(7>'7. IPTT'!$C$3,"",IFERROR((SUMPRODUCT(ISNUMBER(SEARCH($C22,'8. Activity Tracker'!$J$7:$J$93))*N('8. Activity Tracker'!V$7:V$93))+SUMPRODUCT(ISNUMBER(SEARCH($C22,'8. Activity Tracker'!$J$7:$J$93))*N('8. Activity Tracker'!W$7:W$93))+SUMPRODUCT(ISNUMBER(SEARCH($C22,'8. Activity Tracker'!$J$7:$J$93))*N('8. Activity Tracker'!X$7:X$93))+SUMPRODUCT(ISNUMBER(SEARCH($C22,'8. Activity Tracker'!$J$7:$J$93))*N('8. Activity Tracker'!Y$7:Y$93))+SUMPRODUCT(ISNUMBER(SEARCH($C22,'8. Activity Tracker'!$J$7:$J$93))*N('8. Activity Tracker'!Z$7:Z$93))+SUMPRODUCT(ISNUMBER(SEARCH($C22,'8. Activity Tracker'!$J$7:$J$93))*N('8. Activity Tracker'!AA$7:AA$93))+SUMPRODUCT(ISNUMBER(SEARCH($C22,'8. Activity Tracker'!$J$7:$J$93))*N('8. Activity Tracker'!AB$7:AB$93))),0)) | V22: =IF(8>'7. IPTT'!$C$3,"",IFERROR((SUMPRODUCT(ISNUMBER(SEARCH($C22,'8. Activity Tracker'!$J$7:$J$93))*N('8. Activity Tracker'!V$7:V$93))+SUMPRODUCT(ISNUMBER(SEARCH($C22,'8. Activity Tracker'!$J$7:$J$93))*N('8. Activity Tracker'!W$7:W$93))+SUMPRODUCT(ISNUMBER(SEARCH($C22,'8. Activity Tracker'!$J$7:$J$93))*N('8. Activity Tracker'!X$7:X$93))+SUMPRODUCT(ISNUMBER(SEARCH($C22,'8. Activity Tracker'!$J$7:$J$93))*N('8. Activity Tracker'!Y$7:Y$93))+SUMPRODUCT(ISNUMBER(SEARCH($C22,'8. Activity Tracker'!$J$7:$J$93))*N('8. Activity Tracker'!Z$7:Z$93))+SUMPRODUCT(ISNUMBER(SEARCH($C22,'8. Activity Tracker'!$J$7:$J$93))*N('8. Activity Tracker'!AA$7:AA$93))+SUMPRODUCT(ISNUMBER(SEARCH($C22,'8. Activity Tracker'!$J$7:$J$93))*N('8. Activity Tracker'!AB$7:AB$93))+SUMPRODUCT(ISNUMBER(SEARCH($C22,'8. Activity Tracker'!$J$7:$J$93))*N('8. Activity Tracker'!AC$7:AC$93))),0)) | W22: =IFERROR(LOOKUP(2,1/(O22:V22<>""),O22:V22)/$M22,"") -> 0 | X22: =IFERROR(IF(COUNT(O22:V22)=0,"No data yet",IF(LOOKUP(2,1/(O22:V22<>""),O22:V22)>=INDEX(O9:V9,$C$3)*$M22,"On Track",IF(LOOKUP(2,1/(O22:V22<>""),O22:V22)>=INDEX(O9:V9,$C$3)*$M22*0.85,"Slightly Behind","Behind"))),"") -> Behind | Y22: Pre/post training assessment records, observation checklists, supervision reports | Z22: Source: pre/post training assessment records, observation checklists, supervision visit reports. Method: compiled by CBLF teaching volunteers, implementing partners and Education Officers. Frequency: quarterly; Outcome Assessment data collected periodically. | AA22: Pre/post assessment scores reviewed by Education Coordinator; PIB technical review of training content each cycle. | AB22: Quarterly; Outcome Assessment data collected periodically | AC22: Education Officer | AD22: Field data collection & first-line reporting | AE22: Turnover of trained teachers/facilitators may erode cumulative protection knowledge within the workforce. | AF22: =IFERROR("During the reporting period (cumulative through Q"&'7. IPTT'!$C$3&"), FIVDB reported "&TEXT(LOOKUP(2,1/(O22:V22<>""),O22:V22),"#,##0")&" against the indicator '"&$F22&"' - "&TEXT($W22,"0%")&" of the "&TEXT($M22,"#,##0")&" life-of-project target. "&"Disaggregated: "&TEXT($AH22,"#,##0")&" girls (<18), "&TEXT($AI22,"#,##0")&" boys (<18), "&TEXT($AJ22,"#,##0")&" women (18+), "&TEXT($AK22,"#,##0")&" men (18+).","During the reporting period, FIVDB reported progress against this indicator - see Cumulative Actual to Date and % of LOP Target Achieved.") -> During the reporting period (cumulative through Q1), FIVDB reported 0 against the indicator 'Number of teachers and other education personnel showing increased knowledge and skills to address the protection needs of girls and boys' - 0% of the 68 life-of-project target. Disaggregated: 0 girls (<18), 0 boys (<18), 0 women (18+), 0 men (18+). | AG22: Narrative Proposal, Result 1 Indicator 7: consortium Baseline 280 (CESG members trained under ECHO HIP 2023) / consortium Target 408 (SC 240: 140 CESG members across 35 CESGs + 100 teachers; PLAN/FIVDB 168: 68 teachers/education personnel + 100 members across ~26 CESGs). CLARIFICATION: FIVDB's own contribution to the consortium's 168 sub-total is 68 teachers only (the 100 CESG members in that 168 figure sit under R1-I6-adjacent community-engagement activities, not 'other education personnel' here) - see Activity Tracker R1A4 rows for the exact training cohorts. | AH22: =IFERROR(SUMPRODUCT(ISNUMBER(SEARCH($C22,'10. Activity Data Log'!$AC$7:$AC$46))*(IFERROR(VALUE(MID('10. Activity Data Log'!$AD$7:$AD$46,2,1)),99)<='7. IPTT'!$C$3)*N('10. Activity Data Log'!$O$7:$O$46))+SUMPRODUCT(ISNUMBER(SEARCH($C22,'11. Distribution Log'!$AH$7:$AH$46))*(IFERROR(VALUE(MID('11. Distribution Log'!$AI$7:$AI$46,2,1)),99)<='7. IPTT'!$C$3)*N('11. Distribution Log'!$Q$7:$Q$46))+SUMPRODUCT(ISNUMBER(SEARCH($C22,'10. Activity Data Log'!$AC$7:$AC$46))*(IFERROR(VALUE(MID('10. Activity Data Log'!$AD$7:$AD$46,2,1)),99)<='7. IPTT'!$C$3)*N('10. Activity Data Log'!$S$7:$S$46))+SUMPRODUCT(ISNUMBER(SEARCH($C22,'11. Distribution Log'!$AH$7:$AH$46))*(IFERROR(VALUE(MID('11. Distribution Log'!$AI$7:$AI$46,2,1)),99)<='7. IPTT'!$C$3)*N('11. Distribution Log'!$U$7:$U$46)),0) -> 0 | AI22: =IFERROR(SUMPRODUCT(ISNUMBER(SEARCH($C22,'10. Activity Data Log'!$AC$7:$AC$46))*(IFERROR(VALUE(MID('10. Activity Data Log'!$AD$7:$AD$46,2,1)),99)<='7. IPTT'!$C$3)*N('10. Activity Data Log'!$M$7:$M$46))+SUMPRODUCT(ISNUMBER(SEARCH($C22,'11. Distribution Log'!$AH$7:$AH$46))*(IFERROR(VALUE(MID('11. Distribution Log'!$AI$7:$AI$46,2,1)),99)<='7. IPTT'!$C$3)*N('11. Distribution Log'!$O$7:$O$46))+SUMPRODUCT(ISNUMBER(SEARCH($C22,'10. Activity Data Log'!$AC$7:$AC$46))*(IFERROR(VALUE(MID('10. Activity Data Log'!$AD$7:$AD$46,2,1)),99)<='7. IPTT'!$C$3)*N('10. Activity Data Log'!$Q$7:$Q$46))+SUMPRODUCT(ISNUMBER(SEARCH($C22,'11. Distribution Log'!$AH$7:$AH$46))*(IFERROR(VALUE(MID('11. Distribution Log'!$AI$7:$AI$46,2,1)),99)<='7. IPTT'!$C$3)*N('11. Distribution Log'!$S$7:$S$46)),0) -> 0 | AJ22: =IFERROR(SUMPRODUCT(ISNUMBER(SEARCH($C22,'10. Activity Data Log'!$AC$7:$AC$46))*(IFERROR(VALUE(MID('10. Activity Data Log'!$AD$7:$AD$46,2,1)),99)<='7. IPTT'!$C$3)*N('10. Activity Data Log'!$P$7:$P$46))+SUMPRODUCT(ISNUMBER(SEARCH($C22,'11. Distribution Log'!$AH$7:$AH$46))*(IFERROR(VALUE(MID('11. Distribution Log'!$AI$7:$AI$46,2,1)),99)<='7. IPTT'!$C$3)*N('11. Distribution Log'!$R$7:$R$46))+SUMPRODUCT(ISNUMBER(SEARCH($C22,'10. Activity Data Log'!$AC$7:$AC$46))*(IFERROR(VALUE(MID('10. Activity Data Log'!$AD$7:$AD$46,2,1)),99)<='7. IPTT'!$C$3)*N('10. Activity Data Log'!$T$7:$T$46))+SUMPRODUCT(ISNUMBER(SEARCH($C22,'11. Distribution Log'!$AH$7:$AH$46))*(IFERROR(VALUE(MID('11. Distribution Log'!$AI$7:$AI$46,2,1)),99)<='7. IPTT'!$C$3)*N('11. Distribution Log'!$V$7:$V$46)),0) -> 0 | AK22: =IFERROR(SUMPRODUCT(ISNUMBER(SEARCH($C22,'10. Activity Data Log'!$AC$7:$AC$46))*(IFERROR(VALUE(MID('10. Activity Data Log'!$AD$7:$AD$46,2,1)),99)<='7. IPTT'!$C$3)*N('10. Activity Data Log'!$N$7:$N$46))+SUMPRODUCT(ISNUMBER(SEARCH($C22,'11. Distribution Log'!$AH$7:$AH$46))*(IFERROR(VALUE(MID('11. Distribution Log'!$AI$7:$AI$46,2,1)),99)<='7. IPTT'!$C$3)*N('11. Distribution Log'!$P$7:$P$46))+SUMPRODUCT(ISNUMBER(SEARCH($C22,'10. Activity Data Log'!$AC$7:$AC$46))*(IFERROR(VALUE(MID('10. Activity Data Log'!$AD$7:$AD$46,2,1)),99)<='7. IPTT'!$C$3)*N('10. Activity Data Log'!$R$7:$R$46))+SUMPRODUCT(ISNUMBER(SEARCH($C22,'11. Distribution Log'!$AH$7:$AH$46))*(IFERROR(VALUE(MID('11. Distribution Log'!$AI$7:$AI$46,2,1)),99)<='7. IPTT'!$C$3)*N('11. Distribution Log'!$T$7:$T$46)),0) -> 0
B23: Result 1 | C23: R1-I8 | D23: R1-A4 | F23: Number of girls and boys referred to specialised services (e.g. child protection, health, MHPSS) | G23: Logframe (Annex I), Result 1 indicators - code R1-I8 | H23: Referrals must be based on up-to-date referral mechanisms assessing both availability and quality of service delivery. Disaggregate by sex, NFE type/level of education and disability. | I23: Standardized referral logbooks and case-management databases maintained by implementing partners and service providers; trained case workers record referral type, pathway and expected feedback timelines, disaggregated by sex, age, disability and sector. | J23: Sex, level of education, disability | K23: 0 | L23: - | M23: 122 | N23: Number | O23: =IF(1>'7. IPTT'!$C$3,"",IFERROR((SUMPRODUCT(ISNUMBER(SEARCH($C23,'8. Activity Tracker'!$J$7:$J$93))*N('8. Activity Tracker'!V$7:V$93))),0)) -> 0 | P23: =IF(2>'7. IPTT'!$C$3,"",IFERROR((SUMPRODUCT(ISNUMBER(SEARCH($C23,'8. Activity Tracker'!$J$7:$J$93))*N('8. Activity Tracker'!V$7:V$93))+SUMPRODUCT(ISNUMBER(SEARCH($C23,'8. Activity Tracker'!$J$7:$J$93))*N('8. Activity Tracker'!W$7:W$93))),0)) | Q23: =IF(3>'7. IPTT'!$C$3,"",IFERROR((SUMPRODUCT(ISNUMBER(SEARCH($C23,'8. Activity Tracker'!$J$7:$J$93))*N('8. Activity Tracker'!V$7:V$93))+SUMPRODUCT(ISNUMBER(SEARCH($C23,'8. Activity Tracker'!$J$7:$J$93))*N('8. Activity Tracker'!W$7:W$93))+SUMPRODUCT(ISNUMBER(SEARCH($C23,'8. Activity Tracker'!$J$7:$J$93))*N('8. Activity Tracker'!X$7:X$93))),0)) | R23: =IF(4>'7. IPTT'!$C$3,"",IFERROR((SUMPRODUCT(ISNUMBER(SEARCH($C23,'8. Activity Tracker'!$J$7:$J$93))*N('8. Activity Tracker'!V$7:V$93))+SUMPRODUCT(ISNUMBER(SEARCH($C23,'8. Activity Tracker'!$J$7:$J$93))*N('8. Activity Tracker'!W$7:W$93))+SUMPRODUCT(ISNUMBER(SEARCH($C23,'8. Activity Tracker'!$J$7:$J$93))*N('8. Activity Tracker'!X$7:X$93))+SUMPRODUCT(ISNUMBER(SEARCH($C23,'8. Activity Tracker'!$J$7:$J$93))*N('8. Activity Tracker'!Y$7:Y$93))),0)) | S23: =IF(5>'7. IPTT'!$C$3,"",IFERROR((SUMPRODUCT(ISNUMBER(SEARCH($C23,'8. Activity Tracker'!$J$7:$J$93))*N('8. Activity Tracker'!V$7:V$93))+SUMPRODUCT(ISNUMBER(SEARCH($C23,'8. Activity Tracker'!$J$7:$J$93))*N('8. Activity Tracker'!W$7:W$93))+SUMPRODUCT(ISNUMBER(SEARCH($C23,'8. Activity Tracker'!$J$7:$J$93))*N('8. Activity Tracker'!X$7:X$93))+SUMPRODUCT(ISNUMBER(SEARCH($C23,'8. Activity Tracker'!$J$7:$J$93))*N('8. Activity Tracker'!Y$7:Y$93))+SUMPRODUCT(ISNUMBER(SEARCH($C23,'8. Activity Tracker'!$J$7:$J$93))*N('8. Activity Tracker'!Z$7:Z$93))),0)) | T23: =IF(6>'7. IPTT'!$C$3,"",IFERROR((SUMPRODUCT(ISNUMBER(SEARCH($C23,'8. Activity Tracker'!$J$7:$J$93))*N('8. Activity Tracker'!V$7:V$93))+SUMPRODUCT(ISNUMBER(SEARCH($C23,'8. Activity Tracker'!$J$7:$J$93))*N('8. Activity Tracker'!W$7:W$93))+SUMPRODUCT(ISNUMBER(SEARCH($C23,'8. Activity Tracker'!$J$7:$J$93))*N('8. Activity Tracker'!X$7:X$93))+SUMPRODUCT(ISNUMBER(SEARCH($C23,'8. Activity Tracker'!$J$7:$J$93))*N('8. Activity Tracker'!Y$7:Y$93))+SUMPRODUCT(ISNUMBER(SEARCH($C23,'8. Activity Tracker'!$J$7:$J$93))*N('8. Activity Tracker'!Z$7:Z$93))+SUMPRODUCT(ISNUMBER(SEARCH($C23,'8. Activity Tracker'!$J$7:$J$93))*N('8. Activity Tracker'!AA$7:AA$93))),0)) | U23: =IF(7>'7. IPTT'!$C$3,"",IFERROR((SUMPRODUCT(ISNUMBER(SEARCH($C23,'8. Activity Tracker'!$J$7:$J$93))*N('8. Activity Tracker'!V$7:V$93))+SUMPRODUCT(ISNUMBER(SEARCH($C23,'8. Activity Tracker'!$J$7:$J$93))*N('8. Activity Tracker'!W$7:W$93))+SUMPRODUCT(ISNUMBER(SEARCH($C23,'8. Activity Tracker'!$J$7:$J$93))*N('8. Activity Tracker'!X$7:X$93))+SUMPRODUCT(ISNUMBER(SEARCH($C23,'8. Activity Tracker'!$J$7:$J$93))*N('8. Activity Tracker'!Y$7:Y$93))+SUMPRODUCT(ISNUMBER(SEARCH($C23,'8. Activity Tracker'!$J$7:$J$93))*N('8. Activity Tracker'!Z$7:Z$93))+SUMPRODUCT(ISNUMBER(SEARCH($C23,'8. Activity Tracker'!$J$7:$J$93))*N('8. Activity Tracker'!AA$7:AA$93))+SUMPRODUCT(ISNUMBER(SEARCH($C23,'8. Activity Tracker'!$J$7:$J$93))*N('8. Activity Tracker'!AB$7:AB$93))),0)) | V23: =IF(8>'7. IPTT'!$C$3,"",IFERROR((SUMPRODUCT(ISNUMBER(SEARCH($C23,'8. Activity Tracker'!$J$7:$J$93))*N('8. Activity Tracker'!V$7:V$93))+SUMPRODUCT(ISNUMBER(SEARCH($C23,'8. Activity Tracker'!$J$7:$J$93))*N('8. Activity Tracker'!W$7:W$93))+SUMPRODUCT(ISNUMBER(SEARCH($C23,'8. Activity Tracker'!$J$7:$J$93))*N('8. Activity Tracker'!X$7:X$93))+SUMPRODUCT(ISNUMBER(SEARCH($C23,'8. Activity Tracker'!$J$7:$J$93))*N('8. Activity Tracker'!Y$7:Y$93))+SUMPRODUCT(ISNUMBER(SEARCH($C23,'8. Activity Tracker'!$J$7:$J$93))*N('8. Activity Tracker'!Z$7:Z$93))+SUMPRODUCT(ISNUMBER(SEARCH($C23,'8. Activity Tracker'!$J$7:$J$93))*N('8. Activity Tracker'!AA$7:AA$93))+SUMPRODUCT(ISNUMBER(SEARCH($C23,'8. Activity Tracker'!$J$7:$J$93))*N('8. Activity Tracker'!AB$7:AB$93))+SUMPRODUCT(ISNUMBER(SEARCH($C23,'8. Activity Tracker'!$J$7:$J$93))*N('8. Activity Tracker'!AC$7:AC$93))),0)) | W23: =IFERROR(LOOKUP(2,1/(O23:V23<>""),O23:V23)/$M23,"") -> 0 | X23: =IFERROR(IF(COUNT(O23:V23)=0,"No data yet",IF(LOOKUP(2,1/(O23:V23<>""),O23:V23)>=INDEX(O9:V9,$C$3)*$M23,"On Track",IF(LOOKUP(2,1/(O23:V23<>""),O23:V23)>=INDEX(O9:V9,$C$3)*$M23*0.85,"Slightly Behind","Behind"))),"") -> Behind | Y23: Referral logbook, case management database | Z23: Source: standardized referral logbooks, case-management databases. Method: maintained by implementing partners and service providers; trained case workers record referral type, pathway and expected feedback timelines, disaggregated by sex, age, disability and sector. Frequency: referral data collected and reviewed monthly; reported through partner progress reports and quarterly project reports. | AA23: Referral tracker cross-checked monthly against confirmation received from CP/Health/MHPSS receiving services. | AB23: Referral data collected and reviewed monthly; reported through partner progress reports and quarterly project reports | AC23: MEAL Officer | AD23: Data consolidation, quality assurance & reporting | AE23: Referral-pathway bottlenecks at receiving CP/Health services may delay confirmed uptake, understating the indicator. | AF23: =IFERROR("During the reporting period (cumulative through Q"&'7. IPTT'!$C$3&"), FIVDB reported "&TEXT(LOOKUP(2,1/(O23:V23<>""),O23:V23),"#,##0")&" against the indicator '"&$F23&"' - "&TEXT($W23,"0%")&" of the "&TEXT($M23,"#,##0")&" life-of-project target. "&"Disaggregated: "&TEXT($AH23,"#,##0")&" girls (<18), "&TEXT($AI23,"#,##0")&" boys (<18), "&TEXT($AJ23,"#,##0")&" women (18+), "&TEXT($AK23,"#,##0")&" men (18+).","During the reporting period, FIVDB reported progress against this indicator - see Cumulative Actual to Date and % of LOP Target Achieved.") -> During the reporting period (cumulative through Q1), FIVDB reported 0 against the indicator 'Number of girls and boys referred to specialised services (e.g. child protection, health, MHPSS)' - 0% of the 122 life-of-project target. Disaggregated: 0 girls (<18), 0 boys (<18), 0 women (18+), 0 men (18+). | AG23: Narrative Proposal, Result 1 Indicator 8: consortium Baseline 0 / consortium Target 406, projected at ~10% of enrolled learners requiring referral (SC ~284 of 2,843; PLAN/FIVDB ~122 of 1,224). Explicitly noted as a projection based on historical trends that may vary depending on identified needs. Corrected from an earlier internal draft that showed 131 - the 10% calculation always gave ~122; the LOP Target has been aligned to match. CLARIFICATION: 122 = ~10% of 1,224 enrolled learners. Explicitly a projection, not a fixed quota - referral volume 'may vary depending on identified needs' per the Narrative Proposal. This LOP target was corrected from an earlier internal draft that showed 131. | AH23: =IFERROR(SUMPRODUCT(ISNUMBER(SEARCH($C23,'10. Activity Data Log'!$AC$7:$AC$46))*(IFERROR(VALUE(MID('10. Activity Data Log'!$AD$7:$AD$46,2,1)),99)<='7. IPTT'!$C$3)*N('10. Activity Data Log'!$O$7:$O$46))+SUMPRODUCT(ISNUMBER(SEARCH($C23,'11. Distribution Log'!$AH$7:$AH$46))*(IFERROR(VALUE(MID('11. Distribution Log'!$AI$7:$AI$46,2,1)),99)<='7. IPTT'!$C$3)*N('11. Distribution Log'!$Q$7:$Q$46))+SUMPRODUCT(ISNUMBER(SEARCH($C23,'10. Activity Data Log'!$AC$7:$AC$46))*(IFERROR(VALUE(MID('10. Activity Data Log'!$AD$7:$AD$46,2,1)),99)<='7. IPTT'!$C$3)*N('10. Activity Data Log'!$S$7:$S$46))+SUMPRODUCT(ISNUMBER(SEARCH($C23,'11. Distribution Log'!$AH$7:$AH$46))*(IFERROR(VALUE(MID('11. Distribution Log'!$AI$7:$AI$46,2,1)),99)<='7. IPTT'!$C$3)*N('11. Distribution Log'!$U$7:$U$46)),0) -> 0 | AI23: =IFERROR(SUMPRODUCT(ISNUMBER(SEARCH($C23,'10. Activity Data Log'!$AC$7:$AC$46))*(IFERROR(VALUE(MID('10. Activity Data Log'!$AD$7:$AD$46,2,1)),99)<='7. IPTT'!$C$3)*N('10. Activity Data Log'!$M$7:$M$46))+SUMPRODUCT(ISNUMBER(SEARCH($C23,'11. Distribution Log'!$AH$7:$AH$46))*(IFERROR(VALUE(MID('11. Distribution Log'!$AI$7:$AI$46,2,1)),99)<='7. IPTT'!$C$3)*N('11. Distribution Log'!$O$7:$O$46))+SUMPRODUCT(ISNUMBER(SEARCH($C23,'10. Activity Data Log'!$AC$7:$AC$46))*(IFERROR(VALUE(MID('10. Activity Data Log'!$AD$7:$AD$46,2,1)),99)<='7. IPTT'!$C$3)*N('10. Activity Data Log'!$Q$7:$Q$46))+SUMPRODUCT(ISNUMBER(SEARCH($C23,'11. Distribution Log'!$AH$7:$AH$46))*(IFERROR(VALUE(MID('11. Distribution Log'!$AI$7:$AI$46,2,1)),99)<='7. IPTT'!$C$3)*N('11. Distribution Log'!$S$7:$S$46)),0) -> 0 | AJ23: =IFERROR(SUMPRODUCT(ISNUMBER(SEARCH($C23,'10. Activity Data Log'!$AC$7:$AC$46))*(IFERROR(VALUE(MID('10. Activity Data Log'!$AD$7:$AD$46,2,1)),99)<='7. IPTT'!$C$3)*N('10. Activity Data Log'!$P$7:$P$46))+SUMPRODUCT(ISNUMBER(SEARCH($C23,'11. Distribution Log'!$AH$7:$AH$46))*(IFERROR(VALUE(MID('11. Distribution Log'!$AI$7:$AI$46,2,1)),99)<='7. IPTT'!$C$3)*N('11. Distribution Log'!$R$7:$R$46))+SUMPRODUCT(ISNUMBER(SEARCH($C23,'10. Activity Data Log'!$AC$7:$AC$46))*(IFERROR(VALUE(MID('10. Activity Data Log'!$AD$7:$AD$46,2,1)),99)<='7. IPTT'!$C$3)*N('10. Activity Data Log'!$T$7:$T$46))+SUMPRODUCT(ISNUMBER(SEARCH($C23,'11. Distribution Log'!$AH$7:$AH$46))*(IFERROR(VALUE(MID('11. Distribution Log'!$AI$7:$AI$46,2,1)),99)<='7. IPTT'!$C$3)*N('11. Distribution Log'!$V$7:$V$46)),0) -> 0 | AK23: =IFERROR(SUMPRODUCT(ISNUMBER(SEARCH($C23,'10. Activity Data Log'!$AC$7:$AC$46))*(IFERROR(VALUE(MID('10. Activity Data Log'!$AD$7:$AD$46,2,1)),99)<='7. IPTT'!$C$3)*N('10. Activity Data Log'!$N$7:$N$46))+SUMPRODUCT(ISNUMBER(SEARCH($C23,'11. Distribution Log'!$AH$7:$AH$46))*(IFERROR(VALUE(MID('11. Distribution Log'!$AI$7:$AI$46,2,1)),99)<='7. IPTT'!$C$3)*N('11. Distribution Log'!$P$7:$P$46))+SUMPRODUCT(ISNUMBER(SEARCH($C23,'10. Activity Data Log'!$AC$7:$AC$46))*(IFERROR(VALUE(MID('10. Activity Data Log'!$AD$7:$AD$46,2,1)),99)<='7. IPTT'!$C$3)*N('10. Activity Data Log'!$R$7:$R$46))+SUMPRODUCT(ISNUMBER(SEARCH($C23,'11. Distribution Log'!$AH$7:$AH$46))*(IFERROR(VALUE(MID('11. Distribution Log'!$AI$7:$AI$46,2,1)),99)<='7. IPTT'!$C$3)*N('11. Distribution Log'!$T$7:$T$46)),0) -> 0
B24: Result 1 | C24: R1-I9 | D24: R1-A1 | F24: % educational facilities that are carrying out environmental and climate friendly activities day-to-day | G24: Logframe (Annex I), Result 1 indicators - code R1-I9 | H24: Environmental/climate-friendly activities may take place during the school day (lesson modules) or after school (extra-curricular). Examples: planting/maintaining school (vegetable) gardens, tree planting, solid waste sorting, upcycling, energy/water-consumption reduction actions. | I24: Activity and event reports, photographic documentation, observation reports, and monitoring visit reports, compiled by Education MIS and MEAL staff. | J24: N/A (facility-level indicator) | K24: 0 | L24: 51 FIVDB-supported facilities | M24: 0.65 | N24: % | W24: =IFERROR(LOOKUP(2,1/(O24:V24<>""),O24:V24)/$M24,"") | X24: =IFERROR(IF(COUNT(O24:V24)=0,"No data yet",IF(LOOKUP(2,1/(O24:V24<>""),O24:V24)>=INDEX(O9:V9,$C$3),"On Track",IF(LOOKUP(2,1/(O24:V24<>""),O24:V24)>=INDEX(O9:V9,$C$3)*0.85,"Slightly Behind","Behind"))),"") -> No data yet | Y24: Activity/event reports, photographic documentation, monitoring visit reports | Z24: Source: activity and event reports, photographic documentation, observation reports, monitoring visit reports. Method: compiled by Education MIS and MEAL staff. Frequency: monthly and quarterly reporting; routine monitoring visits. | AA24: Facility Monitoring Checklist verified on-site quarterly; photographic evidence of the activity retained. | AB24: Monthly and quarterly reporting; routine monitoring visits | AC24: Education Officer | AD24: Field data collection & first-line reporting | AE24: Environmental activities may be deprioritised against core education delivery if resources/time are constrained. | AF24: [P]% of FIVDB-supported facilities ([X] of 51) were implementing environmental/climate-friendly activities as of [date], against a 65% target. | AG24: Narrative Proposal, Result 1 Indicator 9: consortium Baseline 0% (pilot intervention, not previously implemented) / consortium Target 65% of all 121 supported facilities (SC: 70 facilities target >=33 implementing; PLAN/FIVDB: 51 CBLFs target >=33 implementing), primarily via homestead vertical gardening adapted to the camp context. CLARIFICATION: 65% of FIVDB's 51 CBLFs = ~33 facilities. This is the officially approved consortium-wide %, applied identically to FIVDB's own facility count (not an FIVDB-specific calculation). | AH24: N/A | AI24: N/A | AJ24: N/A | AK24: N/A
B25: RESULT 2 - CHILD PROTECTION (FIVDB Activities 1, 3, 4, 5)
B26: Result 2 | C26: R2-I1 | D26: R2A1.2 | E26: R2A1.3, R2A1.4, R2A1.6, R2A1.7 | F26: (MANDATORY) % of children and caregivers whose urgent child protection needs/risks have been addressed through the case management process | G26: Logframe (Annex I), Result 2 indicators - code R2-I1 | H26: Numerator = children and caregivers surveyed reporting their urgent child protection needs were addressed via the case-management (CM) process. Denominator = total children and caregivers surveyed who received CM. Survey administered at case closure or case follow-up; children and caregivers measured separately. Case-management quality demonstrated by meeting the CP Case Management Minimum Standards in Humanitarian Settings (7-step process). | I26: CPIMS+, case management registers, individual case files/hard-copy case records, and survey reports, recorded by caseworkers. | J26: Children and caregivers measured separately; sex, age | K26: 0 | L26: ~320 FIVDB case-management caseload (A1) | M26: 0.95 | N26: % | W26: =IFERROR(LOOKUP(2,1/(O26:V26<>""),O26:V26)/$M26,"") | X26: =IFERROR(IF(COUNT(O26:V26)=0,"No data yet",IF(LOOKUP(2,1/(O26:V26<>""),O26:V26)>=INDEX(O9:V9,$C$3),"On Track",IF(LOOKUP(2,1/(O26:V26<>""),O26:V26)>=INDEX(O9:V9,$C$3)*0.85,"Slightly Behind","Behind"))),"") -> No data yet | Y26: CPIMS+, case management registers, individual case files, survey reports | Z26: Source: CPIMS+, case management registers, individual case files/hard-copy case records, survey reports. Method: recorded by caseworkers, per the CP Case Management Minimum Standards (7-step process). Frequency: case reporting monthly; satisfaction survey reports annually. | AA26: PIB technical supervisor reviews a sample of closed case files each month against closure-survey responses. | AB26: Case reporting monthly; satisfaction survey reports annually | AC26: Technical Coordinator–Protection | AD26: Field data collection, case oversight & first-line reporting | AE26: Case backlog if caseworker-to-case ratio exceeds CPMS standards; high mobility of families may disrupt follow-up. | AF26: [P]% of children and caregivers surveyed reported that their urgent child protection needs were addressed through FIVDB's case management process during [reporting period], against a 95% target. | AG26: Narrative Proposal, Result 2 Indicator 1 (mandatory): Baseline 0 (not systematically tracked pre-action) / Target 95%, based on performance achieved in previous ECHO-funded CP case management in Cox's Bazar, factoring anticipated caseload/complexity, staffing/supervision capacity and planned investment in caseworker training and quality referrals. CLARIFICATION: 95% is the officially approved Logframe (Annex I) target, not FIVDB-set. R2-I1 through R2-I5 percentages cluster in the 75-95% range because they come from the same approved Logframe table and comparable ECHO HIP 2023 baselines - each has its own distinct source paragraph in the Narrative Proposal, not a copied figure. | AH26: N/A | AI26: N/A | AJ26: N/A | AK26: N/A
B27: Result 2 | C27: R2-I2 | D27: R2A1.1 | E27: - | F27: % of children separated from or allegedly associated with armed groups and armed forces who benefit from appropriate care and services | G27: Logframe (Annex I), Result 2 indicators - code R2-I2 | H27: Children Associated with Armed Forces and Armed Groups (CAAFAG) = all children, including girls, under age 18 who are or have been recruited or used by any armed force or group in any capacity. Numerator = identified CAAFAG children who receive care/services. Denominator = total identified CAAFAG children. Appropriate care/services can include health care, education, legal aid, MHPSS, interim care, reintegration into family/community. Measure each service separately. | I27: CPIMS+, case management registers, individual case files/hard-copy case records, and relevant survey reports, recorded by caseworkers. | J27: Sex, age | K27: 0 | L27: Subset of 314 caseload (# CAAFAG confirmed at identification) | M27: 0.8 | N27: % | W27: =IFERROR(LOOKUP(2,1/(O27:V27<>""),O27:V27)/$M27,"") | X27: =IFERROR(IF(COUNT(O27:V27)=0,"No data yet",IF(LOOKUP(2,1/(O27:V27<>""),O27:V27)>=INDEX(O9:V9,$C$3),"On Track",IF(LOOKUP(2,1/(O27:V27<>""),O27:V27)>=INDEX(O9:V9,$C$3)*0.85,"Slightly Behind","Behind"))),"") -> No data yet | Y27: Case management database | Z27: Source: CPIMS+, case management registers, individual case files/hard-copy case records, relevant survey reports. Method: recorded by caseworkers, measured per service type separately. Frequency: case data daily; reporting monthly; survey reports annually. | AA27: Case-file review cross-checked with service-provision records (health, education, legal aid, MHPSS, interim care). | AB27: Case data daily; reporting monthly; survey reports annually | AC27: Technical Coordinator–Protection | AD27: Field data collection, case oversight & first-line reporting | AE27: Under-identification of CAAFAG cases due to stigma/fear of reprisal; service availability gaps at receiving agencies. | AF27: [P]% of identified CAAFAG children benefited from at least one appropriate care/service during [reporting period], against an 80% target. | AG27: Narrative Proposal, Result 2 Indicator 2 (CAAFAG): Baseline 0% (no action-specific reference value) / Target 80%, informed by previous ECHO-funded CAAFAG/CP programming in Cox's Bazar, factoring expected caseload, sensitivity/complexity of CAAFAG cases, security/access constraints, and referral-pathway capacity. CLARIFICATION: 80% applies only to children identified as CAAFAG within FIVDB's caseload - not a general child-protection percentage across all 320 case-management children. | AH27: N/A | AI27: N/A | AJ27: N/A | AK27: N/A
B28: Result 2 | C28: R2-I3 | D28: R2A1.5 | E28: R2A4.1, R2A4.4, R2A5.1, R2A5.3 | F28: Average % knowledge increase amongst participants on the protection subject in focus | G28: Logframe (Annex I), Result 2 indicators - code R2-I3 | H28: Comments field defines: type of participants (population/authorities/armed forces/armed groups etc.), number of expected participants, and subject of training. Reports disaggregate number of participants by age and sex. | I28: Pre-test and post-test assessment forms, training attendance records, and capacity assessment survey questionnaires, compiled by CP, MIS and MEAL focal points. | J28: Age, sex | K28: 0 | L28: FIVDB frontline staff/volunteers attending R2-A5 trainings | M28: 0.8 | N28: % | W28: =IFERROR(LOOKUP(2,1/(O28:V28<>""),O28:V28)/$M28,"") | X28: =IFERROR(IF(COUNT(O28:V28)=0,"No data yet",IF(LOOKUP(2,1/(O28:V28<>""),O28:V28)>=INDEX(O9:V9,$C$3),"On Track",IF(LOOKUP(2,1/(O28:V28<>""),O28:V28)>=INDEX(O9:V9,$C$3)*0.85,"Slightly Behind","Behind"))),"") -> No data yet | Y28: Pre/post assessment forms, training attendance records, capacity assessment survey | Z28: Source: pre-test and post-test assessment forms, training attendance records, capacity assessment survey questionnaires. Method: compiled by CP, MIS and MEAL focal points; participant type/number/subject specified in comments. Frequency: assessment reports monthly; comprehensive training reports quarterly; survey reports annually. | AA28: MEAL Officer verifies pre/post test scoring for each session; PIB reviews a sample of training packs quarterly. | AB28: Assessment reports monthly; comprehensive training reports quarterly; survey reports annually | AC28: MEAL Officer | AD28: Data consolidation, quality assurance & reporting | AE28: High staff/volunteer turnover may erode cumulative knowledge retention between training cycles. | AF28: Frontline staff and volunteers trained by FIVDB showed an average knowledge increase of [P]% during [reporting period], against an 80% target. | AG28: Narrative Proposal, Result 2 Indicator 3: Baseline 0% (increase is measured through pre/post tests introduced under the action) / Target 80% average knowledge increase, informed by performance in previous HIP activities. Consortium-wide, this indicator covers an estimated 4,805 unique participants (carers, adolescents, community leaders, para-social workers, volunteers, multi-sector staff) across all capacity-building activities on protection subjects. CLARIFICATION: Measures average knowledge GAIN (post-test minus pre-test, divided by pre-test), not an absolute post-test score. | AH28: N/A | AI28: N/A | AJ28: N/A | AK28: N/A
B29: Result 2 | C29: R2-I4 | D29: R2A3.1 | E29: R2A3.2, R2A3.3, R2A3.4, R2A3.5, R2A3.6, R2A4.2, R2A4.3, R2A4.5, R2A4.6, INC-5, GEN-2 | F29: (MANDATORY) % of persons who receive appropriate PSS reporting improved mental health and psychosocial well-being OR capacities to cope | G29: Logframe (Annex I), Result 2 indicators - code R2-I4 | H29: Mental health and psychosocial wellbeing measured using one of the six IASC Common M&E Framework domains: functioning; subjective wellbeing; disabling distress/symptoms; coping; social behaviour; social connectedness. Delivered as a layered system of complementary supports, with safe, confidential, timely referrals, per IASC MHPSS in Emergency Settings Guideline and the MHPSS Minimum Service Package. | I29: Standardized pre- and post-assessment tools (validated for context/language), wellbeing surveys, focus group discussions, key informant interviews, case files, and MHPSS activity records, following the IASC Common M&E Framework. | J29: Sex, age; IASC domain used | K29: 0 | L29: ~8,640 in PALS/MPCAC/WGSS/community groups (A3-A4) | M29: 0.8 | N29: % | W29: =IFERROR(LOOKUP(2,1/(O29:V29<>""),O29:V29)/$M29,"") | X29: =IFERROR(IF(COUNT(O29:V29)=0,"No data yet",IF(LOOKUP(2,1/(O29:V29<>""),O29:V29)>=INDEX(O9:V9,$C$3),"On Track",IF(LOOKUP(2,1/(O29:V29<>""),O29:V29)>=INDEX(O9:V9,$C$3)*0.85,"Slightly Behind","Behind"))),"") -> No data yet | Y29: Pre/post PSS assessment tool (IASC domains), wellbeing surveys, case files | Z29: Source: standardized pre-/post-assessment tools (validated for context/language), wellbeing surveys, focus group discussions, key informant interviews, case files, MHPSS activity records. Method: following the IASC Common M&E Framework (6 domains). Frequency: recorded at PSS phase start/end; compiled monthly for ongoing monitoring; comprehensive outcome reports (quantitative + qualitative) annually. | AA29: PIB technical supervisor reviews a sample of pre/post assessment pairs each quarter for consistency. | AB29: Recorded at PSS phase start/end; compiled monthly for ongoing monitoring; comprehensive outcome reports (quantitative + qualitative) annually | AC29: Technical Coordinator–Protection | AD29: Field data collection, case oversight & first-line reporting | AE29: Under-reporting of distress due to stigma; drop-out between group entry and exit reduces paired-assessment sample size. | AF29: [P]% of persons receiving psychosocial support through FIVDB's MPCAC/WGSS/community-group sessions reported improved wellbeing or coping during [reporting period], against an 80% target. | AG29: Narrative Proposal, Result 2 Indicator 7 (mandatory): Baseline 0% (wellbeing/coping can only be measured after participants complete PSS support) / Target 80%, justified by previous PSS intervention results, the IASC-aligned package delivered through MPCACs/WGSSs, trained facilitators, and functioning referral pathways. CLARIFICATION: Numbered 'Result 2 Indicator 7' in the consortium's full 8-indicator Result 2 set (3 of the 8 are SC-led GBV-specific reference items tracked separately - see R2-Ref rows). | AH29: N/A | AI29: N/A | AJ29: N/A | AK29: N/A
B30: Result 2 | C30: R2-I5 | D30: INC-12 | E30: - | F30: % of caseworkers whose knowledge assessment score is at least 70% | G30: Logframe (Annex I), Result 2 indicators - code R2-I5 | H30: Numerator = case workers who score 70% or higher on the knowledge assessment. Denominator = case workers who finalised the Case Worker Capacity Assessment. Assesses caseworker attitudes, knowledge and skills against minimum competency standards for case management service providers, identifying possible service-quality gaps. | I30: Case Worker Capacity Assessment Tool, applied by implementing-partner staff and the consortium's Case Management/MEAL teams. | J30: Sex | K30: 0 | L30: All active FIVDB case workers | M30: 0.75 | N30: % | W30: =IFERROR(LOOKUP(2,1/(O30:V30<>""),O30:V30)/$M30,"") | X30: =IFERROR(IF(COUNT(O30:V30)=0,"No data yet",IF(LOOKUP(2,1/(O30:V30<>""),O30:V30)>=INDEX(O9:V9,$C$3),"On Track",IF(LOOKUP(2,1/(O30:V30<>""),O30:V30)>=INDEX(O9:V9,$C$3)*0.85,"Slightly Behind","Behind"))),"") -> No data yet | Y30: Case Worker Capacity Assessment Tool | Z30: Source: Case Worker Capacity Assessment Tool. Method: applied by implementing-partner staff and the consortium's Case Management/MEAL teams, assessed against minimum competency standards for case management service providers. Frequency: annually. | AA30: PIB technical supervisor co-scores a sample of assessments to check inter-rater consistency. | AB30: Annually | AC30: Technical Coordinator–Protection | AD30: Field data collection, case oversight & first-line reporting | AE30: High case-worker turnover may mean new starters are assessed before consolidating knowledge; coaching capacity constraints. | AF30: [P]% of FIVDB case workers assessed scored 70% or above on the Case Worker Capacity Assessment during [reporting period], against a 75% target. | AG30: Narrative Proposal, Result 2 Indicator 8 (Protection of individuals): Baseline 75% expected pass rate is itself the assumption underpinning the target - the Narrative states 'it is expected that at least 75% of trainees will achieve a minimum score of 70%'. Results to be disaggregated by agency (SC/PLAN), sex, age, disability status and role where feasible. CLARIFICATION: Numerator = caseworkers scoring >=70%; Denominator = caseworkers who completed the assessment (not all caseworkers on payroll, only those assessed). | AH30: N/A | AI30: N/A | AJ30: N/A | AK30: N/A
B31: RESULT 2 - REFERENCE ONLY: GBV Case Management (SC-led, Activity 2 - NOT delivered by FIVDB)
B32: Result 2 (ref.) | C32: R2-Ref1 | D32: R2-A2 (SC) | F32: (MANDATORY) Number of minimum standards for care for survivors achieved | G32: Logframe (Annex I), Result 2 indicators - SC-led (reference only, not FIVDB-delivered) | H32: For baseline: Numerator = minimum standards of care for survivors met prior to action start. Denominator = total minimum standards of care for survivors. For target: Numerator = standards met prior to action start PLUS standards to be met within the action timeframe. Denominator = total minimum standards. Checklist contextualised and submitted at proposal stage. | I32: Structured service quality assessment using a contextualized GBV Minimum Standards Checklist (adapted from the Inter-Agency GBV Case Management Guidelines, 2017); only standards assessed as 'Met' count toward the numerator; consolidated at service-point level and validated by GBV supervisors. | J32: N/A (standards checklist, SC-led) | K32: 0 | L32: N/A | M32: N/A | N32: Number | O32: =IF(1>'7. IPTT'!$C$3,"",IFERROR((SUMPRODUCT(ISNUMBER(SEARCH($C32,'8. Activity Tracker'!$J$7:$J$93))*N('8. Activity Tracker'!V$7:V$93))),0)) -> 0 | P32: =IF(2>'7. IPTT'!$C$3,"",IFERROR((SUMPRODUCT(ISNUMBER(SEARCH($C32,'8. Activity Tracker'!$J$7:$J$93))*N('8. Activity Tracker'!V$7:V$93))+SUMPRODUCT(ISNUMBER(SEARCH($C32,'8. Activity Tracker'!$J$7:$J$93))*N('8. Activity Tracker'!W$7:W$93))),0)) | Q32: =IF(3>'7. IPTT'!$C$3,"",IFERROR((SUMPRODUCT(ISNUMBER(SEARCH($C32,'8. Activity Tracker'!$J$7:$J$93))*N('8. Activity Tracker'!V$7:V$93))+SUMPRODUCT(ISNUMBER(SEARCH($C32,'8. Activity Tracker'!$J$7:$J$93))*N('8. Activity Tracker'!W$7:W$93))+SUMPRODUCT(ISNUMBER(SEARCH($C32,'8. Activity Tracker'!$J$7:$J$93))*N('8. Activity Tracker'!X$7:X$93))),0)) | R32: =IF(4>'7. IPTT'!$C$3,"",IFERROR((SUMPRODUCT(ISNUMBER(SEARCH($C32,'8. Activity Tracker'!$J$7:$J$93))*N('8. Activity Tracker'!V$7:V$93))+SUMPRODUCT(ISNUMBER(SEARCH($C32,'8. Activity Tracker'!$J$7:$J$93))*N('8. Activity Tracker'!W$7:W$93))+SUMPRODUCT(ISNUMBER(SEARCH($C32,'8. Activity Tracker'!$J$7:$J$93))*N('8. Activity Tracker'!X$7:X$93))+SUMPRODUCT(ISNUMBER(SEARCH($C32,'8. Activity Tracker'!$J$7:$J$93))*N('8. Activity Tracker'!Y$7:Y$93))),0)) | S32: =IF(5>'7. IPTT'!$C$3,"",IFERROR((SUMPRODUCT(ISNUMBER(SEARCH($C32,'8. Activity Tracker'!$J$7:$J$93))*N('8. Activity Tracker'!V$7:V$93))+SUMPRODUCT(ISNUMBER(SEARCH($C32,'8. Activity Tracker'!$J$7:$J$93))*N('8. Activity Tracker'!W$7:W$93))+SUMPRODUCT(ISNUMBER(SEARCH($C32,'8. Activity Tracker'!$J$7:$J$93))*N('8. Activity Tracker'!X$7:X$93))+SUMPRODUCT(ISNUMBER(SEARCH($C32,'8. Activity Tracker'!$J$7:$J$93))*N('8. Activity Tracker'!Y$7:Y$93))+SUMPRODUCT(ISNUMBER(SEARCH($C32,'8. Activity Tracker'!$J$7:$J$93))*N('8. Activity Tracker'!Z$7:Z$93))),0)) | T32: =IF(6>'7. IPTT'!$C$3,"",IFERROR((SUMPRODUCT(ISNUMBER(SEARCH($C32,'8. Activity Tracker'!$J$7:$J$93))*N('8. Activity Tracker'!V$7:V$93))+SUMPRODUCT(ISNUMBER(SEARCH($C32,'8. Activity Tracker'!$J$7:$J$93))*N('8. Activity Tracker'!W$7:W$93))+SUMPRODUCT(ISNUMBER(SEARCH($C32,'8. Activity Tracker'!$J$7:$J$93))*N('8. Activity Tracker'!X$7:X$93))+SUMPRODUCT(ISNUMBER(SEARCH($C32,'8. Activity Tracker'!$J$7:$J$93))*N('8. Activity Tracker'!Y$7:Y$93))+SUMPRODUCT(ISNUMBER(SEARCH($C32,'8. Activity Tracker'!$J$7:$J$93))*N('8. Activity Tracker'!Z$7:Z$93))+SUMPRODUCT(ISNUMBER(SEARCH($C32,'8. Activity Tracker'!$J$7:$J$93))*N('8. Activity Tracker'!AA$7:AA$93))),0)) | U32: =IF(7>'7. IPTT'!$C$3,"",IFERROR((SUMPRODUCT(ISNUMBER(SEARCH($C32,'8. Activity Tracker'!$J$7:$J$93))*N('8. Activity Tracker'!V$7:V$93))+SUMPRODUCT(ISNUMBER(SEARCH($C32,'8. Activity Tracker'!$J$7:$J$93))*N('8. Activity Tracker'!W$7:W$93))+SUMPRODUCT(ISNUMBER(SEARCH($C32,'8. Activity Tracker'!$J$7:$J$93))*N('8. Activity Tracker'!X$7:X$93))+SUMPRODUCT(ISNUMBER(SEARCH($C32,'8. Activity Tracker'!$J$7:$J$93))*N('8. Activity Tracker'!Y$7:Y$93))+SUMPRODUCT(ISNUMBER(SEARCH($C32,'8. Activity Tracker'!$J$7:$J$93))*N('8. Activity Tracker'!Z$7:Z$93))+SUMPRODUCT(ISNUMBER(SEARCH($C32,'8. Activity Tracker'!$J$7:$J$93))*N('8. Activity Tracker'!AA$7:AA$93))+SUMPRODUCT(ISNUMBER(SEARCH($C32,'8. Activity Tracker'!$J$7:$J$93))*N('8. Activity Tracker'!AB$7:AB$93))),0)) | V32: =IF(8>'7. IPTT'!$C$3,"",IFERROR((SUMPRODUCT(ISNUMBER(SEARCH($C32,'8. Activity Tracker'!$J$7:$J$93))*N('8. Activity Tracker'!V$7:V$93))+SUMPRODUCT(ISNUMBER(SEARCH($C32,'8. Activity Tracker'!$J$7:$J$93))*N('8. Activity Tracker'!W$7:W$93))+SUMPRODUCT(ISNUMBER(SEARCH($C32,'8. Activity Tracker'!$J$7:$J$93))*N('8. Activity Tracker'!X$7:X$93))+SUMPRODUCT(ISNUMBER(SEARCH($C32,'8. Activity Tracker'!$J$7:$J$93))*N('8. Activity Tracker'!Y$7:Y$93))+SUMPRODUCT(ISNUMBER(SEARCH($C32,'8. Activity Tracker'!$J$7:$J$93))*N('8. Activity Tracker'!Z$7:Z$93))+SUMPRODUCT(ISNUMBER(SEARCH($C32,'8. Activity Tracker'!$J$7:$J$93))*N('8. Activity Tracker'!AA$7:AA$93))+SUMPRODUCT(ISNUMBER(SEARCH($C32,'8. Activity Tracker'!$J$7:$J$93))*N('8. Activity Tracker'!AB$7:AB$93))+SUMPRODUCT(ISNUMBER(SEARCH($C32,'8. Activity Tracker'!$J$7:$J$93))*N('8. Activity Tracker'!AC$7:AC$93))),0)) | W32: N/A | X32: N/A | Y32: GBV minimum standards checklist | Z32: Source: contextualized GBV Minimum Standards Checklist (adapted from the Inter-Agency GBV Case Management Guidelines, 2017). Method: only standards assessed as 'Met' count toward the numerator; consolidated at service-point level and validated by GBV supervisors. Frequency: initial assessment followed by quarterly monitoring. | AA32: N/A - SC-led verification. | AB32: Initial assessment followed by quarterly monitoring | AC32: SC | AD32: Field data collection & first-line reporting | AE32: Not a FIVDB risk owner - dependent on SC's GBV case-management capacity and standards implementation. | AF32: =IFERROR("During the reporting period (cumulative through Q"&'7. IPTT'!$C$3&"), FIVDB reported "&TEXT(LOOKUP(2,1/(O32:V32<>""),O32:V32),"#,##0")&" against the indicator '"&$F32&"' - "&TEXT($W32,"0%")&" of the "&TEXT($M32,"#,##0")&" life-of-project target. "&"Disaggregated: "&TEXT($AH32,"#,##0")&" girls (<18), "&TEXT($AI32,"#,##0")&" boys (<18), "&TEXT($AJ32,"#,##0")&" women (18+), "&TEXT($AK32,"#,##0")&" men (18+).","During the reporting period, FIVDB reported progress against this indicator - see Cumulative Actual to Date and % of LOP Target Achieved.") -> During the reporting period (cumulative through Q1), FIVDB reported 0 against the indicator '(MANDATORY) Number of minimum standards for care for survivors achieved' - N/A of the N/A life-of-project target. Disaggregated: 0 girls (<18), 0 boys (<18), 0 women (18+), 0 men (18+). | AG32: Narrative Proposal, Result 2 Indicator 5 (GBV, mandatory, minimum standards for survivor care): Baseline 0 (checklist-based measurement introduced under this action). Based on a review of 31 minimum standards (Annex 27): SC target = 16 standards (reflecting its EiE, protection and health interventions); PLAN target = 12 standards (aligned with its EiE and Child Protection interventions - separate from, and not solely 'SC-led', though FIVDB's own role in the underlying GBV case management activity, R2-A2, remains referral-only). CLARIFICATION: Annex 27 = the GBV Minimum Standards Checklist referenced in the Narrative Proposal (Result 2, Activity 2 section) - an annex to the consortium's DG ECHO Single Form, held by PIB/SC, not a standalone FIVDB document. This row is shown for traceability only; FIVDB is not directly accountable for it since the underlying Activity 2 is SC-led. | AH32: =IFERROR(SUMPRODUCT(ISNUMBER(SEARCH($C32,'10. Activity Data Log'!$AC$7:$AC$46))*(IFERROR(VALUE(MID('10. Activity Data Log'!$AD$7:$AD$46,2,1)),99)<='7. IPTT'!$C$3)*N('10. Activity Data Log'!$O$7:$O$46))+SUMPRODUCT(ISNUMBER(SEARCH($C32,'11. Distribution Log'!$AH$7:$AH$46))*(IFERROR(VALUE(MID('11. Distribution Log'!$AI$7:$AI$46,2,1)),99)<='7. IPTT'!$C$3)*N('11. Distribution Log'!$Q$7:$Q$46))+SUMPRODUCT(ISNUMBER(SEARCH($C32,'10. Activity Data Log'!$AC$7:$AC$46))*(IFERROR(VALUE(MID('10. Activity Data Log'!$AD$7:$AD$46,2,1)),99)<='7. IPTT'!$C$3)*N('10. Activity Data Log'!$S$7:$S$46))+SUMPRODUCT(ISNUMBER(SEARCH($C32,'11. Distribution Log'!$AH$7:$AH$46))*(IFERROR(VALUE(MID('11. Distribution Log'!$AI$7:$AI$46,2,1)),99)<='7. IPTT'!$C$3)*N('11. Distribution Log'!$U$7:$U$46)),0) -> 0 | AI32: =IFERROR(SUMPRODUCT(ISNUMBER(SEARCH($C32,'10. Activity Data Log'!$AC$7:$AC$46))*(IFERROR(VALUE(MID('10. Activity Data Log'!$AD$7:$AD$46,2,1)),99)<='7. IPTT'!$C$3)*N('10. Activity Data Log'!$M$7:$M$46))+SUMPRODUCT(ISNUMBER(SEARCH($C32,'11. Distribution Log'!$AH$7:$AH$46))*(IFERROR(VALUE(MID('11. Distribution Log'!$AI$7:$AI$46,2,1)),99)<='7. IPTT'!$C$3)*N('11. Distribution Log'!$O$7:$O$46))+SUMPRODUCT(ISNUMBER(SEARCH($C32,'10. Activity Data Log'!$AC$7:$AC$46))*(IFERROR(VALUE(MID('10. Activity Data Log'!$AD$7:$AD$46,2,1)),99)<='7. IPTT'!$C$3)*N('10. Activity Data Log'!$Q$7:$Q$46))+SUMPRODUCT(ISNUMBER(SEARCH($C32,'11. Distribution Log'!$AH$7:$AH$46))*(IFERROR(VALUE(MID('11. Distribution Log'!$AI$7:$AI$46,2,1)),99)<='7. IPTT'!$C$3)*N('11. Distribution Log'!$S$7:$S$46)),0) -> 0 | AJ32: =IFERROR(SUMPRODUCT(ISNUMBER(SEARCH($C32,'10. Activity Data Log'!$AC$7:$AC$46))*(IFERROR(VALUE(MID('10. Activity Data Log'!$AD$7:$AD$46,2,1)),99)<='7. IPTT'!$C$3)*N('10. Activity Data Log'!$P$7:$P$46))+SUMPRODUCT(ISNUMBER(SEARCH($C32,'11. Distribution Log'!$AH$7:$AH$46))*(IFERROR(VALUE(MID('11. Distribution Log'!$AI$7:$AI$46,2,1)),99)<='7. IPTT'!$C$3)*N('11. Distribution Log'!$R$7:$R$46))+SUMPRODUCT(ISNUMBER(SEARCH($C32,'10. Activity Data Log'!$AC$7:$AC$46))*(IFERROR(VALUE(MID('10. Activity Data Log'!$AD$7:$AD$46,2,1)),99)<='7. IPTT'!$C$3)*N('10. Activity Data Log'!$T$7:$T$46))+SUMPRODUCT(ISNUMBER(SEARCH($C32,'11. Distribution Log'!$AH$7:$AH$46))*(IFERROR(VALUE(MID('11. Distribution Log'!$AI$7:$AI$46,2,1)),99)<='7. IPTT'!$C$3)*N('11. Distribution Log'!$V$7:$V$46)),0) -> 0 | AK32: =IFERROR(SUMPRODUCT(ISNUMBER(SEARCH($C32,'10. Activity Data Log'!$AC$7:$AC$46))*(IFERROR(VALUE(MID('10. Activity Data Log'!$AD$7:$AD$46,2,1)),99)<='7. IPTT'!$C$3)*N('10. Activity Data Log'!$N$7:$N$46))+SUMPRODUCT(ISNUMBER(SEARCH($C32,'11. Distribution Log'!$AH$7:$AH$46))*(IFERROR(VALUE(MID('11. Distribution Log'!$AI$7:$AI$46,2,1)),99)<='7. IPTT'!$C$3)*N('11. Distribution Log'!$P$7:$P$46))+SUMPRODUCT(ISNUMBER(SEARCH($C32,'10. Activity Data Log'!$AC$7:$AC$46))*(IFERROR(VALUE(MID('10. Activity Data Log'!$AD$7:$AD$46,2,1)),99)<='7. IPTT'!$C$3)*N('10. Activity Data Log'!$R$7:$R$46))+SUMPRODUCT(ISNUMBER(SEARCH($C32,'11. Distribution Log'!$AH$7:$AH$46))*(IFERROR(VALUE(MID('11. Distribution Log'!$AI$7:$AI$46,2,1)),99)<='7. IPTT'!$C$3)*N('11. Distribution Log'!$T$7:$T$46)),0) -> 0
B33: Result 2 (ref.) | C33: R2-Ref2 | D33: R2-A2 (SC) | F33: Number of individuals benefiting from GBV response services (SC-led, R2-A2) | G33: Logframe (Annex I), Result 2 indicators - SC-led (reference only, not FIVDB-delivered) | H33: Covers response services to survivors of GBV (women, men, girls, boys); disaggregated by age, sex and service(s) received; strategies applied to avoid double counting. | I33: SC's GBV case-management database. FIVDB contributes only via safe identification/referral, not direct service delivery, so this indicator is tracked by SC, not FIVDB. | J33: Age, sex, service type (SC-led) | K33: 0 | L33: N/A | M33: N/A | N33: % | O33: N/A | P33: N/A | Q33: N/A | R33: N/A | S33: N/A | T33: N/A | U33: N/A | V33: N/A | W33: N/A | X33: N/A | Y33: GBV case management database (SC) | Z33: Not specified in Narrative Proposal - to be defined by FIVDB/PIB. | AA33: N/A - SC-led verification. | AB33: n/a | AC33: SC | AD33: Field data collection & first-line reporting | AE33: Not a FIVDB risk owner - dependent on SC's GBV case-management capacity. | AF33: Not reported in FIVDB's own narrative - this is delivered by SC under Result 2-Activity 2. Where relevant, describe FIVDB's referral contribution qualitatively rather than against this target. | AG33: Consortium target 750 - not FIVDB-delivered; referral only | AH33: N/A | AI33: N/A | AJ33: N/A | AK33: N/A
B34: Result 2 (ref.) | C34: R2-Ref3 | D34: R2-A2 (SC) | F34: % of GBV high-risk cases supervised (SC-led, R2-A2) | G34: Logframe (Annex I), Result 2 indicators - SC-led (reference only, not FIVDB-delivered) | H34: Numerator = total high-risk cases reviewed by a supervisor. Denominator = total high-risk cases in the case-management process. High-risk = immediate threat to survivor safety/health requiring urgent action. | I34: SC's GBV supervision log (one-on-one, group, on-the-job observation/coaching, team meetings). Not applicable to FIVDB, which does not hold GBV case-management caseload under R2-A2. | J34: N/A (case-level, SC-led) | K34: 0 | L34: N/A | M34: N/A | N34: % | O34: N/A | P34: N/A | Q34: N/A | R34: N/A | S34: N/A | T34: N/A | U34: N/A | V34: N/A | W34: N/A | X34: N/A | Y34: GBV case management database (SC) | Z34: Not specified in Narrative Proposal - to be defined by FIVDB/PIB. | AA34: N/A - SC-led verification. | AB34: n/a | AC34: SC | AD34: Field data collection & first-line reporting | AE34: Not a FIVDB risk owner - FIVDB has no GBV case-management caseload under R2-A2. | AF34: Not reported in FIVDB's own narrative - this is delivered by SC under Result 2-Activity 2; FIVDB has no caseload against this indicator. | AG34: Consortium target 95% - not FIVDB-delivered; referral only | AH34: N/A | AI34: N/A | AJ34: N/A | AK34: N/A
B35: SPECIFIC-OBJECTIVE / CROSS-CUTTING INDICATORS
B36: Specific objective | C36: SO-I1 | D36: R1A5.2 | E36: R1A5.3, INC-6, GEN-4 | F36: % of beneficiaries reporting that humanitarian assistance is delivered in a safe, accessible, accountable and participatory manner | G36: Logframe (Annex I), Specific Objective indicators - code SO-I1 | H36: This is more a process than an outcome indicator; DG ECHO wants to ensure sufficient attention is given to protection mainstreaming so corrective measures are identified and implemented when required during the action. At reporting stage, also state the total number of beneficiaries interviewed. Disaggregate figures (% and absolute numbers) by sex, age and disability. | I36: KOI perception surveys, Post-Distribution Monitoring (PDM) reports, client satisfaction surveys, and outcome assessment reports, administered by skilled enumerators and implementing-partner staff. | J36: Sex, age, disability | K36: 0 | L36: Survey sample (size confirmed per round) | M36: 0.85 | N36: % | W36: =IFERROR(LOOKUP(2,1/(O36:V36<>""),O36:V36)/$M36,"") | X36: =IFERROR(IF(COUNT(O36:V36)=0,"No data yet",IF(LOOKUP(2,1/(O36:V36<>""),O36:V36)>=INDEX(O9:V9,$C$3),"On Track",IF(LOOKUP(2,1/(O36:V36<>""),O36:V36)>=INDEX(O9:V9,$C$3)*0.85,"Slightly Behind","Behind"))),"") -> No data yet | Y36: Community perception survey | Z36: Source: KOI perception surveys, Post-Distribution Monitoring (PDM) reports, client satisfaction surveys, outcome assessment reports. Method: administered by skilled enumerators and implementing-partner staff, disaggregated by sex, age and disability. Frequency: every four months, plus annual reporting. | AA36: Survey tool piloted and reviewed by PIB M&E before each round; data entry double-checked against paper/digital forms. | AB36: Every four months, plus annual reporting | AC36: MEAL Officer | AD36: Data consolidation, quality assurance & reporting | AE36: Survey response bias or low response rate; sensitive questions may be under-reported without skilled enumerators. | AF36: [P]% of [N] beneficiaries surveyed in FIVDB's camps reported that assistance was delivered safely, accessibly, accountably and participatorily, against an 85% target. | AG36: Consortium specific-objective target 85%; FIVDB tracks its respondent share | AH36: N/A | AI36: N/A | AJ36: N/A | AK36: N/A
B37: Specific objective | C37: SO-I2 | D37: R1-A1 to R1-A7 | F37: % targeted girls and boys who are retained in education at the end of the action | G37: Logframe (Annex I), Specific Objective indicators - code SO-I2 | H37: Measures the % of children targeted for EiE support who remain in some form of education at the end of the action. Targeted girls and boys = any child supported by the project (including those already enrolled at action start and those newly enrolled during the action). Retained = still enrolled in NFE or formal education at the end of the action; actions ending during school holidays use the last academic term as the end point. Learners completing the final grade of secondary school count as still in education. Disaggregate by sex, NFE type/level of education and disability. | I37: Enrolment registers, daily attendance sheets, retention tracking records, endline attendance documentation, cross-checked with the Education Management Information System (EMIS) database, compiled by CBLF facilitators and consolidated by the Education/MEAL team. | J37: Sex, level/type of education, disability | K37: 0 | L37: 1,224 targeted learners | M37: 0.9 | N37: % | W37: =IFERROR(LOOKUP(2,1/(O37:V37<>""),O37:V37)/$M37,"") | X37: =IFERROR(IF(COUNT(O37:V37)=0,"No data yet",IF(LOOKUP(2,1/(O37:V37<>""),O37:V37)>=INDEX(O9:V9,$C$3),"On Track",IF(LOOKUP(2,1/(O37:V37<>""),O37:V37)>=INDEX(O9:V9,$C$3)*0.85,"Slightly Behind","Behind"))),"") -> No data yet | Y37: CBLF enrolment & tracking registers | Z37: Source: enrolment registers, daily attendance sheets, retention tracking records, endline attendance documentation. Method: cross-checked with the Education Management Information System (EMIS) database; compiled by CBLF facilitators and consolidated by the Education/MEAL team. Frequency: monthly reviews, final retention calculation at endline. | AA37: Endline tracking cross-checked against attendance/drop-out records; PIB verifies a sample against household follow-up. | AB37: Monthly reviews; final retention calculation at endline | AC37: Education Officer | AD37: Field data collection & first-line reporting | AE37: High mobility of the Rohingya population (incl. potential relocation to Bhasan Char) may affect endline tracking accuracy. | AF37: [P]% of FIVDB's 1,224 targeted learners ([X] children) remained enrolled in education at the end of the action, against a 90% target. | AG37: Consortium specific-objective target 90%; applies to FIVDB's 1,224 learners (updated from 1,187 per Detailed Budget/Narrative Proposal) | AH37: N/A | AI37: N/A | AJ37: N/A | AK37: N/A

Sheet 8. Activity Tracker
B2: 8. Activity Tracker - FIVDB Implementation Activities (Sub-activity Level)
B3: Tracks physical progress of FIVDB's workplan sub-activities, separate from the outcome/output indicators in the IPTT. Each Activity Code (R1A1, R2A1, etc.) IS the FIVDB Detailed Budget's own Reference code - used directly, not a cross-reference. 'Sub-sub-activity' further splits a sub-activity into its distinct component tasks where useful (e.g. 'establish' vs 'refurbish', or two different kit types bundled in one description) - populated only where a split adds real tracking value; blank elsewhere. 'Process (How Conducted)' summarises the delivery method for each sub-activity; 'Contribution to Indicator' explains how the sub-activity's output feeds its linked IPTT indicator(s). 'Source Reference' cites the exact Detailed Budget row for every sub-activity. 'Related Budget Line' and 'Approved Budget (EUR/BDT)' show the full budget line total this sub-activity draws on - shared across several sub-activities/rows below; do not sum this column. Example: all 14 sub-activities under R1A4 show the SAME Approved Budget figure (that budget line's full total) - this is intentional, not 14 separate budgets; see Sheet 13 (Budget Tracker) for the actual itemised cost breakdown within each line. PLANNED (by quarter) is a MANUAL numeric entry - FIVDB enters the target number planned for that specific quarter (yellow cells; e.g. 20 learners planned in Q1, 15 in Q2, etc. - not cumulative). ACTUAL (by quarter) is fully AUTOMATIC - the sum of 'Total Participants' (Sheet 10, Activity Data Log) plus 'Total Recipients' (Sheet 11, Distribution Log) logged against this exact Activity/Sub-activity Code within that quarter. No manual entry; recalculates as Sheets 10-11 are populated. % Physical Progress = cumulative ACTUAL up to the current reporting quarter (Sheet 7) / cumulative PLANNED up to the same quarter. RAG Status: On Track >=90%, Slightly Behind 70-89%, Behind <70%. 'Data Log Cross-Check' shows the underlying entry count/average from Sheet 10, for transparency. Output targets, locations and budget categories are indicative planning estimates - to be validated with PIB and FIVDB's detailed budget at inception.
B5: Result | C5: Activity Code | D5: Sub-activity Code | E5: Sub-activity Description | F5: Sub-sub-activity (where applicable) | G5: Process (How Conducted) | H5: Location / Camps | I5: Output Target (indicative) | J5: Linked Indicator(s) | K5: Contribution to Indicator | L5: Target Number | M5: Unit | N5: PLANNED (by quarter) - FIVDB manual target number | V5: ACTUAL (by quarter) - auto total from Sheets 10-11 | AD5: % Physical Progress (auto) | AE5: RAG Status | AF5: Budget Category (indicative) | AG5: Related Budget Line (see Sheet 13) | AH5: Approved Budget (EUR, full line) | AI5: Approved Budget (BDT, full line) | AJ5: Data Log Cross-Check (Sheet 10, latest entry) | AK5: How to Articulate in Narrative Report | AL5: Means of Verification | AM5: Source Reference | AN5: Responsible | AO5: Comments
N6: Q1 | O6: Q2 | P6: Q3 | Q6: Q4 | R6: Q5 | S6: Q6 | T6: Q7 | U6: Q8 | V6: Q1 | W6: Q2 | X6: Q3 | Y6: Q4 | Z6: Q5 | AA6: Q6 | AB6: Q7 | AC6: Q8
B7: R1A1 - Identification, Assessment & Placement of Out-of-School/Dropout Children (Budget Ref R1A1, BDT 40,000 / EUR 279.72)
